Workbook
Name Month: [3]Data!$F:$F
Name Period: [3]Data!$C:$C
Name Product: [3]Data!$D:$D
Name Sales: [3]Data!$E:$E
Name Version: [3]Data!$B:$B
Name Year: [3]Data!$A:$A

Sheet Introduction
B5: Title | D5: Trend Analysis
A7: Navigation | B7: Content | D7: This file enables you to perform a detailed trend and variance analysis using statistical methods provided by Microsoft Excel
A8: Mapping | D8: With the integrated drop-down lists, you can easily navigate across months to analyze performance.
A9: Bridges for Trends | D9: Everything is set up already - all you need to do is bring in your data (sales and units)
D10: In addition, the template features a view on Month-to-Date (MTD) and Year-to-Date (YTD) results. The difference is explained below:
A11: Sales Data
A12: Units sold | D12: MTD: Refers to a single month (e.g. Oct MTD = the results of October only)
D13: YTD: Refers to the results of the entire year up to the selected month (e.g. Oct YTD = Jan + Feb + Mar + ... + Oct)
A14: Summary
B15: Customization difficulty (1-3) | D15: 2
A16: Chairs
A17: Tables | B17: Explanation of sheets | C17: Mapping: | D17: You can adjust all cells colored in green, which will then translate into the various drop-down lists across the file. You can also adjust the conversion factor (such as showing numbers in thousands, millions, etc.)
A18: Kitchen | C18: Sales Data & Units sold: | D18: This sheet contains the prepopulated data, Actuals are available until July YTD to provide a realistic picture of a business situation (middle of the year, still some months to go). Make sure to copy-paste your data into the right columns, and don't change the order of the cells.
A19: Accessories | C19: Bridges for Trends: | D19: Do not change this sheet. It is set up to automatically calculate the trend bridges needed for the statistical extrapolation in your various sheets.
C20: Summary: | D20: Select the month, and you are good to go! All kinds of different analyses, showing MTD, YTD and FY Performance, as well as variances.
C21: Individual Analysis sheets: | D21: Get the maximum level of detail for your product portfolio, showing trends, historical analyses, visualizations, and much more!
B23: How to customize | C23: 1) | D23: Ensure that the regional settings of your computer align with the "Months" in D:D on the sheet "Mapping" and update columns A:A and B:B for your particular data
C24: 2) | D24: On the data tabs "Sales Data" and "Units sold", bring in all relevant data in the green columns. Make sure the months in column B:B align with your mapping tab, and that they follow the same setup (e.g. "Jan 2020")
C25: 3) | D25: If your data set only allows for one version, copy-paste the data into both the "Budget" and "Actuals" column.
C26: 4) | D26: If needed, check out the video in which I walk you through each and every step!
C27: 5) | D27: Depending on the number of products you want to include in your file, simply copy-paste one of the invididual analysis sheets and change the product in cell E2.
C28: 6) | D28: For a detailed walkthrough, check out the attached video!

Sheet Mapping
A1: Products | B1: Version | C1: Conversion Factor | D1: Months
A2: Tables | B2: Actual | C2: 1000 | D2: Jan
A3: Kitchen | B3: Budget | D3: Feb
A4: Chairs | D4: Mar
A5: Accessories | D5: Apr
A6: Placeholder 1 | D6: May
A7: Placeholder 2 | D7: Jun
A8: Placeholder 3 | D8: Jul
A9: Placeholder 4 | D9: Aug
A10: Placeholder 5 | D10: Sep
A11: Placeholder 6 | D11: Oct
A12: Placeholder 7 | D12: Nov
A13: Placeholder 8 | D13: Dec
A14: Placeholder 9
A15: Placeholder 10
A16: Placeholder 11
A17: Placeholder 12
A18: Placeholder 13
A19: Placeholder 14

Sheet Bridges for Trends
A3: Current Month | B3: -1 | C3: -2 | D3: -3 | E3: -4 | F3: -5 | G3: -6 | H3: -7 | I3: -8 | J3: -9 | K3: -10 | L3: -11 | M3: -12 | N3: -13 | O3: -14 | P3: -15 | Q3: -16 | R3: -17 | S3: -18 | T3: -19 | U3: -20 | V3: -21 | W3: -22 | X3: -23 | Y3: -24
A4: ="Jan "&Summary!$C$2 -> Jan 2020 | B4: ="Dec "&Summary!$C$2-1 -> Dec 2019 | C4: ="Nov "&Summary!$C$2-1 -> Nov 2019 | D4: ="Oct "&Summary!$C$2-1 -> Oct 2019 | E4: ="Sep "&Summary!$C$2-1 -> Sep 2019 | F4: ="Aug "&Summary!$C$2-1 -> Aug 2019 | G4: ="Jul "&Summary!$C$2-1 -> Jul 2019 | H4: ="Jun "&Summary!$C$2-1 -> Jun 2019 | I4: ="May "&Summary!$C$2-1 -> May 2019 | J4: ="Apr "&Summary!$C$2-1 -> Apr 2019 | K4: ="Mar "&Summary!$C$2-1 -> Mar 2019 | L4: ="Feb "&Summary!$C$2-1 -> Feb 2019 | M4: ="Jan "&Summary!$C$2-1 -> Jan 2019 | N4: ="Dec "&Summary!$C$2-2 -> Dec 2018 | O4: ="Nov "&Summary!$C$2-2 -> Nov 2018 | P4: ="Oct "&Summary!$C$2-2 -> Oct 2018 | Q4: ="Sep "&Summary!$C$2-2 -> Sep 2018 | R4: ="Aug "&Summary!$C$2-2 -> Aug 2018 | S4: ="Jul "&Summary!$C$2-2 -> Jul 2018 | T4: ="Jun "&Summary!$C$2-2 -> Jun 2018 | U4: ="May "&Summary!$C$2-2 -> May 2018 | V4: ="Apr "&Summary!$C$2-2 -> Apr 2018 | W4: ="Mar "&Summary!$C$2-2 -> Mar 2018 | X4: ="Feb "&Summary!$C$2-2 -> Feb 2018 | Y4: ="Jan "&Summary!$C$2-2 -> Jan 2018
A5: ="Feb "&Summary!$C$2 -> Feb 2020 | B5: ="Jan "&Summary!$C$2 -> Jan 2020 | C5: ="Dec "&Summary!$C$2-1 -> Dec 2019 | D5: ="Nov "&Summary!$C$2-1 -> Nov 2019 | E5: Oct 2019 | F5: Sep 2019 | G5: Aug 2019 | H5: Jul 2019 | I5: ="Jun "&Summary!$C$2-1 -> Jun 2019 | J5: ="May "&Summary!$C$2-1 -> May 2019 | K5: ="Apr "&Summary!$C$2-1 -> Apr 2019 | L5: ="Mar "&Summary!$C$2-1 -> Mar 2019 | M5: ="Feb "&Summary!$C$2-1 -> Feb 2019 | N5: ="Jan "&Summary!$C$2-1 -> Jan 2019 | O5: Dec 2018 | P5: Nov 2018 | Q5: Oct 2018 | R5: Sep 2018 | S5: Aug 2018 | T5: Jul 2018 | U5: Jun 2018 | V5: May 2018 | W5: Apr 2018 | X5: Mar 2018 | Y5: Feb 2018
A6: ="Mar "&Summary!$C$2 -> Mar 2020 | B6: ="Feb "&Summary!$C$2 -> Feb 2020 | C6: ="Jan "&Summary!$C$2 -> Jan 2020 | D6: ="Dec "&Summary!$C$2-1 -> Dec 2019 | E6: Nov 2019 | F6: Oct 2019 | G6: Sep 2019 | H6: Aug 2019 | I6: Jul 2019 | J6: ="Jun "&Summary!$C$2-1 -> Jun 2019 | K6: ="May "&Summary!$C$2-1 -> May 2019 | L6: ="Apr "&Summary!$C$2-1 -> Apr 2019 | M6: ="Mar "&Summary!$C$2-1 -> Mar 2019 | N6: ="Feb "&Summary!$C$2-1 -> Feb 2019 | O6: Jan 2019 | P6: Dec 2018 | Q6: Nov 2018 | R6: Oct 2018 | S6: Sep 2018 | T6: Aug 2018 | U6: Jul 2018 | V6: Jun 2018 | W6: May 2018 | X6: Apr 2018 | Y6: Mar 2018
A7: ="Apr "&Summary!$C$2 -> Apr 2020 | B7: ="Mar "&Summary!$C$2 -> Mar 2020 | C7: ="Feb "&Summary!$C$2 -> Feb 2020 | D7: ="Jan "&Summary!$C$2 -> Jan 2020 | E7: Dec 2019 | F7: Nov 2019 | G7: Oct 2019 | H7: Sep 2019 | I7: Aug 2019 | J7: Jul 2019 | K7: ="Jun "&Summary!$C$2-1 -> Jun 2019 | L7: ="May "&Summary!$C$2-1 -> May 2019 | M7: ="Apr "&Summary!$C$2-1 -> Apr 2019 | N7: ="Mar "&Summary!$C$2-1 -> Mar 2019 | O7: Feb 2019 | P7: Jan 2019 | Q7: Dec 2018 | R7: Nov 2018 | S7: Oct 2018 | T7: Sep 2018 | U7: Aug 2018 | V7: Jul 2018 | W7: Jun 2018 | X7: May 2018 | Y7: Apr 2018
A8: ="May "&Summary!$C$2 -> May 2020 | B8: ="Apr "&Summary!$C$2 -> Apr 2020 | C8: ="Mar "&Summary!$C$2 -> Mar 2020 | D8: ="Feb "&Summary!$C$2 -> Feb 2020 | E8: Jan 2020 | F8: Dec 2019 | G8: Nov 2019 | H8: Oct 2019 | I8: Sep 2019 | J8: Aug 2019 | K8: Jul 2019 | L8: ="Jun "&Summary!$C$2-1 -> Jun 2019 | M8: ="May "&Summary!$C$2-1 -> May 2019 | N8: ="Apr "&Summary!$C$2-1 -> Apr 2019 | O8: Mar 2019 | P8: Feb 2019 | Q8: Jan 2019 | R8: Dec 2018 | S8: Nov 2018 | T8: Oct 2018 | U8: Sep 2018 | V8: Aug 2018 | W8: Jul 2018 | X8: Jun 2018 | Y8: May 2018
A9: ="Jun "&Summary!$C$2 -> Jun 2020 | B9: ="May "&Summary!$C$2 -> May 2020 | C9: ="Apr "&Summary!$C$2 -> Apr 2020 | D9: ="Mar "&Summary!$C$2 -> Mar 2020 | E9: Feb 2020 | F9: Jan 2020 | G9: Dec 2019 | H9: Nov 2019 | I9: Oct 2019 | J9: Sep 2019 | K9: Aug 2019 | L9: Jul 2019 | M9: ="Jun "&Summary!$C$2-1 -> Jun 2019 | N9: ="May "&Summary!$C$2-1 -> May 2019 | O9: Apr 2019 | P9: Mar 2019 | Q9: Feb 2019 | R9: Jan 2019 | S9: Dec 2018 | T9: Nov 2018 | U9: Oct 2018 | V9: Sep 2018 | W9: Aug 2018 | X9: Jul 2018 | Y9: Jun 2018
A10: ="Jul "&Summary!$C$2 -> Jul 2020 | B10: ="Jun "&Summary!$C$2 -> Jun 2020 | C10: ="May "&Summary!$C$2 -> May 2020 | D10: ="Apr "&Summary!$C$2 -> Apr 2020 | E10: Mar 2020 | F10: Feb 2020 | G10: Jan 2020 | H10: Dec 2019 | I10: Nov 2019 | J10: Oct 2019 | K10: Sep 2019 | L10: Aug 2019 | M10: Jul 2019 | N10: ="Jun "&Summary!$C$2-1 -> Jun 2019 | O10: May 2019 | P10: Apr 2019 | Q10: Mar 2019 | R10: Feb 2019 | S10: Jan 2019 | T10: Dec 2018 | U10: Nov 2018 | V10: Oct 2018 | W10: Sep 2018 | X10: Aug 2018 | Y10: Jul 2018
A11: ="Aug "&Summary!$C$2 -> Aug 2020 | B11: ="Jul "&Summary!$C$2 -> Jul 2020 | C11: ="Jun "&Summary!$C$2 -> Jun 2020 | D11: ="May "&Summary!$C$2 -> May 2020 | E11: Apr 2020 | F11: Mar 2020 | G11: Feb 2020 | H11: Jan 2020 | I11: Dec 2019 | J11: Nov 2019 | K11: Oct 2019 | L11: Sep 2019 | M11: Aug 2019 | N11: Jul 2019 | O11: Jun 2019 | P11: May 2019 | Q11: Apr 2019 | R11: Mar 2019 | S11: Feb 2019 | T11: Jan 2019 | U11: Dec 2018 | V11: Nov 2018 | W11: Oct 2018 | X11: Sep 2018 | Y11: Aug 2018
A12: ="Sep "&Summary!$C$2 -> Sep 2020 | B12: ="Aug "&Summary!$C$2 -> Aug 2020 | C12: ="Jul "&Summary!$C$2 -> Jul 2020 | D12: ="Jun "&Summary!$C$2 -> Jun 2020 | E12: May 2020 | F12: Apr 2020 | G12: Mar 2020 | H12: Feb 2020 | I12: Jan 2020 | J12: Dec 2019 | K12: Nov 2019 | L12: Oct 2019 | M12: Sep 2019 | N12: Aug 2019 | O12: Jul 2019 | P12: Jun 2019 | Q12: May 2019 | R12: Apr 2019 | S12: Mar 2019 | T12: Feb 2019 | U12: Jan 2019 | V12: Dec 2018 | W12: Nov 2018 | X12: Oct 2018 | Y12: Sep 2018
A13: ="Oct "&Summary!$C$2 -> Oct 2020 | B13: ="Sep "&Summary!$C$2 -> Sep 2020 | C13: ="Aug "&Summary!$C$2 -> Aug 2020 | D13: ="Jul "&Summary!$C$2 -> Jul 2020 | E13: Jun 2020 | F13: May 2020 | G13: Apr 2020 | H13: Mar 2020 | I13: Feb 2020 | J13: Jan 2020 | K13: Dec 2019 | L13: Nov 2019 | M13: Oct 2019 | N13: Sep 2019 | O13: Aug 2019 | P13: Jul 2019 | Q13: Jun 2019 | R13: May 2019 | S13: Apr 2019 | T13: Mar 2019 | U13: Feb 2019 | V13: Jan 2019 | W13: Dec 2018 | X13: Nov 2018 | Y13: Oct 2018
A14: ="Nov "&Summary!$C$2 -> Nov 2020 | B14: ="Oct "&Summary!$C$2 -> Oct 2020 | C14: ="Sep "&Summary!$C$2 -> Sep 2020 | D14: ="Aug "&Summary!$C$2 -> Aug 2020 | E14: Jul 2020 | F14: Jun 2020 | G14: May 2020 | H14: Apr 2020 | I14: Mar 2020 | J14: Feb 2020 | K14: Jan 2020 | L14: Dec 2019 | M14: Nov 2019 | N14: Oct 2019 | O14: Sep 2019 | P14: Aug 2019 | Q14: Jul 2019 | R14: Jun 2019 | S14: May 2019 | T14: Apr 2019 | U14: Mar 2019 | V14: Feb 2019 | W14: Jan 2019 | X14: Dec 2018 | Y14: Nov 2018
A15: ="Dec "&Summary!$C$2 -> Dec 2020 | B15: ="Nov "&Summary!$C$2 -> Nov 2020 | C15: ="Oct "&Summary!$C$2 -> Oct 2020 | D15: ="Sep "&Summary!$C$2 -> Sep 2020 | E15: Aug 2020 | F15: Jul 2020 | G15: Jun 2020 | H15: May 2020 | I15: Apr 2020 | J15: Mar 2020 | K15: Feb 2020 | L15: Jan 2020 | M15: Dec 2019 | N15: Nov 2019 | O15: Oct 2019 | P15: Sep 2019 | Q15: Aug 2019 | R15: Jul 2019 | S15: Jun 2019 | T15: May 2019 | U15: Apr 2019 | V15: Mar 2019 | W15: Feb 2019 | X15: Jan 2019 | Y15: Dec 2018

Sheet Sales Data
A1: Product | B1: Time | C1: Measure | D1: =Mapping!B3 -> Budget | E1: =Mapping!B2 -> Actual | F1: Year | G1: Period
A2: Chairs | B2: Apr 2018 | C2: Periodic | D2: 0 | E2: 207079.93 | F2: =YEAR(B2) -> 2018 | G2: =MONTH(DATEVALUE(LEFT(B2,3)&"1")) -> 4
A3: Accessories | B3: Apr 2018 | C3: Periodic | D3: 1397148.3 | E3: 1527716.3 | F3: =YEAR(B3) -> 2018 | G3: =MONTH(DATEVALUE(LEFT(B3,3)&"1")) -> 4
A4: Kitchen | B4: Apr 2018 | C4: Periodic | D4: 0 | E4: 50651.194 | F4: =YEAR(B4) -> 2018 | G4: =MONTH(DATEVALUE(LEFT(B4,3)&"1")) -> 4
A5: Tables | B5: Apr 2018 | C5: Periodic | D5: 248821.32 | E5: 334043.49 | F5: =YEAR(B5) -> 2018 | G5: =MONTH(DATEVALUE(LEFT(B5,3)&"1")) -> 4
A6: Chairs | B6: May 2019 | C6: Periodic | D6: 244543.69 | E6: 370877.74 | F6: =YEAR(B6) -> 2019 | G6: =MONTH(DATEVALUE(LEFT(B6,3)&"1")) -> 5
A7: Accessories | B7: May 2019 | C7: Periodic | D7: 1814704 | E7: 1970303.9 | F7: =YEAR(B7) -> 2019 | G7: =MONTH(DATEVALUE(LEFT(B7,3)&"1")) -> 5
A8: Kitchen | B8: May 2019 | C8: Periodic | D8: 103896.2 | E8: 99382.012 | F8: =YEAR(B8) -> 2019 | G8: =MONTH(DATEVALUE(LEFT(B8,3)&"1")) -> 5
A9: Tables | B9: May 2019 | C9: Periodic | D9: 444389.1 | E9: 473905.04 | F9: =YEAR(B9) -> 2019 | G9: =MONTH(DATEVALUE(LEFT(B9,3)&"1")) -> 5
A10: Chairs | B10: Apr 2020 | C10: Periodic | D10: 314809.77 | E10: 268370.6 | F10: =YEAR(B10) -> 2020 | G10: =MONTH(DATEVALUE(LEFT(B10,3)&"1")) -> 4
A11: Accessories | B11: Apr 2020 | C11: Periodic | D11: 2263168.4 | E11: 1927719.7 | F11: =YEAR(B11) -> 2020 | G11: =MONTH(DATEVALUE(LEFT(B11,3)&"1")) -> 4
A12: Kitchen | B12: Apr 2020 | C12: Periodic | D12: 311976.86 | E12: 206040.26 | F12: =YEAR(B12) -> 2020 | G12: =MONTH(DATEVALUE(LEFT(B12,3)&"1")) -> 4
A13: Tables | B13: Apr 2020 | C13: Periodic | D13: 523327.32 | E13: 309662.81 | F13: =YEAR(B13) -> 2020 | G13: =MONTH(DATEVALUE(LEFT(B13,3)&"1")) -> 4
... A145: Tables | B145: Sep 2020 | C145: Periodic | D145: 456199.94 | E145: 0 | F145: =YEAR(B145) -> 2020 | G145: =MONTH(DATEVALUE(LEFT(B145,3)&"1")) -> 9

Sheet Units sold
A1: Product | B1: Time | C1: Measure | D1: =Mapping!B3 -> Budget | E1: =Mapping!B2 -> Actual
A2: Chairs | B2: Apr 2018 | C2: Periodic | D2: 0 | E2: 0
A3: Chairs | B3: Apr 2018 | C3: Periodic | D3: 0 | E3: 0
A4: Chairs | B4: Apr 2018 | C4: Periodic | D4: 0 | E4: 46
A5: Chairs | B5: Apr 2018 | C5: Periodic | D5: 0 | E5: 12
A6: Accessories | B6: Apr 2018 | C6: Periodic | D6: 0 | E6: 0
A7: Accessories | B7: Apr 2018 | C7: Periodic | D7: 0 | E7: 0
A8: Accessories | B8: Apr 2018 | C8: Periodic | D8: 0 | E8: 0
A9: Accessories | B9: Apr 2018 | C9: Periodic | D9: 0 | E9: 0
A10: Accessories | B10: Apr 2018 | C10: Periodic | D10: 0 | E10: 0
A11: Accessories | B11: Apr 2018 | C11: Periodic | D11: 0 | E11: 0
A12: Accessories | B12: Apr 2018 | C12: Periodic | D12: 0 | E12: 198
A13: Accessories | B13: Apr 2018 | C13: Periodic | D13: 0 | E13: 300
... A1153: Tables | B1153: Sep 2020 | C1153: Periodic | D1153: 0 | E1153: 0

Sheet Summary
C1: Header | D1: YTD | E1: YTG | BG1: =MONTH(DATEVALUE(LEFT(BG6,3)&"1")) -> 8 | BH1: =MONTH(DATEVALUE(LEFT(BH6,3)&"1")) -> 9 | BI1: =MONTH(DATEVALUE(LEFT(BI6,3)&"1")) -> 10 | BJ1: =MONTH(DATEVALUE(LEFT(BJ6,3)&"1")) -> 11 | BK1: =MONTH(DATEVALUE(LEFT(BK6,3)&"1")) -> 12 | BL1: =MONTH(DATEVALUE(LEFT(BL6,3)&"1")) -> 1 | BM1: =MONTH(DATEVALUE(LEFT(BM6,3)&"1")) -> 2 | BN1: =MONTH(DATEVALUE(LEFT(BN6,3)&"1")) -> 3 | ... BR1: =MONTH(DATEVALUE(LEFT(BR6,3)&"1")) -> 7 | BT1: 13 | BU1: 14 | BV1: 15 | BW1: 16 | BX1: 17 | BY1: 18 | BZ1: 19 | CA1: 20 | CB1: 21 | CC1: 22 | CD1: 23 | CE1: 24 | CH1: 13 | CI1: 14 | CJ1: 15 | CK1: 16 | CL1: 17 | CM1: 18 | CN1: 19 | CO1: 20 | CP1: 21 | CQ1: 22 | CR1: 23 | CS1: 24
B2: Current Year | C2: 2020
B3: Current Month | C3: Jul | D3: =MONTH(DATEVALUE(C3&"1")) -> 7 | E3: =12-D3 -> 5
BT4: 12-month Trend | CH4: 6-month Trend | CV4: Monthly Average
C5: ="MTD "&$C$3 -> MTD Jul | G5: Variance | L5: ="YTD "&$C$3 -> YTD Jul | P5: Variance | U5: FY | Y5: Variance | AF5: Monthly Average | AJ5: FY Trend Outlook | AS5: ="Act "&Summary!$C$2 -> Act 2020 | CZ5: Performance
B6: =IF(Mapping!$C$2=1000,"Total Sales in kUSD",IF(Mapping!C2=1,"Total Sales in USD",IF(Mapping!C2=1000000,"Total Sales in mUSD","Error"))) -> Total Sales in kUSD | C6: ="Act "&Summary!$C$2-1 -> Act 2019 | D6: =Mapping!$B$3&" "&Summary!$C$2 -> Budget 2020 | E6: ="Act "&Summary!$C$2 -> Act 2020 | G6: Vs PY | I6: Vs BUD | L6: =C6 -> Act 2019 | M6: =D6 -> Budget 2020 | N6: =E6 -> Act 2020 | P6: Vs PY | R6: Vs BUD | U6: =L6 -> Act 2019 | V6: =M6 -> Budget 2020 | W6: ="Act "&Summary!$C$2 -> Act 2020 | Y6: Vs PY | AA6: Vs BUD | AC6: ="vs "&LEFT(#REF!,6) -> #REF! | AF6: YTD | AG6: YTG | AH6: Delta | AJ6: YTD +3m Rolling Rate | AK6: YTD +6m Rolling Rate | AL6: YTD +12m Rolling Rate | AM6: 6-month Trend | AN6: 12-month Trend | AP6: ="YTG "&RIGHT(Summary!$C$2,2)-1 -> YTG 19 | AQ6: ="YTG "&RIGHT(Summary!$C$2,2) -> YTG 20 | AS6: ='Bridges for Trends'!$A$4 -> Jan 2020 | AT6: ='Bridges for Trends'!$A$5 -> Feb 2020 | AU6: ='Bridges for Trends'!$A$6 -> Mar 2020 | AV6: ='Bridges for Trends'!$A$7 -> Apr 2020 | AW6: ='Bridges for Trends'!$A$8 -> May 2020 | AX6: ='Bridges for Trends'!$A$9 -> Jun 2020 | AY6: ='Bridges for Trends'!$A$10 -> Jul 2020 | AZ6: ='Bridges for Trends'!$A$11 -> Aug 2020 | BA6: ='Bridges for Trends'!$A$12 -> Sep 2020 | BB6: ='Bridges for Trends'!$A$13 -> Oct 2020 | BC6: ='Bridges for Trends'!$A$14 -> Nov 2020 | BD6: ='Bridges for Trends'!$A$15 -> Dec 2020 | BE6: FY | BG6: =VLOOKUP($BR6,'Bridges for Trends'!$A:$M,12,FALSE) -> Aug 2019 | BH6: =VLOOKUP($BR6,'Bridges for Trends'!$A:$M,11,FALSE) -> Sep 2019 | BI6: =VLOOKUP($BR6,'Bridges for Trends'!$A:$M,10,FALSE) -> Oct 2019 | BJ6: =VLOOKUP($BR6,'Bridges for Trends'!$A:$M,9,FALSE) -> Nov 2019 | BK6: =VLOOKUP($BR6,'Bridges for Trends'!$A:$M,8,FALSE) -> Dec 2019 | BL6: =VLOOKUP($BR6,'Bridges for Trends'!$A:$M,7,FALSE) -> Jan 2020 | BM6: =VLOOKUP($BR6,'Bridges for Trends'!$A:$M,6,FALSE) -> Feb 2020 | BN6: =VLOOKUP($BR6,'Bridges for Trends'!$A:$M,5,FALSE) -> Mar 2020 | BO6: =VLOOKUP($BR6,'Bridges for Trends'!$A:$M,4,FALSE) -> Apr 2020 | BP6: =VLOOKUP($BR6,'Bridges for Trends'!$A:$M,3,FALSE) -> May 2020 | BQ6: =VLOOKUP($BR6,'Bridges for Trends'!$A:$M,2,FALSE) -> Jun 2020 | BR6: =Summary!$C$3&" "&Summary!$C$2 -> Jul 2020 | BT6: =Mapping!$D$2 -> Jan | BU6: =Mapping!$D$3 -> Feb | BV6: =Mapping!$D$4 -> Mar | BW6: =Mapping!$D$5 -> Apr | BX6: =Mapping!$D$6 -> May | BY6: =Mapping!$D$7 -> Jun | BZ6: =Mapping!$D$8 -> Jul | CA6: =Mapping!$D$9 -> Aug | CB6: =Mapping!$D$10 -> Sep | CC6: =Mapping!$D$11 -> Oct | CD6: =Mapping!$D$12 -> Nov | CE6: =Mapping!$D$13 -> Dec | CF6: FY | CH6: =Mapping!$D$2 -> Jan | CI6: =Mapping!$D$3 -> Feb | CJ6: =Mapping!$D$4 -> Mar | CK6: =Mapping!$D$5 -> Apr | CL6: =Mapping!$D$6 -> May | CM6: =Mapping!$D$7 -> Jun | CN6: =Mapping!$D$8 -> Jul | CO6: =Mapping!$D$9 -> Aug | CP6: =Mapping!$D$10 -> Sep | CQ6: =Mapping!$D$11 -> Oct | CR6: =Mapping!$D$12 -> Nov | CS6: =Mapping!$D$13 -> Dec | CT6: FY | CV6: 3m | CW6: 6m | CX6: 12m | CZ6: YTD +3 month rolling rate | DA6: YTD +6 month rolling rate | DB6: YTD +12 month rolling rate
B7: =Mapping!A2 -> Tables | C7: =SUMIFS('Sales Data'!$E:$E,'Sales Data'!$A:$A,$B7,'Sales Data'!$B:$B,Summary!$C$3&" "&Summary!$C$2-1,'Sales Data'!$C:$C,"Periodic")/Mapping!$C$2 -> 445.98746 | D7: =SUMIFS('Sales Data'!$D:$D,'Sales Data'!$A:$A,$B7,'Sales Data'!$B:$B,Summary!$C$3&" "&Summary!$C$2,'Sales Data'!$C:$C,"Periodic")/Mapping!$C$2 -> 451.00764 | E7: =SUMIFS('Sales Data'!$E:$E,'Sales Data'!$A:$A,$B7,'Sales Data'!$B:$B,Summary!$C$3&" "&Summary!$C$2,'Sales Data'!$C:$C,"Periodic")/Mapping!$C$2 -> 321.86195 | G7: =E7-C7 -> -124.12551 | H7: =IF(ISERROR((E7/C7)-1),"N/A",(E7/C7)-1) -> -0.27831614 | I7: =E7-D7 -> -129.14569 | J7: =IF(ISERROR((E7/D7)-1),"N/A",(E7/D7)-1) -> -0.28634923 | L7: =SUMIFS('Sales Data'!$E:$E,'Sales Data'!$A:$A,$B7,'Sales Data'!$F:$F,$C$2-1,'Sales Data'!$G:$G,"<="&$D$3)/Mapping!$C$2 -> 3292.3216 | M7: =SUMIFS('Sales Data'!$D:$D,'Sales Data'!$A:$A,$B7,'Sales Data'!$F:$F,$C$2,'Sales Data'!$G:$G,"<="&$D$3)/Mapping!$C$2 -> 3514.9751 | N7: =SUMIFS('Sales Data'!$E:$E,'Sales Data'!$A:$A,$B7,'Sales Data'!$F:$F,$C$2,'Sales Data'!$G:$G,"<="&$D$3)/Mapping!$C$2 -> 2793.6432 | P7: =N7-L7 -> -498.67843 | Q7: =IF(ISERROR((N7/L7)-1),"N/A",(N7/L7)-1) -> -0.15146711 | R7: =N7-M7 -> -721.33197 | S7: =IF(ISERROR((N7/M7)-1),"N/A",(N7/M7)-1) -> -0.20521681 | U7: =SUMIFS('Sales Data'!$E:$E,'Sales Data'!$A:$A,$B7,'Sales Data'!$F:$F,$C$2-1,'Sales Data'!$G:$G,"<="&12)/Mapping!$C$2 -> 5941.2575 | V7: =SUMIFS('Sales Data'!$D:$D,'Sales Data'!$A:$A,$B7,'Sales Data'!$F:$F,$C$2,'Sales Data'!$G:$G,"<="&12)/Mapping!$C$2 -> 5937.3393 | W7: =SUMIFS('Sales Data'!$E:$E,'Sales Data'!$A:$A,$B7,'Sales Data'!$F:$F,$C$2,'Sales Data'!$G:$G,"<="&12)/Mapping!$C$2 -> 2793.6432 | Y7: =W7-U7 -> -3147.6143 | Z7: =IF(ISERROR((W7/U7)-1),"N/A",(W7/U7)-1) -> -0.52978924 | AA7: =W7-V7 -> -3143.6962 | AB7: =IF(ISERROR((W7/V7)-1),"N/A",(W7/V7)-1) -> -0.52947895 | AC7: =W7-#REF! -> #REF! | AD7: =IF(ISERROR((W7/#REF!)-1),"N/A",(W7/#REF!)-1) -> N/A | AF7: =N7/Summary!$D$3 -> 399.09188 | AG7: =(V7-N7)/Summary!$E$3 -> 628.73924 | AH7: =AG7-AF7 -> 229.64735 | AJ7: =CZ7-W7 -> 2115.0615 | AK7: =DA7-W7 -> 1954.3023 | AL7: =DB7-W7 -> 2267.7413 | AM7: =CT7-W7 -> 2227.3198 | AN7: =CF7-W7 -> 3456.9441 | AP7: =U7-L7 -> 2648.9359 | AQ7: =V7-N7 -> 3143.6962 | AS7: =SUMIFS('Sales Data'!$E:$E,'Sales Data'!$A:$A,$B7,'Sales Data'!$B:$B,AS$6,'Sales Data'!$C:$C,"Periodic")/Mapping!$C$2 -> 448.48043 | AT7: =SUMIFS('Sales Data'!$E:$E,'Sales Data'!$A:$A,$B7,'Sales Data'!$B:$B,AT$6,'Sales Data'!$C:$C,"Periodic")/Mapping!$C$2 -> 404.02749 | AU7: =SUMIFS('Sales Data'!$E:$E,'Sales Data'!$A:$A,$B7,'Sales Data'!$B:$B,AU$6,'Sales Data'!$C:$C,"Periodic")/Mapping!$C$2 -> 362.43555 | AV7: =SUMIFS('Sales Data'!$E:$E,'Sales Data'!$A:$A,$B7,'Sales Data'!$B:$B,AV$6,'Sales Data'!$C:$C,"Periodic")/Mapping!$C$2 -> 309.66281 | AW7: =SUMIFS('Sales Data'!$E:$E,'Sales Data'!$A:$A,$B7,'Sales Data'!$B:$B,AW$6,'Sales Data'!$C:$C,"Periodic")/Mapping!$C$2 -> 462.2603 | AX7: =SUMIFS('Sales Data'!$E:$E,'Sales Data'!$A:$A,$B7,'Sales Data'!$B:$B,AX$6,'Sales Data'!$C:$C,"Periodic")/Mapping!$C$2 -> 484.91463 | AY7: =SUMIFS('Sales Data'!$E:$E,'Sales Data'!$A:$A,$B7,'Sales Data'!$B:$B,AY$6,'Sales Data'!$C:$C,"Periodic")/Mapping!$C$2 -> 321.86195 | AZ7: =SUMIFS('Sales Data'!$E:$E,'Sales Data'!$A:$A,$B7,'Sales Data'!$B:$B,AZ$6,'Sales Data'!$C:$C,"Periodic")/Mapping!$C$2 -> 0 | ... BD7: =SUMIFS('Sales Data'!$E:$E,'Sales Data'!$A:$A,$B7,'Sales Data'!$B:$B,BD$6,'Sales Data'!$C:$C,"Periodic")/Mapping!$C$2 -> 0 | BE7: =SUM(AS7:BD7) -> 2793.6432 | BG7: =SUMIFS('Sales Data'!$E:$E,'Sales Data'!$A:$A,$B7,'Sales Data'!$B:$B,BG$6,'Sales Data'!$C:$C,"Periodic")/Mapping!$C$2 -> 508.46155 | BH7: =SUMIFS('Sales Data'!$E:$E,'Sales Data'!$A:$A,$B7,'Sales Data'!$B:$B,BH$6,'Sales Data'!$C:$C,"Periodic")/Mapping!$C$2 -> 424.09441 | BI7: =SUMIFS('Sales Data'!$E:$E,'Sales Data'!$A:$A,$B7,'Sales Data'!$B:$B,BI$6,'Sales Data'!$C:$C,"Periodic")/Mapping!$C$2 -> 633.17249 | BJ7: =SUMIFS('Sales Data'!$E:$E,'Sales Data'!$A:$A,$B7,'Sales Data'!$B:$B,BJ$6,'Sales Data'!$C:$C,"Periodic")/Mapping!$C$2 -> 700.03737 | BK7: =SUMIFS('Sales Data'!$E:$E,'Sales Data'!$A:$A,$B7,'Sales Data'!$B:$B,BK$6,'Sales Data'!$C:$C,"Periodic")/Mapping!$C$2 -> 383.17004 | BL7: =SUMIFS('Sales Data'!$E:$E,'Sales Data'!$A:$A,$B7,'Sales Data'!$B:$B,BL$6,'Sales Data'!$C:$C,"Periodic")/Mapping!$C$2 -> 448.48043 | BM7: =SUMIFS('Sales Data'!$E:$E,'Sales Data'!$A:$A,$B7,'Sales Data'!$B:$B,BM$6,'Sales Data'!$C:$C,"Periodic")/Mapping!$C$2 -> 404.02749 | BN7: =SUMIFS('Sales Data'!$E:$E,'Sales Data'!$A:$A,$B7,'Sales Data'!$B:$B,BN$6,'Sales Data'!$C:$C,"Periodic")/Mapping!$C$2 -> 362.43555 | ... BR7: =SUMIFS('Sales Data'!$E:$E,'Sales Data'!$A:$A,$B7,'Sales Data'!$B:$B,BR$6,'Sales Data'!$C:$C,"Periodic")/Mapping!$C$2 -> 321.86195 | BT7: =IFERROR(IF(AS7<>0,AS7,FORECAST(BT$1,$BG7:$BR7,$BG$1:$BR$1)),"") -> 448.48043 | BU7: =IFERROR(IF(AT7<>0,AT7,FORECAST(BU$1,$BG7:$BR7,$BG$1:$BR$1)),"") -> 404.02749 | BV7: =IFERROR(IF(AU7<>0,AU7,FORECAST(BV$1,$BG7:$BR7,$BG$1:$BR$1)),"") -> 362.43555 | BW7: =IFERROR(IF(AV7<>0,AV7,FORECAST(BW$1,$BG7:$BR7,$BG$1:$BR$1)),"") -> 309.66281 | BX7: =IFERROR(IF(AW7<>0,AW7,FORECAST(BX$1,$BG7:$BR7,$BG$1:$BR$1)),"") -> 462.2603 | BY7: =IFERROR(IF(AX7<>0,AX7,FORECAST(BY$1,$BG7:$BR7,$BG$1:$BR$1)),"") -> 484.91463 | BZ7: =IFERROR(IF(AY7<>0,AY7,FORECAST(BZ$1,$BG7:$BR7,$BG$1:$BR$1)),"") -> 321.86195 | CA7: =IFERROR(IF(AZ7<>0,AZ7,FORECAST(CA$1,$BG7:$BR7,$BG$1:$BR$1)),"") -> 660.69972 | ... CE7: =IFERROR(IF(BD7<>0,BD7,FORECAST(CE$1,$BG7:$BR7,$BG$1:$BR$1)),"") -> 722.07793 | CF7: =SUM(BT7:CE7) -> 6250.5873 | CH7: =IFERROR(IF(AS7<>0,AS7,FORECAST(CH$1,$BM7:$BR7,$BM$1:$BR$1)),"") -> 448.48043 | CI7: =IFERROR(IF(AT7<>0,AT7,FORECAST(CI$1,$BM7:$BR7,$BM$1:$BR$1)),"") -> 404.02749 | CJ7: =IFERROR(IF(AU7<>0,AU7,FORECAST(CJ$1,$BM7:$BR7,$BM$1:$BR$1)),"") -> 362.43555 | CK7: =IFERROR(IF(AV7<>0,AV7,FORECAST(CK$1,$BM7:$BR7,$BM$1:$BR$1)),"") -> 309.66281 | CL7: =IFERROR(IF(AW7<>0,AW7,FORECAST(CL$1,$BM7:$BR7,$BM$1:$BR$1)),"") -> 462.2603 | CM7: =IFERROR(IF(AX7<>0,AX7,FORECAST(CM$1,$BM7:$BR7,$BM$1:$BR$1)),"") -> 484.91463 | CN7: =IFERROR(IF(AY7<>0,AY7,FORECAST(CN$1,$BM7:$BR7,$BM$1:$BR$1)),"") -> 321.86195 | CO7: =IFERROR(IF(AZ7<>0,AZ7,FORECAST(CO$1,$BM7:$BR7,$BM$1:$BR$1)),"") -> 439.22356 | ... CS7: =IFERROR(IF(BD7<>0,BD7,FORECAST(CS$1,$BM7:$BR7,$BM$1:$BR$1)),"") -> 451.70436 | CT7: =SUM(CH7:CS7) -> 5020.963 | CV7: =SUM(BP7:BR7)/3 -> 423.01229 | CW7: =SUM(BM7:BR7)/6 -> 390.86046 | CX7: =SUM(BG7:BR7)/12 -> 453.54825 | CZ7: =N7+Summary!$E$3*CV7 -> 4908.7046 | DA7: =N7+CW7*Summary!$E$3 -> 4747.9455 | DB7: =N7+CX7*Summary!$E$3 -> 5061.3844
B8: =Mapping!A3 -> Kitchen | C8: =SUMIFS('Sales Data'!$E:$E,'Sales Data'!$A:$A,$B8,'Sales Data'!$B:$B,Summary!$C$3&" "&Summary!$C$2-1,'Sales Data'!$C:$C,"Periodic")/Mapping!$C$2 -> 141.73288 | D8: =SUMIFS('Sales Data'!$D:$D,'Sales Data'!$A:$A,$B8,'Sales Data'!$B:$B,Summary!$C$3&" "&Summary!$C$2,'Sales Data'!$C:$C,"Periodic")/Mapping!$C$2 -> 417.69261 | E8: =SUMIFS('Sales Data'!$E:$E,'Sales Data'!$A:$A,$B8,'Sales Data'!$B:$B,Summary!$C$3&" "&Summary!$C$2,'Sales Data'!$C:$C,"Periodic")/Mapping!$C$2 -> 294.97234 | G8: =E8-C8 -> 153.23947 | H8: =IF(ISERROR((E8/C8)-1),"N/A",(E8/C8)-1) -> 1.081185 | I8: =E8-D8 -> -122.72026 | J8: =IF(ISERROR((E8/D8)-1),"N/A",(E8/D8)-1) -> -0.2938052 | L8: =SUMIFS('Sales Data'!$E:$E,'Sales Data'!$A:$A,$B8,'Sales Data'!$F:$F,$C$2-1,'Sales Data'!$G:$G,"<="&$D$3)/Mapping!$C$2 -> 754.79524 | M8: =SUMIFS('Sales Data'!$D:$D,'Sales Data'!$A:$A,$B8,'Sales Data'!$F:$F,$C$2,'Sales Data'!$G:$G,"<="&$D$3)/Mapping!$C$2 -> 2282.5057 | N8: =SUMIFS('Sales Data'!$E:$E,'Sales Data'!$A:$A,$B8,'Sales Data'!$F:$F,$C$2,'Sales Data'!$G:$G,"<="&$D$3)/Mapping!$C$2 -> 1731.7656 | P8: =N8-L8 -> 976.9704 | Q8: =IF(ISERROR((N8/L8)-1),"N/A",(N8/L8)-1) -> 1.2943516 | R8: =N8-M8 -> -550.74001 | S8: =IF(ISERROR((N8/M8)-1),"N/A",(N8/M8)-1) -> -0.24128747 | U8: =SUMIFS('Sales Data'!$E:$E,'Sales Data'!$A:$A,$B8,'Sales Data'!$F:$F,$C$2-1,'Sales Data'!$G:$G,"<="&12)/Mapping!$C$2 -> 1792.1636 | V8: =SUMIFS('Sales Data'!$D:$D,'Sales Data'!$A:$A,$B8,'Sales Data'!$F:$F,$C$2,'Sales Data'!$G:$G,"<="&12)/Mapping!$C$2 -> 4921.3566 | W8: =SUMIFS('Sales Data'!$E:$E,'Sales Data'!$A:$A,$B8,'Sales Data'!$F:$F,$C$2,'Sales Data'!$G:$G,"<="&12)/Mapping!$C$2 -> 1731.7656 | Y8: =W8-U8 -> -60.397989 | Z8: =IF(ISERROR((W8/U8)-1),"N/A",(W8/U8)-1) -> -0.033701158 | AA8: =W8-V8 -> -3189.5909 | AB8: =IF(ISERROR((W8/V8)-1),"N/A",(W8/V8)-1) -> -0.64811214 | AC8: =W8-#REF! -> #REF! | AD8: =IF(ISERROR((W8/#REF!)-1),"N/A",(W8/#REF!)-1) -> N/A | AF8: =N8/Summary!$D$3 -> 247.39509 | AG8: =(V8-N8)/Summary!$E$3 -> 637.91818 | AH8: =AG8-AF8 -> 390.52309 | AJ8: =CZ8-V8 -> -1874.2471 | AK8: =DA8-V8 -> -1926.1317 | AL8: =DB8-V8 -> -2035.7851 | AM8: =CT8-V8 -> -1246.7198 | AN8: =CF8-V8 -> -2178.5762 | AP8: =U8-L8 -> 1037.3684 | AQ8: =V8-N8 -> 3189.5909 | AS8: =SUMIFS('Sales Data'!$E:$E,'Sales Data'!$A:$A,$B8,'Sales Data'!$B:$B,AS$6,'Sales Data'!$C:$C,"Periodic")/Mapping!$C$2 -> 215.61462 | AT8: =SUMIFS('Sales Data'!$E:$E,'Sales Data'!$A:$A,$B8,'Sales Data'!$B:$B,AT$6,'Sales Data'!$C:$C,"Periodic")/Mapping!$C$2 -> 214.22627 | AU8: =SUMIFS('Sales Data'!$E:$E,'Sales Data'!$A:$A,$B8,'Sales Data'!$B:$B,AU$6,'Sales Data'!$C:$C,"Periodic")/Mapping!$C$2 -> 306.67823 | AV8: =SUMIFS('Sales Data'!$E:$E,'Sales Data'!$A:$A,$B8,'Sales Data'!$B:$B,AV$6,'Sales Data'!$C:$C,"Periodic")/Mapping!$C$2 -> 206.04026 | AW8: =SUMIFS('Sales Data'!$E:$E,'Sales Data'!$A:$A,$B8,'Sales Data'!$B:$B,AW$6,'Sales Data'!$C:$C,"Periodic")/Mapping!$C$2 -> 244.29622 | AX8: =SUMIFS('Sales Data'!$E:$E,'Sales Data'!$A:$A,$B8,'Sales Data'!$B:$B,AX$6,'Sales Data'!$C:$C,"Periodic")/Mapping!$C$2 -> 249.9377 | AY8: =SUMIFS('Sales Data'!$E:$E,'Sales Data'!$A:$A,$B8,'Sales Data'!$B:$B,AY$6,'Sales Data'!$C:$C,"Periodic")/Mapping!$C$2 -> 294.97234 | AZ8: =SUMIFS('Sales Data'!$E:$E,'Sales Data'!$A:$A,$B8,'Sales Data'!$B:$B,AZ$6,'Sales Data'!$C:$C,"Periodic")/Mapping!$C$2 -> 0 | ... BD8: =SUMIFS('Sales Data'!$E:$E,'Sales Data'!$A:$A,$B8,'Sales Data'!$B:$B,BD$6,'Sales Data'!$C:$C,"Periodic")/Mapping!$C$2 -> 0 | BE8: =SUM(AS8:BD8) -> 1731.7656 | BG8: =SUMIFS('Sales Data'!$E:$E,'Sales Data'!$A:$A,$B8,'Sales Data'!$B:$B,BG$6,'Sales Data'!$C:$C,"Periodic")/Mapping!$C$2 -> 171.96272 | BH8: =SUMIFS('Sales Data'!$E:$E,'Sales Data'!$A:$A,$B8,'Sales Data'!$B:$B,BH$6,'Sales Data'!$C:$C,"Periodic")/Mapping!$C$2 -> 171.63258 | BI8: =SUMIFS('Sales Data'!$E:$E,'Sales Data'!$A:$A,$B8,'Sales Data'!$B:$B,BI$6,'Sales Data'!$C:$C,"Periodic")/Mapping!$C$2 -> 212.70068 | BJ8: =SUMIFS('Sales Data'!$E:$E,'Sales Data'!$A:$A,$B8,'Sales Data'!$B:$B,BJ$6,'Sales Data'!$C:$C,"Periodic")/Mapping!$C$2 -> 258.54867 | BK8: =SUMIFS('Sales Data'!$E:$E,'Sales Data'!$A:$A,$B8,'Sales Data'!$B:$B,BK$6,'Sales Data'!$C:$C,"Periodic")/Mapping!$C$2 -> 222.52373 | BL8: =SUMIFS('Sales Data'!$E:$E,'Sales Data'!$A:$A,$B8,'Sales Data'!$B:$B,BL$6,'Sales Data'!$C:$C,"Periodic")/Mapping!$C$2 -> 215.61462 | BM8: =SUMIFS('Sales Data'!$E:$E,'Sales Data'!$A:$A,$B8,'Sales Data'!$B:$B,BM$6,'Sales Data'!$C:$C,"Periodic")/Mapping!$C$2 -> 214.22627 | BN8: =SUMIFS('Sales Data'!$E:$E,'Sales Data'!$A:$A,$B8,'Sales Data'!$B:$B,BN$6,'Sales Data'!$C:$C,"Periodic")/Mapping!$C$2 -> 306.67823 | ... BR8: =SUMIFS('Sales Data'!$E:$E,'Sales Data'!$A:$A,$B8,'Sales Data'!$B:$B,BR$6,'Sales Data'!$C:$C,"Periodic")/Mapping!$C$2 -> 294.97234 | BT8: =IFERROR(IF(AS8<>0,AS8,FORECAST(BT$1,$BG8:$BR8,$BG$1:$BR$1)),"") -> 215.61462 | BU8: =IFERROR(IF(AT8<>0,AT8,FORECAST(BU$1,$BG8:$BR8,$BG$1:$BR$1)),"") -> 214.22627 | BV8: =IFERROR(IF(AU8<>0,AU8,FORECAST(BV$1,$BG8:$BR8,$BG$1:$BR$1)),"") -> 306.67823 | BW8: =IFERROR(IF(AV8<>0,AV8,FORECAST(BW$1,$BG8:$BR8,$BG$1:$BR$1)),"") -> 206.04026 | BX8: =IFERROR(IF(AW8<>0,AW8,FORECAST(BX$1,$BG8:$BR8,$BG$1:$BR$1)),"") -> 244.29622 | BY8: =IFERROR(IF(AX8<>0,AX8,FORECAST(BY$1,$BG8:$BR8,$BG$1:$BR$1)),"") -> 249.9377 | BZ8: =IFERROR(IF(AY8<>0,AY8,FORECAST(BZ$1,$BG8:$BR8,$BG$1:$BR$1)),"") -> 294.97234 | CA8: =IFERROR(IF(AZ8<>0,AZ8,FORECAST(CA$1,$BG8:$BR8,$BG$1:$BR$1)),"") -> 205.88788 | ... CE8: =IFERROR(IF(BD8<>0,BD8,FORECAST(CE$1,$BG8:$BR8,$BG$1:$BR$1)),"") -> 198.51802 | CF8: =SUM(BT8:CE8) -> 2742.7804 | CH8: =IFERROR(IF(AS8<>0,AS8,FORECAST(CH$1,$BM8:$BR8,$BM$1:$BR$1)),"") -> 215.61462 | CI8: =IFERROR(IF(AT8<>0,AT8,FORECAST(CI$1,$BM8:$BR8,$BM$1:$BR$1)),"") -> 214.22627 | CJ8: =IFERROR(IF(AU8<>0,AU8,FORECAST(CJ$1,$BM8:$BR8,$BM$1:$BR$1)),"") -> 306.67823 | CK8: =IFERROR(IF(AV8<>0,AV8,FORECAST(CK$1,$BM8:$BR8,$BM$1:$BR$1)),"") -> 206.04026 | CL8: =IFERROR(IF(AW8<>0,AW8,FORECAST(CL$1,$BM8:$BR8,$BM$1:$BR$1)),"") -> 244.29622 | CM8: =IFERROR(IF(AX8<>0,AX8,FORECAST(CM$1,$BM8:$BR8,$BM$1:$BR$1)),"") -> 249.9377 | CN8: =IFERROR(IF(AY8<>0,AY8,FORECAST(CN$1,$BM8:$BR8,$BM$1:$BR$1)),"") -> 294.97234 | CO8: =IFERROR(IF(AZ8<>0,AZ8,FORECAST(CO$1,$BM8:$BR8,$BM$1:$BR$1)),"") -> 373.0448 | ... CS8: =IFERROR(IF(BD8<>0,BD8,FORECAST(CS$1,$BM8:$BR8,$BM$1:$BR$1)),"") -> 404.10363 | CT8: =SUM(CH8:CS8) -> 3674.6367 | CV8: =SUM(BP8:BR8)/3 -> 263.06875 | CW8: =SUM(BM8:BR8)/6 -> 252.69184 | CX8: =SUM(BG8:BR8)/12 -> 230.76117 | CZ8: =N8+Summary!$E$3*CV8 -> 3047.1094 | DA8: =N8+CW8*Summary!$E$3 -> 2995.2248 | DB8: =N8+CX8*Summary!$E$3 -> 2885.5715
B9: =Mapping!A4 -> Chairs | C9: =SUMIFS('Sales Data'!$E:$E,'Sales Data'!$A:$A,$B9,'Sales Data'!$B:$B,Summary!$C$3&" "&Summary!$C$2-1,'Sales Data'!$C:$C,"Periodic")/Mapping!$C$2 -> 330.49778 | D9: =SUMIFS('Sales Data'!$D:$D,'Sales Data'!$A:$A,$B9,'Sales Data'!$B:$B,Summary!$C$3&" "&Summary!$C$2,'Sales Data'!$C:$C,"Periodic")/Mapping!$C$2 -> 329.69726 | E9: =SUMIFS('Sales Data'!$E:$E,'Sales Data'!$A:$A,$B9,'Sales Data'!$B:$B,Summary!$C$3&" "&Summary!$C$2,'Sales Data'!$C:$C,"Periodic")/Mapping!$C$2 -> 348.54445 | G9: =E9-C9 -> 18.046668 | H9: =IF(ISERROR((E9/C9)-1),"N/A",(E9/C9)-1) -> 0.054604505 | I9: =E9-D9 -> 18.847186 | J9: =IF(ISERROR((E9/D9)-1),"N/A",(E9/D9)-1) -> 0.057165127 | L9: =SUMIFS('Sales Data'!$E:$E,'Sales Data'!$A:$A,$B9,'Sales Data'!$F:$F,$C$2-1,'Sales Data'!$G:$G,"<="&$D$3)/Mapping!$C$2 -> 2028.7036 | M9: =SUMIFS('Sales Data'!$D:$D,'Sales Data'!$A:$A,$B9,'Sales Data'!$F:$F,$C$2,'Sales Data'!$G:$G,"<="&$D$3)/Mapping!$C$2 -> 2129.5317 | N9: =SUMIFS('Sales Data'!$E:$E,'Sales Data'!$A:$A,$B9,'Sales Data'!$F:$F,$C$2,'Sales Data'!$G:$G,"<="&$D$3)/Mapping!$C$2 -> 2203.3072 | P9: =N9-L9 -> 174.60358 | Q9: =IF(ISERROR((N9/L9)-1),"N/A",(N9/L9)-1) -> 0.086066578 | R9: =N9-M9 -> 73.775501 | S9: =IF(ISERROR((N9/M9)-1),"N/A",(N9/M9)-1) -> 0.034644002 | U9: =SUMIFS('Sales Data'!$E:$E,'Sales Data'!$A:$A,$B9,'Sales Data'!$F:$F,$C$2-1,'Sales Data'!$G:$G,"<="&12)/Mapping!$C$2 -> 3274.872 | V9: =SUMIFS('Sales Data'!$D:$D,'Sales Data'!$A:$A,$B9,'Sales Data'!$F:$F,$C$2,'Sales Data'!$G:$G,"<="&12)/Mapping!$C$2 -> 3681.2958 | W9: =SUMIFS('Sales Data'!$E:$E,'Sales Data'!$A:$A,$B9,'Sales Data'!$F:$F,$C$2,'Sales Data'!$G:$G,"<="&12)/Mapping!$C$2 -> 2203.3072 | Y9: =W9-U9 -> -1071.5648 | Z9: =IF(ISERROR((W9/U9)-1),"N/A",(W9/U9)-1) -> -0.32720814 | AA9: =W9-V9 -> -1477.9885 | AB9: =IF(ISERROR((W9/V9)-1),"N/A",(W9/V9)-1) -> -0.40148595 | AC9: =W9-#REF! -> #REF! | AD9: =IF(ISERROR((W9/#REF!)-1),"N/A",(W9/#REF!)-1) -> N/A | AF9: =N9/Summary!$D$3 -> 314.75817 | AG9: =(V9-N9)/Summary!$E$3 -> 295.59771 | AH9: =AG9-AF9 -> -19.160468 | AJ9: =CZ9-V9 -> 186.68176 | AK9: =DA9-V9 -> 69.078111 | AL9: =DB9-V9 -> -40.707032 | AM9: =CT9-V9 -> 2024.2416 | AN9: =CF9-V9 -> -529.10159 | AP9: =U9-L9 -> 1246.1684 | AQ9: =V9-N9 -> 1477.9885 | AS9: =SUMIFS('Sales Data'!$E:$E,'Sales Data'!$A:$A,$B9,'Sales Data'!$B:$B,AS$6,'Sales Data'!$C:$C,"Periodic")/Mapping!$C$2 -> 346.82725 | AT9: =SUMIFS('Sales Data'!$E:$E,'Sales Data'!$A:$A,$B9,'Sales Data'!$B:$B,AT$6,'Sales Data'!$C:$C,"Periodic")/Mapping!$C$2 -> 238.7955 | AU9: =SUMIFS('Sales Data'!$E:$E,'Sales Data'!$A:$A,$B9,'Sales Data'!$B:$B,AU$6,'Sales Data'!$C:$C,"Periodic")/Mapping!$C$2 -> 350.5117 | AV9: =SUMIFS('Sales Data'!$E:$E,'Sales Data'!$A:$A,$B9,'Sales Data'!$B:$B,AV$6,'Sales Data'!$C:$C,"Periodic")/Mapping!$C$2 -> 268.3706 | AW9: =SUMIFS('Sales Data'!$E:$E,'Sales Data'!$A:$A,$B9,'Sales Data'!$B:$B,AW$6,'Sales Data'!$C:$C,"Periodic")/Mapping!$C$2 -> 198.77341 | AX9: =SUMIFS('Sales Data'!$E:$E,'Sales Data'!$A:$A,$B9,'Sales Data'!$B:$B,AX$6,'Sales Data'!$C:$C,"Periodic")/Mapping!$C$2 -> 451.48431 | AY9: =SUMIFS('Sales Data'!$E:$E,'Sales Data'!$A:$A,$B9,'Sales Data'!$B:$B,AY$6,'Sales Data'!$C:$C,"Periodic")/Mapping!$C$2 -> 348.54445 | AZ9: =SUMIFS('Sales Data'!$E:$E,'Sales Data'!$A:$A,$B9,'Sales Data'!$B:$B,AZ$6,'Sales Data'!$C:$C,"Periodic")/Mapping!$C$2 -> 0 | ... BD9: =SUMIFS('Sales Data'!$E:$E,'Sales Data'!$A:$A,$B9,'Sales Data'!$B:$B,BD$6,'Sales Data'!$C:$C,"Periodic")/Mapping!$C$2 -> 0 | BE9: =SUM(AS9:BD9) -> 2203.3072 | BG9: =SUMIFS('Sales Data'!$E:$E,'Sales Data'!$A:$A,$B9,'Sales Data'!$B:$B,BG$6,'Sales Data'!$C:$C,"Periodic")/Mapping!$C$2 -> 207.34384 | BH9: =SUMIFS('Sales Data'!$E:$E,'Sales Data'!$A:$A,$B9,'Sales Data'!$B:$B,BH$6,'Sales Data'!$C:$C,"Periodic")/Mapping!$C$2 -> 331.06043 | BI9: =SUMIFS('Sales Data'!$E:$E,'Sales Data'!$A:$A,$B9,'Sales Data'!$B:$B,BI$6,'Sales Data'!$C:$C,"Periodic")/Mapping!$C$2 -> 191.55253 | BJ9: =SUMIFS('Sales Data'!$E:$E,'Sales Data'!$A:$A,$B9,'Sales Data'!$B:$B,BJ$6,'Sales Data'!$C:$C,"Periodic")/Mapping!$C$2 -> 319.95401 | BK9: =SUMIFS('Sales Data'!$E:$E,'Sales Data'!$A:$A,$B9,'Sales Data'!$B:$B,BK$6,'Sales Data'!$C:$C,"Periodic")/Mapping!$C$2 -> 196.25758 | BL9: =SUMIFS('Sales Data'!$E:$E,'Sales Data'!$A:$A,$B9,'Sales Data'!$B:$B,BL$6,'Sales Data'!$C:$C,"Periodic")/Mapping!$C$2 -> 346.82725 | BM9: =SUMIFS('Sales Data'!$E:$E,'Sales Data'!$A:$A,$B9,'Sales Data'!$B:$B,BM$6,'Sales Data'!$C:$C,"Periodic")/Mapping!$C$2 -> 238.7955 | BN9: =SUMIFS('Sales Data'!$E:$E,'Sales Data'!$A:$A,$B9,'Sales Data'!$B:$B,BN$6,'Sales Data'!$C:$C,"Periodic")/Mapping!$C$2 -> 350.5117 | ... BR9: =SUMIFS('Sales Data'!$E:$E,'Sales Data'!$A:$A,$B9,'Sales Data'!$B:$B,BR$6,'Sales Data'!$C:$C,"Periodic")/Mapping!$C$2 -> 348.54445 | BT9: =IFERROR(IF(AS9<>0,AS9,FORECAST(BT$1,$BG9:$BR9,$BG$1:$BR$1)),"") -> 346.82725 | BU9: =IFERROR(IF(AT9<>0,AT9,FORECAST(BU$1,$BG9:$BR9,$BG$1:$BR$1)),"") -> 238.7955 | BV9: =IFERROR(IF(AU9<>0,AU9,FORECAST(BV$1,$BG9:$BR9,$BG$1:$BR$1)),"") -> 350.5117 | BW9: =IFERROR(IF(AV9<>0,AV9,FORECAST(BW$1,$BG9:$BR9,$BG$1:$BR$1)),"") -> 268.3706 | BX9: =IFERROR(IF(AW9<>0,AW9,FORECAST(BX$1,$BG9:$BR9,$BG$1:$BR$1)),"") -> 198.77341 | BY9: =IFERROR(IF(AX9<>0,AX9,FORECAST(BY$1,$BG9:$BR9,$BG$1:$BR$1)),"") -> 451.48431 | BZ9: =IFERROR(IF(AY9<>0,AY9,FORECAST(BZ$1,$BG9:$BR9,$BG$1:$BR$1)),"") -> 348.54445 | CA9: =IFERROR(IF(AZ9<>0,AZ9,FORECAST(CA$1,$BG9:$BR9,$BG$1:$BR$1)),"") -> 202.38112 | ... CE9: =IFERROR(IF(BD9<>0,BD9,FORECAST(CE$1,$BG9:$BR9,$BG$1:$BR$1)),"") -> 177.17366 | CF9: =SUM(BT9:CE9) -> 3152.1942 | CH9: =IFERROR(IF(AS9<>0,AS9,FORECAST(CH$1,$BM9:$BR9,$BM$1:$BR$1)),"") -> 346.82725 | CI9: =IFERROR(IF(AT9<>0,AT9,FORECAST(CI$1,$BM9:$BR9,$BM$1:$BR$1)),"") -> 238.7955 | CJ9: =IFERROR(IF(AU9<>0,AU9,FORECAST(CJ$1,$BM9:$BR9,$BM$1:$BR$1)),"") -> 350.5117 | CK9: =IFERROR(IF(AV9<>0,AV9,FORECAST(CK$1,$BM9:$BR9,$BM$1:$BR$1)),"") -> 268.3706 | CL9: =IFERROR(IF(AW9<>0,AW9,FORECAST(CL$1,$BM9:$BR9,$BM$1:$BR$1)),"") -> 198.77341 | CM9: =IFERROR(IF(AX9<>0,AX9,FORECAST(CM$1,$BM9:$BR9,$BM$1:$BR$1)),"") -> 451.48431 | CN9: =IFERROR(IF(AY9<>0,AY9,FORECAST(CN$1,$BM9:$BR9,$BM$1:$BR$1)),"") -> 348.54445 | CO9: =IFERROR(IF(AZ9<>0,AZ9,FORECAST(CO$1,$BM9:$BR9,$BM$1:$BR$1)),"") -> 655.75658 | ... CS9: =IFERROR(IF(BD9<>0,BD9,FORECAST(CS$1,$BM9:$BR9,$BM$1:$BR$1)),"") -> 745.13548 | CT9: =SUM(CH9:CS9) -> 5705.5374 | CV9: =SUM(BP9:BR9)/3 -> 332.93406 | CW9: =SUM(BM9:BR9)/6 -> 309.41333 | CX9: =SUM(BG9:BR9)/12 -> 287.4563 | CZ9: =N9+Summary!$E$3*CV9 -> 3867.9775 | DA9: =N9+CW9*Summary!$E$3 -> 3750.3739 | DB9: =N9+CX9*Summary!$E$3 -> 3640.5887
B10: =Mapping!A5 -> Accessories | C10: =SUMIFS('Sales Data'!$E:$E,'Sales Data'!$A:$A,$B10,'Sales Data'!$B:$B,Summary!$C$3&" "&Summary!$C$2-1,'Sales Data'!$C:$C,"Periodic")/Mapping!$C$2 -> 2447.2911 | D10: =SUMIFS('Sales Data'!$D:$D,'Sales Data'!$A:$A,$B10,'Sales Data'!$B:$B,Summary!$C$3&" "&Summary!$C$2,'Sales Data'!$C:$C,"Periodic")/Mapping!$C$2 -> 2295.1582 | E10: =SUMIFS('Sales Data'!$E:$E,'Sales Data'!$A:$A,$B10,'Sales Data'!$B:$B,Summary!$C$3&" "&Summary!$C$2,'Sales Data'!$C:$C,"Periodic")/Mapping!$C$2 -> 2230.7594 | G10: =E10-C10 -> -216.53171 | H10: =IF(ISERROR((E10/C10)-1),"N/A",(E10/C10)-1) -> -0.088478117 | I10: =E10-D10 -> -64.398846 | J10: =IF(ISERROR((E10/D10)-1),"N/A",(E10/D10)-1) -> -0.028058565 | L10: =SUMIFS('Sales Data'!$E:$E,'Sales Data'!$A:$A,$B10,'Sales Data'!$F:$F,$C$2-1,'Sales Data'!$G:$G,"<="&$D$3)/Mapping!$C$2 -> 13676.597 | M10: =SUMIFS('Sales Data'!$D:$D,'Sales Data'!$A:$A,$B10,'Sales Data'!$F:$F,$C$2,'Sales Data'!$G:$G,"<="&$D$3)/Mapping!$C$2 -> 14669.69 | N10: =SUMIFS('Sales Data'!$E:$E,'Sales Data'!$A:$A,$B10,'Sales Data'!$F:$F,$C$2,'Sales Data'!$G:$G,"<="&$D$3)/Mapping!$C$2 -> 15745.228 | P10: =N10-L10 -> 2068.6308 | Q10: =IF(ISERROR((N10/L10)-1),"N/A",(N10/L10)-1) -> 0.15125333 | R10: =N10-M10 -> 1075.5383 | S10: =IF(ISERROR((N10/M10)-1),"N/A",(N10/M10)-1) -> 0.073317044 | U10: =SUMIFS('Sales Data'!$E:$E,'Sales Data'!$A:$A,$B10,'Sales Data'!$F:$F,$C$2-1,'Sales Data'!$G:$G,"<="&12)/Mapping!$C$2 -> 23640.903 | V10: =SUMIFS('Sales Data'!$D:$D,'Sales Data'!$A:$A,$B10,'Sales Data'!$F:$F,$C$2,'Sales Data'!$G:$G,"<="&12)/Mapping!$C$2 -> 25060.11 | W10: =SUMIFS('Sales Data'!$E:$E,'Sales Data'!$A:$A,$B10,'Sales Data'!$F:$F,$C$2,'Sales Data'!$G:$G,"<="&12)/Mapping!$C$2 -> 15745.228 | Y10: =W10-U10 -> -7895.6756 | Z10: =IF(ISERROR((W10/U10)-1),"N/A",(W10/U10)-1) -> -0.33398366 | AA10: =W10-V10 -> -9314.882 | AB10: =IF(ISERROR((W10/V10)-1),"N/A",(W10/V10)-1) -> -0.37170156 | AC10: =W10-#REF! -> #REF! | AD10: =IF(ISERROR((W10/#REF!)-1),"N/A",(W10/#REF!)-1) -> N/A | AF10: =N10/Summary!$D$3 -> 2249.3183 | AG10: =(V10-N10)/Summary!$E$3 -> 1862.9764 | AH10: =AG10-AF10 -> -386.34187 | AJ10: =CZ10-V10 -> 1795.9352 | AK10: =DA10-V10 -> 1827.1332 | AL10: =DB10-V10 -> 1397.424 | AM10: =CT10-V10 -> 2601.2068 | AN10: =CF10-V10 -> -784.96534 | AP10: =U10-L10 -> 9964.3064 | AQ10: =V10-N10 -> 9314.882 | AS10: =SUMIFS('Sales Data'!$E:$E,'Sales Data'!$A:$A,$B10,'Sales Data'!$B:$B,AS$6,'Sales Data'!$C:$C,"Periodic")/Mapping!$C$2 -> 2374.8097 | AT10: =SUMIFS('Sales Data'!$E:$E,'Sales Data'!$A:$A,$B10,'Sales Data'!$B:$B,AT$6,'Sales Data'!$C:$C,"Periodic")/Mapping!$C$2 -> 1899.9103 | AU10: =SUMIFS('Sales Data'!$E:$E,'Sales Data'!$A:$A,$B10,'Sales Data'!$B:$B,AU$6,'Sales Data'!$C:$C,"Periodic")/Mapping!$C$2 -> 2876.2979 | AV10: =SUMIFS('Sales Data'!$E:$E,'Sales Data'!$A:$A,$B10,'Sales Data'!$B:$B,AV$6,'Sales Data'!$C:$C,"Periodic")/Mapping!$C$2 -> 1927.7197 | AW10: =SUMIFS('Sales Data'!$E:$E,'Sales Data'!$A:$A,$B10,'Sales Data'!$B:$B,AW$6,'Sales Data'!$C:$C,"Periodic")/Mapping!$C$2 -> 2047.5976 | AX10: =SUMIFS('Sales Data'!$E:$E,'Sales Data'!$A:$A,$B10,'Sales Data'!$B:$B,AX$6,'Sales Data'!$C:$C,"Periodic")/Mapping!$C$2 -> 2388.1333 | AY10: =SUMIFS('Sales Data'!$E:$E,'Sales Data'!$A:$A,$B10,'Sales Data'!$B:$B,AY$6,'Sales Data'!$C:$C,"Periodic")/Mapping!$C$2 -> 2230.7594 | AZ10: =SUMIFS('Sales Data'!$E:$E,'Sales Data'!$A:$A,$B10,'Sales Data'!$B:$B,AZ$6,'Sales Data'!$C:$C,"Periodic")/Mapping!$C$2 -> 0 | ... BD10: =SUMIFS('Sales Data'!$E:$E,'Sales Data'!$A:$A,$B10,'Sales Data'!$B:$B,BD$6,'Sales Data'!$C:$C,"Periodic")/Mapping!$C$2 -> 0 | BE10: =SUM(AS10:BD10) -> 15745.228 | BG10: =SUMIFS('Sales Data'!$E:$E,'Sales Data'!$A:$A,$B10,'Sales Data'!$B:$B,BG$6,'Sales Data'!$C:$C,"Periodic")/Mapping!$C$2 -> 1799.0383 | BH10: =SUMIFS('Sales Data'!$E:$E,'Sales Data'!$A:$A,$B10,'Sales Data'!$B:$B,BH$6,'Sales Data'!$C:$C,"Periodic")/Mapping!$C$2 -> 1950.4351 | BI10: =SUMIFS('Sales Data'!$E:$E,'Sales Data'!$A:$A,$B10,'Sales Data'!$B:$B,BI$6,'Sales Data'!$C:$C,"Periodic")/Mapping!$C$2 -> 2097.4439 | BJ10: =SUMIFS('Sales Data'!$E:$E,'Sales Data'!$A:$A,$B10,'Sales Data'!$B:$B,BJ$6,'Sales Data'!$C:$C,"Periodic")/Mapping!$C$2 -> 1940.724 | BK10: =SUMIFS('Sales Data'!$E:$E,'Sales Data'!$A:$A,$B10,'Sales Data'!$B:$B,BK$6,'Sales Data'!$C:$C,"Periodic")/Mapping!$C$2 -> 2176.665 | BL10: =SUMIFS('Sales Data'!$E:$E,'Sales Data'!$A:$A,$B10,'Sales Data'!$B:$B,BL$6,'Sales Data'!$C:$C,"Periodic")/Mapping!$C$2 -> 2374.8097 | BM10: =SUMIFS('Sales Data'!$E:$E,'Sales Data'!$A:$A,$B10,'Sales Data'!$B:$B,BM$6,'Sales Data'!$C:$C,"Periodic")/Mapping!$C$2 -> 1899.9103 | BN10: =SUMIFS('Sales Data'!$E:$E,'Sales Data'!$A:$A,$B10,'Sales Data'!$B:$B,BN$6,'Sales Data'!$C:$C,"Periodic")/Mapping!$C$2 -> 2876.2979 | ... BR10: =SUMIFS('Sales Data'!$E:$E,'Sales Data'!$A:$A,$B10,'Sales Data'!$B:$B,BR$6,'Sales Data'!$C:$C,"Periodic")/Mapping!$C$2 -> 2230.7594 | BT10: =IFERROR(IF(AS10<>0,AS10,FORECAST(BT$1,$BG10:$BR10,$BG$1:$BR$1)),"") -> 2374.8097 | BU10: =IFERROR(IF(AT10<>0,AT10,FORECAST(BU$1,$BG10:$BR10,$BG$1:$BR$1)),"") -> 1899.9103 | BV10: =IFERROR(IF(AU10<>0,AU10,FORECAST(BV$1,$BG10:$BR10,$BG$1:$BR$1)),"") -> 2876.2979 | BW10: =IFERROR(IF(AV10<>0,AV10,FORECAST(BW$1,$BG10:$BR10,$BG$1:$BR$1)),"") -> 1927.7197 | BX10: =IFERROR(IF(AW10<>0,AW10,FORECAST(BX$1,$BG10:$BR10,$BG$1:$BR$1)),"") -> 2047.5976 | BY10: =IFERROR(IF(AX10<>0,AX10,FORECAST(BY$1,$BG10:$BR10,$BG$1:$BR$1)),"") -> 2388.1333 | BZ10: =IFERROR(IF(AY10<>0,AY10,FORECAST(BZ$1,$BG10:$BR10,$BG$1:$BR$1)),"") -> 2230.7594 | CA10: =IFERROR(IF(AZ10<>0,AZ10,FORECAST(CA$1,$BG10:$BR10,$BG$1:$BR$1)),"") -> 1762.3031 | ... CE10: =IFERROR(IF(BD10<>0,BD10,FORECAST(CE$1,$BG10:$BR10,$BG$1:$BR$1)),"") -> 1649.6636 | CF10: =SUM(BT10:CE10) -> 24275.145 | CH10: =IFERROR(IF(AS10<>0,AS10,FORECAST(CH$1,$BM10:$BR10,$BM$1:$BR$1)),"") -> 2374.8097 | CI10: =IFERROR(IF(AT10<>0,AT10,FORECAST(CI$1,$BM10:$BR10,$BM$1:$BR$1)),"") -> 1899.9103 | CJ10: =IFERROR(IF(AU10<>0,AU10,FORECAST(CJ$1,$BM10:$BR10,$BM$1:$BR$1)),"") -> 2876.2979 | CK10: =IFERROR(IF(AV10<>0,AV10,FORECAST(CK$1,$BM10:$BR10,$BM$1:$BR$1)),"") -> 1927.7197 | CL10: =IFERROR(IF(AW10<>0,AW10,FORECAST(CL$1,$BM10:$BR10,$BM$1:$BR$1)),"") -> 2047.5976 | CM10: =IFERROR(IF(AX10<>0,AX10,FORECAST(CM$1,$BM10:$BR10,$BM$1:$BR$1)),"") -> 2388.1333 | CN10: =IFERROR(IF(AY10<>0,AY10,FORECAST(CN$1,$BM10:$BR10,$BM$1:$BR$1)),"") -> 2230.7594 | CO10: =IFERROR(IF(AZ10<>0,AZ10,FORECAST(CO$1,$BM10:$BR10,$BM$1:$BR$1)),"") -> 2365.5246 | ... CS10: =IFERROR(IF(BD10<>0,BD10,FORECAST(CS$1,$BM10:$BR10,$BM$1:$BR$1)),"") -> 2400.9109 | CT10: =SUM(CH10:CS10) -> 27661.317 | CV10: =SUM(BP10:BR10)/3 -> 2222.1634 | CW10: =SUM(BM10:BR10)/6 -> 2228.403 | CX10: =SUM(BG10:BR10)/12 -> 2142.4612 | CZ10: =N10+Summary!$E$3*CV10 -> 26856.045 | DA10: =N10+CW10*Summary!$E$3 -> 26887.243 | DB10: =N10+CX10*Summary!$E$3 -> 26457.534
B11: =Mapping!A6 -> Placeholder 1 | C11: =SUMIFS('Sales Data'!$E:$E,'Sales Data'!$A:$A,$B11,'Sales Data'!$B:$B,Summary!$C$3&" "&Summary!$C$2-1,'Sales Data'!$C:$C,"Periodic")/Mapping!$C$2 -> 0 | D11: =SUMIFS('Sales Data'!$D:$D,'Sales Data'!$A:$A,$B11,'Sales Data'!$B:$B,Summary!$C$3&" "&Summary!$C$2,'Sales Data'!$C:$C,"Periodic")/Mapping!$C$2 -> 0 | E11: =SUMIFS('Sales Data'!$E:$E,'Sales Data'!$A:$A,$B11,'Sales Data'!$B:$B,Summary!$C$3&" "&Summary!$C$2,'Sales Data'!$C:$C,"Periodic")/Mapping!$C$2 -> 0 | G11: =E11-C11 -> 0 | H11: =IF(ISERROR((E11/C11)-1),"N/A",(E11/C11)-1) -> N/A | I11: =E11-D11 -> 0 | J11: =IF(ISERROR((E11/D11)-1),"N/A",(E11/D11)-1) -> N/A | L11: =SUMIFS('Sales Data'!$E:$E,'Sales Data'!$A:$A,$B11,'Sales Data'!$F:$F,$C$2-1,'Sales Data'!$G:$G,"<="&$D$3)/Mapping!$C$2 -> 0 | M11: =SUMIFS('Sales Data'!$D:$D,'Sales Data'!$A:$A,$B11,'Sales Data'!$F:$F,$C$2,'Sales Data'!$G:$G,"<="&$D$3)/Mapping!$C$2 -> 0 | N11: =SUMIFS('Sales Data'!$E:$E,'Sales Data'!$A:$A,$B11,'Sales Data'!$F:$F,$C$2,'Sales Data'!$G:$G,"<="&$D$3)/Mapping!$C$2 -> 0 | P11: =N11-L11 -> 0 | Q11: =IF(ISERROR((N11/L11)-1),"N/A",(N11/L11)-1) -> N/A | R11: =N11-M11 -> 0 | S11: =IF(ISERROR((N11/M11)-1),"N/A",(N11/M11)-1) -> N/A | U11: =SUMIFS('Sales Data'!$E:$E,'Sales Data'!$A:$A,$B11,'Sales Data'!$F:$F,$C$2-1,'Sales Data'!$G:$G,"<="&12)/Mapping!$C$2 -> 0 | V11: =SUMIFS('Sales Data'!$D:$D,'Sales Data'!$A:$A,$B11,'Sales Data'!$F:$F,$C$2,'Sales Data'!$G:$G,"<="&12)/Mapping!$C$2 -> 0 | W11: =SUMIFS('Sales Data'!$E:$E,'Sales Data'!$A:$A,$B11,'Sales Data'!$F:$F,$C$2,'Sales Data'!$G:$G,"<="&12)/Mapping!$C$2 -> 0 | Y11: =W11-U11 -> 0 | Z11: =IF(ISERROR((W11/U11)-1),"N/A",(W11/U11)-1) -> N/A | AA11: =W11-V11 -> 0 | AB11: =IF(ISERROR((W11/V11)-1),"N/A",(W11/V11)-1) -> N/A | AC11: =W11-#REF! -> #REF! | AD11: =IF(ISERROR((W11/#REF!)-1),"N/A",(W11/#REF!)-1) -> N/A | AF11: =N11/Summary!$D$3 -> 0 | AG11: =(V11-N11)/Summary!$E$3 -> 0 | AH11: =AG11-AF11 -> 0 | AJ11: =CZ11-V11 -> 0 | AK11: =DA11-V11 -> 0 | AL11: =DB11-V11 -> 0 | AM11: =CT11-V11 -> 0 | AN11: =CF11-V11 -> 0 | AP11: =U11-L11 -> 0 | AQ11: =V11-N11 -> 0 | AS11: =SUMIFS('Sales Data'!$E:$E,'Sales Data'!$A:$A,$B11,'Sales Data'!$B:$B,AS$6,'Sales Data'!$C:$C,"Periodic")/Mapping!$C$2 -> 0 | AT11: =SUMIFS('Sales Data'!$E:$E,'Sales Data'!$A:$A,$B11,'Sales Data'!$B:$B,AT$6,'Sales Data'!$C:$C,"Periodic")/Mapping!$C$2 -> 0 | AU11: =SUMIFS('Sales Data'!$E:$E,'Sales Data'!$A:$A,$B11,'Sales Data'!$B:$B,AU$6,'Sales Data'!$C:$C,"Periodic")/Mapping!$C$2 -> 0 | AV11: =SUMIFS('Sales Data'!$E:$E,'Sales Data'!$A:$A,$B11,'Sales Data'!$B:$B,AV$6,'Sales Data'!$C:$C,"Periodic")/Mapping!$C$2 -> 0 | AW11: =SUMIFS('Sales Data'!$E:$E,'Sales Data'!$A:$A,$B11,'Sales Data'!$B:$B,AW$6,'Sales Data'!$C:$C,"Periodic")/Mapping!$C$2 -> 0 | AX11: =SUMIFS('Sales Data'!$E:$E,'Sales Data'!$A:$A,$B11,'Sales Data'!$B:$B,AX$6,'Sales Data'!$C:$C,"Periodic")/Mapping!$C$2 -> 0 | AY11: =SUMIFS('Sales Data'!$E:$E,'Sales Data'!$A:$A,$B11,'Sales Data'!$B:$B,AY$6,'Sales Data'!$C:$C,"Periodic")/Mapping!$C$2 -> 0 | AZ11: =SUMIFS('Sales Data'!$E:$E,'Sales Data'!$A:$A,$B11,'Sales Data'!$B:$B,AZ$6,'Sales Data'!$C:$C,"Periodic")/Mapping!$C$2 -> 0 | ... BD11: =SUMIFS('Sales Data'!$E:$E,'Sales Data'!$A:$A,$B11,'Sales Data'!$B:$B,BD$6,'Sales Data'!$C:$C,"Periodic")/Mapping!$C$2 -> 0 | BE11: =SUM(AS11:BD11) -> 0 | BG11: =SUMIFS('Sales Data'!$E:$E,'Sales Data'!$A:$A,$B11,'Sales Data'!$B:$B,BG$6,'Sales Data'!$C:$C,"Periodic")/Mapping!$C$2 -> 0 | BH11: =SUMIFS('Sales Data'!$E:$E,'Sales Data'!$A:$A,$B11,'Sales Data'!$B:$B,BH$6,'Sales Data'!$C:$C,"Periodic")/Mapping!$C$2 -> 0 | BI11: =SUMIFS('Sales Data'!$E:$E,'Sales Data'!$A:$A,$B11,'Sales Data'!$B:$B,BI$6,'Sales Data'!$C:$C,"Periodic")/Mapping!$C$2 -> 0 | BJ11: =SUMIFS('Sales Data'!$E:$E,'Sales Data'!$A:$A,$B11,'Sales Data'!$B:$B,BJ$6,'Sales Data'!$C:$C,"Periodic")/Mapping!$C$2 -> 0 | BK11: =SUMIFS('Sales Data'!$E:$E,'Sales Data'!$A:$A,$B11,'Sales Data'!$B:$B,BK$6,'Sales Data'!$C:$C,"Periodic")/Mapping!$C$2 -> 0 | BL11: =SUMIFS('Sales Data'!$E:$E,'Sales Data'!$A:$A,$B11,'Sales Data'!$B:$B,BL$6,'Sales Data'!$C:$C,"Periodic")/Mapping!$C$2 -> 0 | BM11: =SUMIFS('Sales Data'!$E:$E,'Sales Data'!$A:$A,$B11,'Sales Data'!$B:$B,BM$6,'Sales Data'!$C:$C,"Periodic")/Mapping!$C$2 -> 0 | BN11: =SUMIFS('Sales Data'!$E:$E,'Sales Data'!$A:$A,$B11,'Sales Data'!$B:$B,BN$6,'Sales Data'!$C:$C,"Periodic")/Mapping!$C$2 -> 0 | ... BR11: =SUMIFS('Sales Data'!$E:$E,'Sales Data'!$A:$A,$B11,'Sales Data'!$B:$B,BR$6,'Sales Data'!$C:$C,"Periodic")/Mapping!$C$2 -> 0 | BT11: =IFERROR(IF(AS11<>0,AS11,FORECAST(BT$1,$BG11:$BR11,$BG$1:$BR$1)),"") -> 0 | BU11: =IFERROR(IF(AT11<>0,AT11,FORECAST(BU$1,$BG11:$BR11,$BG$1:$BR$1)),"") -> 0 | BV11: =IFERROR(IF(AU11<>0,AU11,FORECAST(BV$1,$BG11:$BR11,$BG$1:$BR$1)),"") -> 0 | BW11: =IFERROR(IF(AV11<>0,AV11,FORECAST(BW$1,$BG11:$BR11,$BG$1:$BR$1)),"") -> 0 | BX11: =IFERROR(IF(AW11<>0,AW11,FORECAST(BX$1,$BG11:$BR11,$BG$1:$BR$1)),"") -> 0 | BY11: =IFERROR(IF(AX11<>0,AX11,FORECAST(BY$1,$BG11:$BR11,$BG$1:$BR$1)),"") -> 0 | BZ11: =IFERROR(IF(AY11<>0,AY11,FORECAST(BZ$1,$BG11:$BR11,$BG$1:$BR$1)),"") -> 0 | CA11: =IFERROR(IF(AZ11<>0,AZ11,FORECAST(CA$1,$BG11:$BR11,$BG$1:$BR$1)),"") -> 0 | ... CE11: =IFERROR(IF(BD11<>0,BD11,FORECAST(CE$1,$BG11:$BR11,$BG$1:$BR$1)),"") -> 0 | CF11: =SUM(BT11:CE11) -> 0 | CH11: =IFERROR(IF(AS11<>0,AS11,FORECAST(CH$1,$BM11:$BR11,$BM$1:$BR$1)),"") -> 0 | CI11: =IFERROR(IF(AT11<>0,AT11,FORECAST(CI$1,$BM11:$BR11,$BM$1:$BR$1)),"") -> 0 | CJ11: =IFERROR(IF(AU11<>0,AU11,FORECAST(CJ$1,$BM11:$BR11,$BM$1:$BR$1)),"") -> 0 | CK11: =IFERROR(IF(AV11<>0,AV11,FORECAST(CK$1,$BM11:$BR11,$BM$1:$BR$1)),"") -> 0 | CL11: =IFERROR(IF(AW11<>0,AW11,FORECAST(CL$1,$BM11:$BR11,$BM$1:$BR$1)),"") -> 0 | CM11: =IFERROR(IF(AX11<>0,AX11,FORECAST(CM$1,$BM11:$BR11,$BM$1:$BR$1)),"") -> 0 | CN11: =IFERROR(IF(AY11<>0,AY11,FORECAST(CN$1,$BM11:$BR11,$BM$1:$BR$1)),"") -> 0 | CO11: =IFERROR(IF(AZ11<>0,AZ11,FORECAST(CO$1,$BM11:$BR11,$BM$1:$BR$1)),"") -> 0 | ... CS11: =IFERROR(IF(BD11<>0,BD11,FORECAST(CS$1,$BM11:$BR11,$BM$1:$BR$1)),"") -> 0 | CT11: =SUM(CH11:CS11) -> 0 | CV11: =SUM(BP11:BR11)/3 -> 0 | CW11: =SUM(BM11:BR11)/6 -> 0 | CX11: =SUM(BG11:BR11)/12 -> 0 | CZ11: =N11+Summary!$E$3*CV11 -> 0 | DA11: =N11+CW11*Summary!$E$3 -> 0 | DB11: =N11+CX11*Summary!$E$3 -> 0
B12: =Mapping!A7 -> Placeholder 2 | C12: =SUMIFS('Sales Data'!$E:$E,'Sales Data'!$A:$A,$B12,'Sales Data'!$B:$B,Summary!$C$3&" "&Summary!$C$2-1,'Sales Data'!$C:$C,"Periodic")/Mapping!$C$2 -> 0 | D12: =SUMIFS('Sales Data'!$D:$D,'Sales Data'!$A:$A,$B12,'Sales Data'!$B:$B,Summary!$C$3&" "&Summary!$C$2,'Sales Data'!$C:$C,"Periodic")/Mapping!$C$2 -> 0 | E12: =SUMIFS('Sales Data'!$E:$E,'Sales Data'!$A:$A,$B12,'Sales Data'!$B:$B,Summary!$C$3&" "&Summary!$C$2,'Sales Data'!$C:$C,"Periodic")/Mapping!$C$2 -> 0 | G12: =E12-C12 -> 0 | H12: =IF(ISERROR((E12/C12)-1),"N/A",(E12/C12)-1) -> N/A | I12: =E12-D12 -> 0 | J12: =IF(ISERROR((E12/D12)-1),"N/A",(E12/D12)-1) -> N/A | L12: =SUMIFS('Sales Data'!$E:$E,'Sales Data'!$A:$A,$B12,'Sales Data'!$F:$F,$C$2-1,'Sales Data'!$G:$G,"<="&$D$3)/Mapping!$C$2 -> 0 | M12: =SUMIFS('Sales Data'!$D:$D,'Sales Data'!$A:$A,$B12,'Sales Data'!$F:$F,$C$2,'Sales Data'!$G:$G,"<="&$D$3)/Mapping!$C$2 -> 0 | N12: =SUMIFS('Sales Data'!$E:$E,'Sales Data'!$A:$A,$B12,'Sales Data'!$F:$F,$C$2,'Sales Data'!$G:$G,"<="&$D$3)/Mapping!$C$2 -> 0 | P12: =N12-L12 -> 0 | Q12: =IF(ISERROR((N12/L12)-1),"N/A",(N12/L12)-1) -> N/A | R12: =N12-M12 -> 0 | S12: =IF(ISERROR((N12/M12)-1),"N/A",(N12/M12)-1) -> N/A | U12: =SUMIFS('Sales Data'!$E:$E,'Sales Data'!$A:$A,$B12,'Sales Data'!$F:$F,$C$2-1,'Sales Data'!$G:$G,"<="&12)/Mapping!$C$2 -> 0 | V12: =SUMIFS('Sales Data'!$D:$D,'Sales Data'!$A:$A,$B12,'Sales Data'!$F:$F,$C$2,'Sales Data'!$G:$G,"<="&12)/Mapping!$C$2 -> 0 | W12: =SUMIFS('Sales Data'!$E:$E,'Sales Data'!$A:$A,$B12,'Sales Data'!$F:$F,$C$2,'Sales Data'!$G:$G,"<="&12)/Mapping!$C$2 -> 0 | Y12: =W12-U12 -> 0 | Z12: =IF(ISERROR((W12/U12)-1),"N/A",(W12/U12)-1) -> N/A | AA12: =W12-V12 -> 0 | AB12: =IF(ISERROR((W12/V12)-1),"N/A",(W12/V12)-1) -> N/A | AC12: =W12-#REF! -> #REF! | AD12: =IF(ISERROR((W12/#REF!)-1),"N/A",(W12/#REF!)-1) -> N/A | AF12: =N12/Summary!$D$3 -> 0 | AG12: =(V12-N12)/Summary!$E$3 -> 0 | AH12: =AG12-AF12 -> 0 | AJ12: =CZ12-V12 -> 0 | AK12: =DA12-V12 -> 0 | AL12: =DB12-V12 -> 0 | AM12: =CT12-V12 -> 0 | AN12: =CF12-V12 -> 0 | AP12: =U12-L12 -> 0 | AQ12: =V12-N12 -> 0 | AS12: =SUMIFS('Sales Data'!$E:$E,'Sales Data'!$A:$A,$B12,'Sales Data'!$B:$B,AS$6,'Sales Data'!$C:$C,"Periodic")/Mapping!$C$2 -> 0 | AT12: =SUMIFS('Sales Data'!$E:$E,'Sales Data'!$A:$A,$B12,'Sales Data'!$B:$B,AT$6,'Sales Data'!$C:$C,"Periodic")/Mapping!$C$2 -> 0 | AU12: =SUMIFS('Sales Data'!$E:$E,'Sales Data'!$A:$A,$B12,'Sales Data'!$B:$B,AU$6,'Sales Data'!$C:$C,"Periodic")/Mapping!$C$2 -> 0 | AV12: =SUMIFS('Sales Data'!$E:$E,'Sales Data'!$A:$A,$B12,'Sales Data'!$B:$B,AV$6,'Sales Data'!$C:$C,"Periodic")/Mapping!$C$2 -> 0 | AW12: =SUMIFS('Sales Data'!$E:$E,'Sales Data'!$A:$A,$B12,'Sales Data'!$B:$B,AW$6,'Sales Data'!$C:$C,"Periodic")/Mapping!$C$2 -> 0 | AX12: =SUMIFS('Sales Data'!$E:$E,'Sales Data'!$A:$A,$B12,'Sales Data'!$B:$B,AX$6,'Sales Data'!$C:$C,"Periodic")/Mapping!$C$2 -> 0 | AY12: =SUMIFS('Sales Data'!$E:$E,'Sales Data'!$A:$A,$B12,'Sales Data'!$B:$B,AY$6,'Sales Data'!$C:$C,"Periodic")/Mapping!$C$2 -> 0 | AZ12: =SUMIFS('Sales Data'!$E:$E,'Sales Data'!$A:$A,$B12,'Sales Data'!$B:$B,AZ$6,'Sales Data'!$C:$C,"Periodic")/Mapping!$C$2 -> 0 | ... BD12: =SUMIFS('Sales Data'!$E:$E,'Sales Data'!$A:$A,$B12,'Sales Data'!$B:$B,BD$6,'Sales Data'!$C:$C,"Periodic")/Mapping!$C$2 -> 0 | BE12: =SUM(AS12:BD12) -> 0 | BG12: =SUMIFS('Sales Data'!$E:$E,'Sales Data'!$A:$A,$B12,'Sales Data'!$B:$B,BG$6,'Sales Data'!$C:$C,"Periodic")/Mapping!$C$2 -> 0 | BH12: =SUMIFS('Sales Data'!$E:$E,'Sales Data'!$A:$A,$B12,'Sales Data'!$B:$B,BH$6,'Sales Data'!$C:$C,"Periodic")/Mapping!$C$2 -> 0 | BI12: =SUMIFS('Sales Data'!$E:$E,'Sales Data'!$A:$A,$B12,'Sales Data'!$B:$B,BI$6,'Sales Data'!$C:$C,"Periodic")/Mapping!$C$2 -> 0 | BJ12: =SUMIFS('Sales Data'!$E:$E,'Sales Data'!$A:$A,$B12,'Sales Data'!$B:$B,BJ$6,'Sales Data'!$C:$C,"Periodic")/Mapping!$C$2 -> 0 | BK12: =SUMIFS('Sales Data'!$E:$E,'Sales Data'!$A:$A,$B12,'Sales Data'!$B:$B,BK$6,'Sales Data'!$C:$C,"Periodic")/Mapping!$C$2 -> 0 | BL12: =SUMIFS('Sales Data'!$E:$E,'Sales Data'!$A:$A,$B12,'Sales Data'!$B:$B,BL$6,'Sales Data'!$C:$C,"Periodic")/Mapping!$C$2 -> 0 | BM12: =SUMIFS('Sales Data'!$E:$E,'Sales Data'!$A:$A,$B12,'Sales Data'!$B:$B,BM$6,'Sales Data'!$C:$C,"Periodic")/Mapping!$C$2 -> 0 | BN12: =SUMIFS('Sales Data'!$E:$E,'Sales Data'!$A:$A,$B12,'Sales Data'!$B:$B,BN$6,'Sales Data'!$C:$C,"Periodic")/Mapping!$C$2 -> 0 | ... BR12: =SUMIFS('Sales Data'!$E:$E,'Sales Data'!$A:$A,$B12,'Sales Data'!$B:$B,BR$6,'Sales Data'!$C:$C,"Periodic")/Mapping!$C$2 -> 0 | BT12: =IFERROR(IF(AS12<>0,AS12,FORECAST(BT$1,$BG12:$BR12,$BG$1:$BR$1)),"") -> 0 | BU12: =IFERROR(IF(AT12<>0,AT12,FORECAST(BU$1,$BG12:$BR12,$BG$1:$BR$1)),"") -> 0 | BV12: =IFERROR(IF(AU12<>0,AU12,FORECAST(BV$1,$BG12:$BR12,$BG$1:$BR$1)),"") -> 0 | BW12: =IFERROR(IF(AV12<>0,AV12,FORECAST(BW$1,$BG12:$BR12,$BG$1:$BR$1)),"") -> 0 | BX12: =IFERROR(IF(AW12<>0,AW12,FORECAST(BX$1,$BG12:$BR12,$BG$1:$BR$1)),"") -> 0 | BY12: =IFERROR(IF(AX12<>0,AX12,FORECAST(BY$1,$BG12:$BR12,$BG$1:$BR$1)),"") -> 0 | BZ12: =IFERROR(IF(AY12<>0,AY12,FORECAST(BZ$1,$BG12:$BR12,$BG$1:$BR$1)),"") -> 0 | CA12: =IFERROR(IF(AZ12<>0,AZ12,FORECAST(CA$1,$BG12:$BR12,$BG$1:$BR$1)),"") -> 0 | ... CE12: =IFERROR(IF(BD12<>0,BD12,FORECAST(CE$1,$BG12:$BR12,$BG$1:$BR$1)),"") -> 0 | CF12: =SUM(BT12:CE12) -> 0 | CH12: =IFERROR(IF(AS12<>0,AS12,FORECAST(CH$1,$BM12:$BR12,$BM$1:$BR$1)),"") -> 0 | CI12: =IFERROR(IF(AT12<>0,AT12,FORECAST(CI$1,$BM12:$BR12,$BM$1:$BR$1)),"") -> 0 | CJ12: =IFERROR(IF(AU12<>0,AU12,FORECAST(CJ$1,$BM12:$BR12,$BM$1:$BR$1)),"") -> 0 | CK12: =IFERROR(IF(AV12<>0,AV12,FORECAST(CK$1,$BM12:$BR12,$BM$1:$BR$1)),"") -> 0 | CL12: =IFERROR(IF(AW12<>0,AW12,FORECAST(CL$1,$BM12:$BR12,$BM$1:$BR$1)),"") -> 0 | CM12: =IFERROR(IF(AX12<>0,AX12,FORECAST(CM$1,$BM12:$BR12,$BM$1:$BR$1)),"") -> 0 | CN12: =IFERROR(IF(AY12<>0,AY12,FORECAST(CN$1,$BM12:$BR12,$BM$1:$BR$1)),"") -> 0 | CO12: =IFERROR(IF(AZ12<>0,AZ12,FORECAST(CO$1,$BM12:$BR12,$BM$1:$BR$1)),"") -> 0 | ... CS12: =IFERROR(IF(BD12<>0,BD12,FORECAST(CS$1,$BM12:$BR12,$BM$1:$BR$1)),"") -> 0 | CT12: =SUM(CH12:CS12) -> 0 | CV12: =SUM(BP12:BR12)/3 -> 0 | CW12: =SUM(BM12:BR12)/6 -> 0 | CX12: =SUM(BG12:BR12)/12 -> 0 | CZ12: =N12+Summary!$E$3*CV12 -> 0 | DA12: =N12+CW12*Summary!$E$3 -> 0 | DB12: =N12+CX12*Summary!$E$3 -> 0
B13: =Mapping!A8 -> Placeholder 3 | C13: =SUMIFS('Sales Data'!$E:$E,'Sales Data'!$A:$A,$B13,'Sales Data'!$B:$B,Summary!$C$3&" "&Summary!$C$2-1,'Sales Data'!$C:$C,"Periodic")/Mapping!$C$2 -> 0 | D13: =SUMIFS('Sales Data'!$D:$D,'Sales Data'!$A:$A,$B13,'Sales Data'!$B:$B,Summary!$C$3&" "&Summary!$C$2,'Sales Data'!$C:$C,"Periodic")/Mapping!$C$2 -> 0 | E13: =SUMIFS('Sales Data'!$E:$E,'Sales Data'!$A:$A,$B13,'Sales Data'!$B:$B,Summary!$C$3&" "&Summary!$C$2,'Sales Data'!$C:$C,"Periodic")/Mapping!$C$2 -> 0 | G13: =E13-C13 -> 0 | H13: =IF(ISERROR((E13/C13)-1),"N/A",(E13/C13)-1) -> N/A | I13: =E13-D13 -> 0 | J13: =IF(ISERROR((E13/D13)-1),"N/A",(E13/D13)-1) -> N/A | L13: =SUMIFS('Sales Data'!$E:$E,'Sales Data'!$A:$A,$B13,'Sales Data'!$F:$F,$C$2-1,'Sales Data'!$G:$G,"<="&$D$3)/Mapping!$C$2 -> 0 | M13: =SUMIFS('Sales Data'!$D:$D,'Sales Data'!$A:$A,$B13,'Sales Data'!$F:$F,$C$2,'Sales Data'!$G:$G,"<="&$D$3)/Mapping!$C$2 -> 0 | N13: =SUMIFS('Sales Data'!$E:$E,'Sales Data'!$A:$A,$B13,'Sales Data'!$F:$F,$C$2,'Sales Data'!$G:$G,"<="&$D$3)/Mapping!$C$2 -> 0 | P13: =N13-L13 -> 0 | Q13: =IF(ISERROR((N13/L13)-1),"N/A",(N13/L13)-1) -> N/A | R13: =N13-M13 -> 0 | S13: =IF(ISERROR((N13/M13)-1),"N/A",(N13/M13)-1) -> N/A | U13: =SUMIFS('Sales Data'!$E:$E,'Sales Data'!$A:$A,$B13,'Sales Data'!$F:$F,$C$2-1,'Sales Data'!$G:$G,"<="&12)/Mapping!$C$2 -> 0 | V13: =SUMIFS('Sales Data'!$D:$D,'Sales Data'!$A:$A,$B13,'Sales Data'!$F:$F,$C$2,'Sales Data'!$G:$G,"<="&12)/Mapping!$C$2 -> 0 | W13: =SUMIFS('Sales Data'!$E:$E,'Sales Data'!$A:$A,$B13,'Sales Data'!$F:$F,$C$2,'Sales Data'!$G:$G,"<="&12)/Mapping!$C$2 -> 0 | Y13: =W13-U13 -> 0 | Z13: =IF(ISERROR((W13/U13)-1),"N/A",(W13/U13)-1) -> N/A | AA13: =W13-V13 -> 0 | AB13: =IF(ISERROR((W13/V13)-1),"N/A",(W13/V13)-1) -> N/A | AC13: =W13-#REF! -> #REF! | AD13: =IF(ISERROR((W13/#REF!)-1),"N/A",(W13/#REF!)-1) -> N/A | AF13: =N13/Summary!$D$3 -> 0 | AG13: =(V13-N13)/Summary!$E$3 -> 0 | AH13: =AG13-AF13 -> 0 | AJ13: =CZ13-V13 -> 0 | AK13: =DA13-V13 -> 0 | AL13: =DB13-V13 -> 0 | AM13: =CT13-V13 -> 0 | AN13: =CF13-V13 -> 0 | AP13: =U13-L13 -> 0 | AQ13: =V13-N13 -> 0 | AS13: =SUMIFS('Sales Data'!$E:$E,'Sales Data'!$A:$A,$B13,'Sales Data'!$B:$B,AS$6,'Sales Data'!$C:$C,"Periodic")/Mapping!$C$2 -> 0 | AT13: =SUMIFS('Sales Data'!$E:$E,'Sales Data'!$A:$A,$B13,'Sales Data'!$B:$B,AT$6,'Sales Data'!$C:$C,"Periodic")/Mapping!$C$2 -> 0 | AU13: =SUMIFS('Sales Data'!$E:$E,'Sales Data'!$A:$A,$B13,'Sales Data'!$B:$B,AU$6,'Sales Data'!$C:$C,"Periodic")/Mapping!$C$2 -> 0 | AV13: =SUMIFS('Sales Data'!$E:$E,'Sales Data'!$A:$A,$B13,'Sales Data'!$B:$B,AV$6,'Sales Data'!$C:$C,"Periodic")/Mapping!$C$2 -> 0 | AW13: =SUMIFS('Sales Data'!$E:$E,'Sales Data'!$A:$A,$B13,'Sales Data'!$B:$B,AW$6,'Sales Data'!$C:$C,"Periodic")/Mapping!$C$2 -> 0 | AX13: =SUMIFS('Sales Data'!$E:$E,'Sales Data'!$A:$A,$B13,'Sales Data'!$B:$B,AX$6,'Sales Data'!$C:$C,"Periodic")/Mapping!$C$2 -> 0 | AY13: =SUMIFS('Sales Data'!$E:$E,'Sales Data'!$A:$A,$B13,'Sales Data'!$B:$B,AY$6,'Sales Data'!$C:$C,"Periodic")/Mapping!$C$2 -> 0 | AZ13: =SUMIFS('Sales Data'!$E:$E,'Sales Data'!$A:$A,$B13,'Sales Data'!$B:$B,AZ$6,'Sales Data'!$C:$C,"Periodic")/Mapping!$C$2 -> 0 | ... BD13: =SUMIFS('Sales Data'!$E:$E,'Sales Data'!$A:$A,$B13,'Sales Data'!$B:$B,BD$6,'Sales Data'!$C:$C,"Periodic")/Mapping!$C$2 -> 0 | BE13: =SUM(AS13:BD13) -> 0 | BG13: =SUMIFS('Sales Data'!$E:$E,'Sales Data'!$A:$A,$B13,'Sales Data'!$B:$B,BG$6,'Sales Data'!$C:$C,"Periodic")/Mapping!$C$2 -> 0 | BH13: =SUMIFS('Sales Data'!$E:$E,'Sales Data'!$A:$A,$B13,'Sales Data'!$B:$B,BH$6,'Sales Data'!$C:$C,"Periodic")/Mapping!$C$2 -> 0 | BI13: =SUMIFS('Sales Data'!$E:$E,'Sales Data'!$A:$A,$B13,'Sales Data'!$B:$B,BI$6,'Sales Data'!$C:$C,"Periodic")/Mapping!$C$2 -> 0 | BJ13: =SUMIFS('Sales Data'!$E:$E,'Sales Data'!$A:$A,$B13,'Sales Data'!$B:$B,BJ$6,'Sales Data'!$C:$C,"Periodic")/Mapping!$C$2 -> 0 | BK13: =SUMIFS('Sales Data'!$E:$E,'Sales Data'!$A:$A,$B13,'Sales Data'!$B:$B,BK$6,'Sales Data'!$C:$C,"Periodic")/Mapping!$C$2 -> 0 | BL13: =SUMIFS('Sales Data'!$E:$E,'Sales Data'!$A:$A,$B13,'Sales Data'!$B:$B,BL$6,'Sales Data'!$C:$C,"Periodic")/Mapping!$C$2 -> 0 | BM13: =SUMIFS('Sales Data'!$E:$E,'Sales Data'!$A:$A,$B13,'Sales Data'!$B:$B,BM$6,'Sales Data'!$C:$C,"Periodic")/Mapping!$C$2 -> 0 | BN13: =SUMIFS('Sales Data'!$E:$E,'Sales Data'!$A:$A,$B13,'Sales Data'!$B:$B,BN$6,'Sales Data'!$C:$C,"Periodic")/Mapping!$C$2 -> 0 | ... BR13: =SUMIFS('Sales Data'!$E:$E,'Sales Data'!$A:$A,$B13,'Sales Data'!$B:$B,BR$6,'Sales Data'!$C:$C,"Periodic")/Mapping!$C$2 -> 0 | BT13: =IFERROR(IF(AS13<>0,AS13,FORECAST(BT$1,$BG13:$BR13,$BG$1:$BR$1)),"") -> 0 | BU13: =IFERROR(IF(AT13<>0,AT13,FORECAST(BU$1,$BG13:$BR13,$BG$1:$BR$1)),"") -> 0 | BV13: =IFERROR(IF(AU13<>0,AU13,FORECAST(BV$1,$BG13:$BR13,$BG$1:$BR$1)),"") -> 0 | BW13: =IFERROR(IF(AV13<>0,AV13,FORECAST(BW$1,$BG13:$BR13,$BG$1:$BR$1)),"") -> 0 | BX13: =IFERROR(IF(AW13<>0,AW13,FORECAST(BX$1,$BG13:$BR13,$BG$1:$BR$1)),"") -> 0 | BY13: =IFERROR(IF(AX13<>0,AX13,FORECAST(BY$1,$BG13:$BR13,$BG$1:$BR$1)),"") -> 0 | BZ13: =IFERROR(IF(AY13<>0,AY13,FORECAST(BZ$1,$BG13:$BR13,$BG$1:$BR$1)),"") -> 0 | CA13: =IFERROR(IF(AZ13<>0,AZ13,FORECAST(CA$1,$BG13:$BR13,$BG$1:$BR$1)),"") -> 0 | ... CE13: =IFERROR(IF(BD13<>0,BD13,FORECAST(CE$1,$BG13:$BR13,$BG$1:$BR$1)),"") -> 0 | CF13: =SUM(BT13:CE13) -> 0 | CH13: =IFERROR(IF(AS13<>0,AS13,FORECAST(CH$1,$BM13:$BR13,$BM$1:$BR$1)),"") -> 0 | CI13: =IFERROR(IF(AT13<>0,AT13,FORECAST(CI$1,$BM13:$BR13,$BM$1:$BR$1)),"") -> 0 | CJ13: =IFERROR(IF(AU13<>0,AU13,FORECAST(CJ$1,$BM13:$BR13,$BM$1:$BR$1)),"") -> 0 | CK13: =IFERROR(IF(AV13<>0,AV13,FORECAST(CK$1,$BM13:$BR13,$BM$1:$BR$1)),"") -> 0 | CL13: =IFERROR(IF(AW13<>0,AW13,FORECAST(CL$1,$BM13:$BR13,$BM$1:$BR$1)),"") -> 0 | CM13: =IFERROR(IF(AX13<>0,AX13,FORECAST(CM$1,$BM13:$BR13,$BM$1:$BR$1)),"") -> 0 | CN13: =IFERROR(IF(AY13<>0,AY13,FORECAST(CN$1,$BM13:$BR13,$BM$1:$BR$1)),"") -> 0 | CO13: =IFERROR(IF(AZ13<>0,AZ13,FORECAST(CO$1,$BM13:$BR13,$BM$1:$BR$1)),"") -> 0 | ... CS13: =IFERROR(IF(BD13<>0,BD13,FORECAST(CS$1,$BM13:$BR13,$BM$1:$BR$1)),"") -> 0 | CT13: =SUM(CH13:CS13) -> 0 | CV13: =SUM(BP13:BR13)/3 -> 0 | CW13: =SUM(BM13:BR13)/6 -> 0 | CX13: =SUM(BG13:BR13)/12 -> 0 | CZ13: =N13+Summary!$E$3*CV13 -> 0 | DA13: =N13+CW13*Summary!$E$3 -> 0 | DB13: =N13+CX13*Summary!$E$3 -> 0
B14: =Mapping!A9 -> Placeholder 4 | C14: =SUMIFS('Sales Data'!$E:$E,'Sales Data'!$A:$A,$B14,'Sales Data'!$B:$B,Summary!$C$3&" "&Summary!$C$2-1,'Sales Data'!$C:$C,"Periodic")/Mapping!$C$2 -> 0 | D14: =SUMIFS('Sales Data'!$D:$D,'Sales Data'!$A:$A,$B14,'Sales Data'!$B:$B,Summary!$C$3&" "&Summary!$C$2,'Sales Data'!$C:$C,"Periodic")/Mapping!$C$2 -> 0 | E14: =SUMIFS('Sales Data'!$E:$E,'Sales Data'!$A:$A,$B14,'Sales Data'!$B:$B,Summary!$C$3&" "&Summary!$C$2,'Sales Data'!$C:$C,"Periodic")/Mapping!$C$2 -> 0 | G14: =E14-C14 -> 0 | H14: =IF(ISERROR((E14/C14)-1),"N/A",(E14/C14)-1) -> N/A | I14: =E14-D14 -> 0 | J14: =IF(ISERROR((E14/D14)-1),"N/A",(E14/D14)-1) -> N/A | L14: =SUMIFS('Sales Data'!$E:$E,'Sales Data'!$A:$A,$B14,'Sales Data'!$F:$F,$C$2-1,'Sales Data'!$G:$G,"<="&$D$3)/Mapping!$C$2 -> 0 | M14: =SUMIFS('Sales Data'!$D:$D,'Sales Data'!$A:$A,$B14,'Sales Data'!$F:$F,$C$2,'Sales Data'!$G:$G,"<="&$D$3)/Mapping!$C$2 -> 0 | N14: =SUMIFS('Sales Data'!$E:$E,'Sales Data'!$A:$A,$B14,'Sales Data'!$F:$F,$C$2,'Sales Data'!$G:$G,"<="&$D$3)/Mapping!$C$2 -> 0 | P14: =N14-L14 -> 0 | Q14: =IF(ISERROR((N14/L14)-1),"N/A",(N14/L14)-1) -> N/A | R14: =N14-M14 -> 0 | S14: =IF(ISERROR((N14/M14)-1),"N/A",(N14/M14)-1) -> N/A | U14: =SUMIFS('Sales Data'!$E:$E,'Sales Data'!$A:$A,$B14,'Sales Data'!$F:$F,$C$2-1,'Sales Data'!$G:$G,"<="&12)/Mapping!$C$2 -> 0 | V14: =SUMIFS('Sales Data'!$D:$D,'Sales Data'!$A:$A,$B14,'Sales Data'!$F:$F,$C$2,'Sales Data'!$G:$G,"<="&12)/Mapping!$C$2 -> 0 | W14: =SUMIFS('Sales Data'!$E:$E,'Sales Data'!$A:$A,$B14,'Sales Data'!$F:$F,$C$2,'Sales Data'!$G:$G,"<="&12)/Mapping!$C$2 -> 0 | Y14: =W14-U14 -> 0 | Z14: =IF(ISERROR((W14/U14)-1),"N/A",(W14/U14)-1) -> N/A | AA14: =W14-V14 -> 0 | AB14: =IF(ISERROR((W14/V14)-1),"N/A",(W14/V14)-1) -> N/A | AC14: =W14-#REF! -> #REF! | AD14: =IF(ISERROR((W14/#REF!)-1),"N/A",(W14/#REF!)-1) -> N/A | AF14: =N14/Summary!$D$3 -> 0 | AG14: =(V14-N14)/Summary!$E$3 -> 0 | AH14: =AG14-AF14 -> 0 | AJ14: =CZ14-V14 -> 0 | AK14: =DA14-V14 -> 0 | AL14: =DB14-V14 -> 0 | AM14: =CT14-V14 -> 0 | AN14: =CF14-V14 -> 0 | AP14: =U14-L14 -> 0 | AQ14: =V14-N14 -> 0 | AS14: =SUMIFS('Sales Data'!$E:$E,'Sales Data'!$A:$A,$B14,'Sales Data'!$B:$B,AS$6,'Sales Data'!$C:$C,"Periodic")/Mapping!$C$2 -> 0 | AT14: =SUMIFS('Sales Data'!$E:$E,'Sales Data'!$A:$A,$B14,'Sales Data'!$B:$B,AT$6,'Sales Data'!$C:$C,"Periodic")/Mapping!$C$2 -> 0 | AU14: =SUMIFS('Sales Data'!$E:$E,'Sales Data'!$A:$A,$B14,'Sales Data'!$B:$B,AU$6,'Sales Data'!$C:$C,"Periodic")/Mapping!$C$2 -> 0 | AV14: =SUMIFS('Sales Data'!$E:$E,'Sales Data'!$A:$A,$B14,'Sales Data'!$B:$B,AV$6,'Sales Data'!$C:$C,"Periodic")/Mapping!$C$2 -> 0 | AW14: =SUMIFS('Sales Data'!$E:$E,'Sales Data'!$A:$A,$B14,'Sales Data'!$B:$B,AW$6,'Sales Data'!$C:$C,"Periodic")/Mapping!$C$2 -> 0 | AX14: =SUMIFS('Sales Data'!$E:$E,'Sales Data'!$A:$A,$B14,'Sales Data'!$B:$B,AX$6,'Sales Data'!$C:$C,"Periodic")/Mapping!$C$2 -> 0 | AY14: =SUMIFS('Sales Data'!$E:$E,'Sales Data'!$A:$A,$B14,'Sales Data'!$B:$B,AY$6,'Sales Data'!$C:$C,"Periodic")/Mapping!$C$2 -> 0 | AZ14: =SUMIFS('Sales Data'!$E:$E,'Sales Data'!$A:$A,$B14,'Sales Data'!$B:$B,AZ$6,'Sales Data'!$C:$C,"Periodic")/Mapping!$C$2 -> 0 | ... BD14: =SUMIFS('Sales Data'!$E:$E,'Sales Data'!$A:$A,$B14,'Sales Data'!$B:$B,BD$6,'Sales Data'!$C:$C,"Periodic")/Mapping!$C$2 -> 0 | BE14: =SUM(AS14:BD14) -> 0 | BG14: =SUMIFS('Sales Data'!$E:$E,'Sales Data'!$A:$A,$B14,'Sales Data'!$B:$B,BG$6,'Sales Data'!$C:$C,"Periodic")/Mapping!$C$2 -> 0 | BH14: =SUMIFS('Sales Data'!$E:$E,'Sales Data'!$A:$A,$B14,'Sales Data'!$B:$B,BH$6,'Sales Data'!$C:$C,"Periodic")/Mapping!$C$2 -> 0 | BI14: =SUMIFS('Sales Data'!$E:$E,'Sales Data'!$A:$A,$B14,'Sales Data'!$B:$B,BI$6,'Sales Data'!$C:$C,"Periodic")/Mapping!$C$2 -> 0 | BJ14: =SUMIFS('Sales Data'!$E:$E,'Sales Data'!$A:$A,$B14,'Sales Data'!$B:$B,BJ$6,'Sales Data'!$C:$C,"Periodic")/Mapping!$C$2 -> 0 | BK14: =SUMIFS('Sales Data'!$E:$E,'Sales Data'!$A:$A,$B14,'Sales Data'!$B:$B,BK$6,'Sales Data'!$C:$C,"Periodic")/Mapping!$C$2 -> 0 | BL14: =SUMIFS('Sales Data'!$E:$E,'Sales Data'!$A:$A,$B14,'Sales Data'!$B:$B,BL$6,'Sales Data'!$C:$C,"Periodic")/Mapping!$C$2 -> 0 | BM14: =SUMIFS('Sales Data'!$E:$E,'Sales Data'!$A:$A,$B14,'Sales Data'!$B:$B,BM$6,'Sales Data'!$C:$C,"Periodic")/Mapping!$C$2 -> 0 | BN14: =SUMIFS('Sales Data'!$E:$E,'Sales Data'!$A:$A,$B14,'Sales Data'!$B:$B,BN$6,'Sales Data'!$C:$C,"Periodic")/Mapping!$C$2 -> 0 | ... BR14: =SUMIFS('Sales Data'!$E:$E,'Sales Data'!$A:$A,$B14,'Sales Data'!$B:$B,BR$6,'Sales Data'!$C:$C,"Periodic")/Mapping!$C$2 -> 0 | BT14: =IFERROR(IF(AS14<>0,AS14,FORECAST(BT$1,$BG14:$BR14,$BG$1:$BR$1)),"") -> 0 | BU14: =IFERROR(IF(AT14<>0,AT14,FORECAST(BU$1,$BG14:$BR14,$BG$1:$BR$1)),"") -> 0 | BV14: =IFERROR(IF(AU14<>0,AU14,FORECAST(BV$1,$BG14:$BR14,$BG$1:$BR$1)),"") -> 0 | BW14: =IFERROR(IF(AV14<>0,AV14,FORECAST(BW$1,$BG14:$BR14,$BG$1:$BR$1)),"") -> 0 | BX14: =IFERROR(IF(AW14<>0,AW14,FORECAST(BX$1,$BG14:$BR14,$BG$1:$BR$1)),"") -> 0 | BY14: =IFERROR(IF(AX14<>0,AX14,FORECAST(BY$1,$BG14:$BR14,$BG$1:$BR$1)),"") -> 0 | BZ14: =IFERROR(IF(AY14<>0,AY14,FORECAST(BZ$1,$BG14:$BR14,$BG$1:$BR$1)),"") -> 0 | CA14: =IFERROR(IF(AZ14<>0,AZ14,FORECAST(CA$1,$BG14:$BR14,$BG$1:$BR$1)),"") -> 0 | ... CE14: =IFERROR(IF(BD14<>0,BD14,FORECAST(CE$1,$BG14:$BR14,$BG$1:$BR$1)),"") -> 0 | CF14: =SUM(BT14:CE14) -> 0 | CH14: =IFERROR(IF(AS14<>0,AS14,FORECAST(CH$1,$BM14:$BR14,$BM$1:$BR$1)),"") -> 0 | CI14: =IFERROR(IF(AT14<>0,AT14,FORECAST(CI$1,$BM14:$BR14,$BM$1:$BR$1)),"") -> 0 | CJ14: =IFERROR(IF(AU14<>0,AU14,FORECAST(CJ$1,$BM14:$BR14,$BM$1:$BR$1)),"") -> 0 | CK14: =IFERROR(IF(AV14<>0,AV14,FORECAST(CK$1,$BM14:$BR14,$BM$1:$BR$1)),"") -> 0 | CL14: =IFERROR(IF(AW14<>0,AW14,FORECAST(CL$1,$BM14:$BR14,$BM$1:$BR$1)),"") -> 0 | CM14: =IFERROR(IF(AX14<>0,AX14,FORECAST(CM$1,$BM14:$BR14,$BM$1:$BR$1)),"") -> 0 | CN14: =IFERROR(IF(AY14<>0,AY14,FORECAST(CN$1,$BM14:$BR14,$BM$1:$BR$1)),"") -> 0 | CO14: =IFERROR(IF(AZ14<>0,AZ14,FORECAST(CO$1,$BM14:$BR14,$BM$1:$BR$1)),"") -> 0 | ... CS14: =IFERROR(IF(BD14<>0,BD14,FORECAST(CS$1,$BM14:$BR14,$BM$1:$BR$1)),"") -> 0 | CT14: =SUM(CH14:CS14) -> 0 | CV14: =SUM(BP14:BR14)/3 -> 0 | CW14: =SUM(BM14:BR14)/6 -> 0 | CX14: =SUM(BG14:BR14)/12 -> 0 | CZ14: =N14+Summary!$E$3*CV14 -> 0 | DA14: =N14+CW14*Summary!$E$3 -> 0 | DB14: =N14+CX14*Summary!$E$3 -> 0
B15: =Mapping!A10 -> Placeholder 5 | C15: =SUMIFS('Sales Data'!$E:$E,'Sales Data'!$A:$A,$B15,'Sales Data'!$B:$B,Summary!$C$3&" "&Summary!$C$2-1,'Sales Data'!$C:$C,"Periodic")/Mapping!$C$2 -> 0 | D15: =SUMIFS('Sales Data'!$D:$D,'Sales Data'!$A:$A,$B15,'Sales Data'!$B:$B,Summary!$C$3&" "&Summary!$C$2,'Sales Data'!$C:$C,"Periodic")/Mapping!$C$2 -> 0 | E15: =SUMIFS('Sales Data'!$E:$E,'Sales Data'!$A:$A,$B15,'Sales Data'!$B:$B,Summary!$C$3&" "&Summary!$C$2,'Sales Data'!$C:$C,"Periodic")/Mapping!$C$2 -> 0 | G15: =E15-C15 -> 0 | H15: =IF(ISERROR((E15/C15)-1),"N/A",(E15/C15)-1) -> N/A | I15: =E15-D15 -> 0 | J15: =IF(ISERROR((E15/D15)-1),"N/A",(E15/D15)-1) -> N/A | L15: =SUMIFS('Sales Data'!$E:$E,'Sales Data'!$A:$A,$B15,'Sales Data'!$F:$F,$C$2-1,'Sales Data'!$G:$G,"<="&$D$3)/Mapping!$C$2 -> 0 | M15: =SUMIFS('Sales Data'!$D:$D,'Sales Data'!$A:$A,$B15,'Sales Data'!$F:$F,$C$2,'Sales Data'!$G:$G,"<="&$D$3)/Mapping!$C$2 -> 0 | N15: =SUMIFS('Sales Data'!$E:$E,'Sales Data'!$A:$A,$B15,'Sales Data'!$F:$F,$C$2,'Sales Data'!$G:$G,"<="&$D$3)/Mapping!$C$2 -> 0 | P15: =N15-L15 -> 0 | Q15: =IF(ISERROR((N15/L15)-1),"N/A",(N15/L15)-1) -> N/A | R15: =N15-M15 -> 0 | S15: =IF(ISERROR((N15/M15)-1),"N/A",(N15/M15)-1) -> N/A | U15: =SUMIFS('Sales Data'!$E:$E,'Sales Data'!$A:$A,$B15,'Sales Data'!$F:$F,$C$2-1,'Sales Data'!$G:$G,"<="&12)/Mapping!$C$2 -> 0 | V15: =SUMIFS('Sales Data'!$D:$D,'Sales Data'!$A:$A,$B15,'Sales Data'!$F:$F,$C$2,'Sales Data'!$G:$G,"<="&12)/Mapping!$C$2 -> 0 | W15: =SUMIFS('Sales Data'!$E:$E,'Sales Data'!$A:$A,$B15,'Sales Data'!$F:$F,$C$2,'Sales Data'!$G:$G,"<="&12)/Mapping!$C$2 -> 0 | Y15: =W15-U15 -> 0 | Z15: =IF(ISERROR((W15/U15)-1),"N/A",(W15/U15)-1) -> N/A | AA15: =W15-V15 -> 0 | AB15: =IF(ISERROR((W15/V15)-1),"N/A",(W15/V15)-1) -> N/A | AC15: =W15-#REF! -> #REF! | AD15: =IF(ISERROR((W15/#REF!)-1),"N/A",(W15/#REF!)-1) -> N/A | AF15: =N15/Summary!$D$3 -> 0 | AG15: =(V15-N15)/Summary!$E$3 -> 0 | AH15: =AG15-AF15 -> 0 | AJ15: =CZ15-V15 -> 0 | AK15: =DA15-V15 -> 0 | AL15: =DB15-V15 -> 0 | AM15: =CT15-V15 -> 0 | AN15: =CF15-V15 -> 0 | AP15: =U15-L15 -> 0 | AQ15: =V15-N15 -> 0 | AS15: =SUMIFS('Sales Data'!$E:$E,'Sales Data'!$A:$A,$B15,'Sales Data'!$B:$B,AS$6,'Sales Data'!$C:$C,"Periodic")/Mapping!$C$2 -> 0 | AT15: =SUMIFS('Sales Data'!$E:$E,'Sales Data'!$A:$A,$B15,'Sales Data'!$B:$B,AT$6,'Sales Data'!$C:$C,"Periodic")/Mapping!$C$2 -> 0 | AU15: =SUMIFS('Sales Data'!$E:$E,'Sales Data'!$A:$A,$B15,'Sales Data'!$B:$B,AU$6,'Sales Data'!$C:$C,"Periodic")/Mapping!$C$2 -> 0 | AV15: =SUMIFS('Sales Data'!$E:$E,'Sales Data'!$A:$A,$B15,'Sales Data'!$B:$B,AV$6,'Sales Data'!$C:$C,"Periodic")/Mapping!$C$2 -> 0 | AW15: =SUMIFS('Sales Data'!$E:$E,'Sales Data'!$A:$A,$B15,'Sales Data'!$B:$B,AW$6,'Sales Data'!$C:$C,"Periodic")/Mapping!$C$2 -> 0 | AX15: =SUMIFS('Sales Data'!$E:$E,'Sales Data'!$A:$A,$B15,'Sales Data'!$B:$B,AX$6,'Sales Data'!$C:$C,"Periodic")/Mapping!$C$2 -> 0 | AY15: =SUMIFS('Sales Data'!$E:$E,'Sales Data'!$A:$A,$B15,'Sales Data'!$B:$B,AY$6,'Sales Data'!$C:$C,"Periodic")/Mapping!$C$2 -> 0 | AZ15: =SUMIFS('Sales Data'!$E:$E,'Sales Data'!$A:$A,$B15,'Sales Data'!$B:$B,AZ$6,'Sales Data'!$C:$C,"Periodic")/Mapping!$C$2 -> 0 | ... BD15: =SUMIFS('Sales Data'!$E:$E,'Sales Data'!$A:$A,$B15,'Sales Data'!$B:$B,BD$6,'Sales Data'!$C:$C,"Periodic")/Mapping!$C$2 -> 0 | BE15: =SUM(AS15:BD15) -> 0 | BG15: =SUMIFS('Sales Data'!$E:$E,'Sales Data'!$A:$A,$B15,'Sales Data'!$B:$B,BG$6,'Sales Data'!$C:$C,"Periodic")/Mapping!$C$2 -> 0 | BH15: =SUMIFS('Sales Data'!$E:$E,'Sales Data'!$A:$A,$B15,'Sales Data'!$B:$B,BH$6,'Sales Data'!$C:$C,"Periodic")/Mapping!$C$2 -> 0 | BI15: =SUMIFS('Sales Data'!$E:$E,'Sales Data'!$A:$A,$B15,'Sales Data'!$B:$B,BI$6,'Sales Data'!$C:$C,"Periodic")/Mapping!$C$2 -> 0 | BJ15: =SUMIFS('Sales Data'!$E:$E,'Sales Data'!$A:$A,$B15,'Sales Data'!$B:$B,BJ$6,'Sales Data'!$C:$C,"Periodic")/Mapping!$C$2 -> 0 | BK15: =SUMIFS('Sales Data'!$E:$E,'Sales Data'!$A:$A,$B15,'Sales Data'!$B:$B,BK$6,'Sales Data'!$C:$C,"Periodic")/Mapping!$C$2 -> 0 | BL15: =SUMIFS('Sales Data'!$E:$E,'Sales Data'!$A:$A,$B15,'Sales Data'!$B:$B,BL$6,'Sales Data'!$C:$C,"Periodic")/Mapping!$C$2 -> 0 | BM15: =SUMIFS('Sales Data'!$E:$E,'Sales Data'!$A:$A,$B15,'Sales Data'!$B:$B,BM$6,'Sales Data'!$C:$C,"Periodic")/Mapping!$C$2 -> 0 | BN15: =SUMIFS('Sales Data'!$E:$E,'Sales Data'!$A:$A,$B15,'Sales Data'!$B:$B,BN$6,'Sales Data'!$C:$C,"Periodic")/Mapping!$C$2 -> 0 | ... BR15: =SUMIFS('Sales Data'!$E:$E,'Sales Data'!$A:$A,$B15,'Sales Data'!$B:$B,BR$6,'Sales Data'!$C:$C,"Periodic")/Mapping!$C$2 -> 0 | BT15: =IFERROR(IF(AS15<>0,AS15,FORECAST(BT$1,$BG15:$BR15,$BG$1:$BR$1)),"") -> 0 | BU15: =IFERROR(IF(AT15<>0,AT15,FORECAST(BU$1,$BG15:$BR15,$BG$1:$BR$1)),"") -> 0 | BV15: =IFERROR(IF(AU15<>0,AU15,FORECAST(BV$1,$BG15:$BR15,$BG$1:$BR$1)),"") -> 0 | BW15: =IFERROR(IF(AV15<>0,AV15,FORECAST(BW$1,$BG15:$BR15,$BG$1:$BR$1)),"") -> 0 | BX15: =IFERROR(IF(AW15<>0,AW15,FORECAST(BX$1,$BG15:$BR15,$BG$1:$BR$1)),"") -> 0 | BY15: =IFERROR(IF(AX15<>0,AX15,FORECAST(BY$1,$BG15:$BR15,$BG$1:$BR$1)),"") -> 0 | BZ15: =IFERROR(IF(AY15<>0,AY15,FORECAST(BZ$1,$BG15:$BR15,$BG$1:$BR$1)),"") -> 0 | CA15: =IFERROR(IF(AZ15<>0,AZ15,FORECAST(CA$1,$BG15:$BR15,$BG$1:$BR$1)),"") -> 0 | ... CE15: =IFERROR(IF(BD15<>0,BD15,FORECAST(CE$1,$BG15:$BR15,$BG$1:$BR$1)),"") -> 0 | CF15: =SUM(BT15:CE15) -> 0 | CH15: =IFERROR(IF(AS15<>0,AS15,FORECAST(CH$1,$BM15:$BR15,$BM$1:$BR$1)),"") -> 0 | CI15: =IFERROR(IF(AT15<>0,AT15,FORECAST(CI$1,$BM15:$BR15,$BM$1:$BR$1)),"") -> 0 | CJ15: =IFERROR(IF(AU15<>0,AU15,FORECAST(CJ$1,$BM15:$BR15,$BM$1:$BR$1)),"") -> 0 | CK15: =IFERROR(IF(AV15<>0,AV15,FORECAST(CK$1,$BM15:$BR15,$BM$1:$BR$1)),"") -> 0 | CL15: =IFERROR(IF(AW15<>0,AW15,FORECAST(CL$1,$BM15:$BR15,$BM$1:$BR$1)),"") -> 0 | CM15: =IFERROR(IF(AX15<>0,AX15,FORECAST(CM$1,$BM15:$BR15,$BM$1:$BR$1)),"") -> 0 | CN15: =IFERROR(IF(AY15<>0,AY15,FORECAST(CN$1,$BM15:$BR15,$BM$1:$BR$1)),"") -> 0 | CO15: =IFERROR(IF(AZ15<>0,AZ15,FORECAST(CO$1,$BM15:$BR15,$BM$1:$BR$1)),"") -> 0 | ... CS15: =IFERROR(IF(BD15<>0,BD15,FORECAST(CS$1,$BM15:$BR15,$BM$1:$BR$1)),"") -> 0 | CT15: =SUM(CH15:CS15) -> 0 | CV15: =SUM(BP15:BR15)/3 -> 0 | CW15: =SUM(BM15:BR15)/6 -> 0 | CX15: =SUM(BG15:BR15)/12 -> 0 | CZ15: =N15+Summary!$E$3*CV15 -> 0 | DA15: =N15+CW15*Summary!$E$3 -> 0 | DB15: =N15+CX15*Summary!$E$3 -> 0
B16: =Mapping!A11 -> Placeholder 6 | C16: =SUMIFS('Sales Data'!$E:$E,'Sales Data'!$A:$A,$B16,'Sales Data'!$B:$B,Summary!$C$3&" "&Summary!$C$2-1,'Sales Data'!$C:$C,"Periodic")/Mapping!$C$2 -> 0 | D16: =SUMIFS('Sales Data'!$D:$D,'Sales Data'!$A:$A,$B16,'Sales Data'!$B:$B,Summary!$C$3&" "&Summary!$C$2,'Sales Data'!$C:$C,"Periodic")/Mapping!$C$2 -> 0 | E16: =SUMIFS('Sales Data'!$E:$E,'Sales Data'!$A:$A,$B16,'Sales Data'!$B:$B,Summary!$C$3&" "&Summary!$C$2,'Sales Data'!$C:$C,"Periodic")/Mapping!$C$2 -> 0 | G16: =E16-C16 -> 0 | H16: =IF(ISERROR((E16/C16)-1),"N/A",(E16/C16)-1) -> N/A | I16: =E16-D16 -> 0 | J16: =IF(ISERROR((E16/D16)-1),"N/A",(E16/D16)-1) -> N/A | L16: =SUMIFS('Sales Data'!$E:$E,'Sales Data'!$A:$A,$B16,'Sales Data'!$F:$F,$C$2-1,'Sales Data'!$G:$G,"<="&$D$3)/Mapping!$C$2 -> 0 | M16: =SUMIFS('Sales Data'!$D:$D,'Sales Data'!$A:$A,$B16,'Sales Data'!$F:$F,$C$2,'Sales Data'!$G:$G,"<="&$D$3)/Mapping!$C$2 -> 0 | N16: =SUMIFS('Sales Data'!$E:$E,'Sales Data'!$A:$A,$B16,'Sales Data'!$F:$F,$C$2,'Sales Data'!$G:$G,"<="&$D$3)/Mapping!$C$2 -> 0 | P16: =N16-L16 -> 0 | Q16: =IF(ISERROR((N16/L16)-1),"N/A",(N16/L16)-1) -> N/A | R16: =N16-M16 -> 0 | S16: =IF(ISERROR((N16/M16)-1),"N/A",(N16/M16)-1) -> N/A | U16: =SUMIFS('Sales Data'!$E:$E,'Sales Data'!$A:$A,$B16,'Sales Data'!$F:$F,$C$2-1,'Sales Data'!$G:$G,"<="&12)/Mapping!$C$2 -> 0 | V16: =SUMIFS('Sales Data'!$D:$D,'Sales Data'!$A:$A,$B16,'Sales Data'!$F:$F,$C$2,'Sales Data'!$G:$G,"<="&12)/Mapping!$C$2 -> 0 | W16: =SUMIFS('Sales Data'!$E:$E,'Sales Data'!$A:$A,$B16,'Sales Data'!$F:$F,$C$2,'Sales Data'!$G:$G,"<="&12)/Mapping!$C$2 -> 0 | Y16: =W16-U16 -> 0 | Z16: =IF(ISERROR((W16/U16)-1),"N/A",(W16/U16)-1) -> N/A | AA16: =W16-V16 -> 0 | AB16: =IF(ISERROR((W16/V16)-1),"N/A",(W16/V16)-1) -> N/A | AC16: =W16-#REF! -> #REF! | AD16: =IF(ISERROR((W16/#REF!)-1),"N/A",(W16/#REF!)-1) -> N/A | AF16: =N16/Summary!$D$3 -> 0 | AG16: =(V16-N16)/Summary!$E$3 -> 0 | AH16: =AG16-AF16 -> 0 | AJ16: =CZ16-V16 -> 0 | AK16: =DA16-V16 -> 0 | AL16: =DB16-V16 -> 0 | AM16: =CT16-V16 -> 0 | AN16: =CF16-V16 -> 0 | AP16: =U16-L16 -> 0 | AQ16: =V16-N16 -> 0 | AS16: =SUMIFS('Sales Data'!$E:$E,'Sales Data'!$A:$A,$B16,'Sales Data'!$B:$B,AS$6,'Sales Data'!$C:$C,"Periodic")/Mapping!$C$2 -> 0 | AT16: =SUMIFS('Sales Data'!$E:$E,'Sales Data'!$A:$A,$B16,'Sales Data'!$B:$B,AT$6,'Sales Data'!$C:$C,"Periodic")/Mapping!$C$2 -> 0 | AU16: =SUMIFS('Sales Data'!$E:$E,'Sales Data'!$A:$A,$B16,'Sales Data'!$B:$B,AU$6,'Sales Data'!$C:$C,"Periodic")/Mapping!$C$2 -> 0 | AV16: =SUMIFS('Sales Data'!$E:$E,'Sales Data'!$A:$A,$B16,'Sales Data'!$B:$B,AV$6,'Sales Data'!$C:$C,"Periodic")/Mapping!$C$2 -> 0 | AW16: =SUMIFS('Sales Data'!$E:$E,'Sales Data'!$A:$A,$B16,'Sales Data'!$B:$B,AW$6,'Sales Data'!$C:$C,"Periodic")/Mapping!$C$2 -> 0 | AX16: =SUMIFS('Sales Data'!$E:$E,'Sales Data'!$A:$A,$B16,'Sales Data'!$B:$B,AX$6,'Sales Data'!$C:$C,"Periodic")/Mapping!$C$2 -> 0 | AY16: =SUMIFS('Sales Data'!$E:$E,'Sales Data'!$A:$A,$B16,'Sales Data'!$B:$B,AY$6,'Sales Data'!$C:$C,"Periodic")/Mapping!$C$2 -> 0 | AZ16: =SUMIFS('Sales Data'!$E:$E,'Sales Data'!$A:$A,$B16,'Sales Data'!$B:$B,AZ$6,'Sales Data'!$C:$C,"Periodic")/Mapping!$C$2 -> 0 | ... BD16: =SUMIFS('Sales Data'!$E:$E,'Sales Data'!$A:$A,$B16,'Sales Data'!$B:$B,BD$6,'Sales Data'!$C:$C,"Periodic")/Mapping!$C$2 -> 0 | BE16: =SUM(AS16:BD16) -> 0 | BG16: =SUMIFS('Sales Data'!$E:$E,'Sales Data'!$A:$A,$B16,'Sales Data'!$B:$B,BG$6,'Sales Data'!$C:$C,"Periodic")/Mapping!$C$2 -> 0 | BH16: =SUMIFS('Sales Data'!$E:$E,'Sales Data'!$A:$A,$B16,'Sales Data'!$B:$B,BH$6,'Sales Data'!$C:$C,"Periodic")/Mapping!$C$2 -> 0 | BI16: =SUMIFS('Sales Data'!$E:$E,'Sales Data'!$A:$A,$B16,'Sales Data'!$B:$B,BI$6,'Sales Data'!$C:$C,"Periodic")/Mapping!$C$2 -> 0 | BJ16: =SUMIFS('Sales Data'!$E:$E,'Sales Data'!$A:$A,$B16,'Sales Data'!$B:$B,BJ$6,'Sales Data'!$C:$C,"Periodic")/Mapping!$C$2 -> 0 | BK16: =SUMIFS('Sales Data'!$E:$E,'Sales Data'!$A:$A,$B16,'Sales Data'!$B:$B,BK$6,'Sales Data'!$C:$C,"Periodic")/Mapping!$C$2 -> 0 | BL16: =SUMIFS('Sales Data'!$E:$E,'Sales Data'!$A:$A,$B16,'Sales Data'!$B:$B,BL$6,'Sales Data'!$C:$C,"Periodic")/Mapping!$C$2 -> 0 | BM16: =SUMIFS('Sales Data'!$E:$E,'Sales Data'!$A:$A,$B16,'Sales Data'!$B:$B,BM$6,'Sales Data'!$C:$C,"Periodic")/Mapping!$C$2 -> 0 | BN16: =SUMIFS('Sales Data'!$E:$E,'Sales Data'!$A:$A,$B16,'Sales Data'!$B:$B,BN$6,'Sales Data'!$C:$C,"Periodic")/Mapping!$C$2 -> 0 | ... BR16: =SUMIFS('Sales Data'!$E:$E,'Sales Data'!$A:$A,$B16,'Sales Data'!$B:$B,BR$6,'Sales Data'!$C:$C,"Periodic")/Mapping!$C$2 -> 0 | BT16: =IFERROR(IF(AS16<>0,AS16,FORECAST(BT$1,$BG16:$BR16,$BG$1:$BR$1)),"") -> 0 | BU16: =IFERROR(IF(AT16<>0,AT16,FORECAST(BU$1,$BG16:$BR16,$BG$1:$BR$1)),"") -> 0 | BV16: =IFERROR(IF(AU16<>0,AU16,FORECAST(BV$1,$BG16:$BR16,$BG$1:$BR$1)),"") -> 0 | BW16: =IFERROR(IF(AV16<>0,AV16,FORECAST(BW$1,$BG16:$BR16,$BG$1:$BR$1)),"") -> 0 | BX16: =IFERROR(IF(AW16<>0,AW16,FORECAST(BX$1,$BG16:$BR16,$BG$1:$BR$1)),"") -> 0 | BY16: =IFERROR(IF(AX16<>0,AX16,FORECAST(BY$1,$BG16:$BR16,$BG$1:$BR$1)),"") -> 0 | BZ16: =IFERROR(IF(AY16<>0,AY16,FORECAST(BZ$1,$BG16:$BR16,$BG$1:$BR$1)),"") -> 0 | CA16: =IFERROR(IF(AZ16<>0,AZ16,FORECAST(CA$1,$BG16:$BR16,$BG$1:$BR$1)),"") -> 0 | ... CE16: =IFERROR(IF(BD16<>0,BD16,FORECAST(CE$1,$BG16:$BR16,$BG$1:$BR$1)),"") -> 0 | CF16: =SUM(BT16:CE16) -> 0 | CH16: =IFERROR(IF(AS16<>0,AS16,FORECAST(CH$1,$BM16:$BR16,$BM$1:$BR$1)),"") -> 0 | CI16: =IFERROR(IF(AT16<>0,AT16,FORECAST(CI$1,$BM16:$BR16,$BM$1:$BR$1)),"") -> 0 | CJ16: =IFERROR(IF(AU16<>0,AU16,FORECAST(CJ$1,$BM16:$BR16,$BM$1:$BR$1)),"") -> 0 | CK16: =IFERROR(IF(AV16<>0,AV16,FORECAST(CK$1,$BM16:$BR16,$BM$1:$BR$1)),"") -> 0 | CL16: =IFERROR(IF(AW16<>0,AW16,FORECAST(CL$1,$BM16:$BR16,$BM$1:$BR$1)),"") -> 0 | CM16: =IFERROR(IF(AX16<>0,AX16,FORECAST(CM$1,$BM16:$BR16,$BM$1:$BR$1)),"") -> 0 | CN16: =IFERROR(IF(AY16<>0,AY16,FORECAST(CN$1,$BM16:$BR16,$BM$1:$BR$1)),"") -> 0 | CO16: =IFERROR(IF(AZ16<>0,AZ16,FORECAST(CO$1,$BM16:$BR16,$BM$1:$BR$1)),"") -> 0 | ... CS16: =IFERROR(IF(BD16<>0,BD16,FORECAST(CS$1,$BM16:$BR16,$BM$1:$BR$1)),"") -> 0 | CT16: =SUM(CH16:CS16) -> 0 | CV16: =SUM(BP16:BR16)/3 -> 0 | CW16: =SUM(BM16:BR16)/6 -> 0 | CX16: =SUM(BG16:BR16)/12 -> 0 | CZ16: =N16+Summary!$E$3*CV16 -> 0 | DA16: =N16+CW16*Summary!$E$3 -> 0 | DB16: =N16+CX16*Summary!$E$3 -> 0
B17: =Mapping!A12 -> Placeholder 7 | C17: =SUMIFS('Sales Data'!$E:$E,'Sales Data'!$A:$A,$B17,'Sales Data'!$B:$B,Summary!$C$3&" "&Summary!$C$2-1,'Sales Data'!$C:$C,"Periodic")/Mapping!$C$2 -> 0 | D17: =SUMIFS('Sales Data'!$D:$D,'Sales Data'!$A:$A,$B17,'Sales Data'!$B:$B,Summary!$C$3&" "&Summary!$C$2,'Sales Data'!$C:$C,"Periodic")/Mapping!$C$2 -> 0 | E17: =SUMIFS('Sales Data'!$E:$E,'Sales Data'!$A:$A,$B17,'Sales Data'!$B:$B,Summary!$C$3&" "&Summary!$C$2,'Sales Data'!$C:$C,"Periodic")/Mapping!$C$2 -> 0 | G17: =E17-C17 -> 0 | H17: =IF(ISERROR((E17/C17)-1),"N/A",(E17/C17)-1) -> N/A | I17: =E17-D17 -> 0 | J17: =IF(ISERROR((E17/D17)-1),"N/A",(E17/D17)-1) -> N/A | L17: =SUMIFS('Sales Data'!$E:$E,'Sales Data'!$A:$A,$B17,'Sales Data'!$F:$F,$C$2-1,'Sales Data'!$G:$G,"<="&$D$3)/Mapping!$C$2 -> 0 | M17: =SUMIFS('Sales Data'!$D:$D,'Sales Data'!$A:$A,$B17,'Sales Data'!$F:$F,$C$2,'Sales Data'!$G:$G,"<="&$D$3)/Mapping!$C$2 -> 0 | N17: =SUMIFS('Sales Data'!$E:$E,'Sales Data'!$A:$A,$B17,'Sales Data'!$F:$F,$C$2,'Sales Data'!$G:$G,"<="&$D$3)/Mapping!$C$2 -> 0 | P17: =N17-L17 -> 0 | Q17: =IF(ISERROR((N17/L17)-1),"N/A",(N17/L17)-1) -> N/A | R17: =N17-M17 -> 0 | S17: =IF(ISERROR((N17/M17)-1),"N/A",(N17/M17)-1) -> N/A | U17: =SUMIFS('Sales Data'!$E:$E,'Sales Data'!$A:$A,$B17,'Sales Data'!$F:$F,$C$2-1,'Sales Data'!$G:$G,"<="&12)/Mapping!$C$2 -> 0 | V17: =SUMIFS('Sales Data'!$D:$D,'Sales Data'!$A:$A,$B17,'Sales Data'!$F:$F,$C$2,'Sales Data'!$G:$G,"<="&12)/Mapping!$C$2 -> 0 | W17: =SUMIFS('Sales Data'!$E:$E,'Sales Data'!$A:$A,$B17,'Sales Data'!$F:$F,$C$2,'Sales Data'!$G:$G,"<="&12)/Mapping!$C$2 -> 0 | Y17: =W17-U17 -> 0 | Z17: =IF(ISERROR((W17/U17)-1),"N/A",(W17/U17)-1) -> N/A | AA17: =W17-V17 -> 0 | AB17: =IF(ISERROR((W17/V17)-1),"N/A",(W17/V17)-1) -> N/A | AC17: =W17-#REF! -> #REF! | AD17: =IF(ISERROR((W17/#REF!)-1),"N/A",(W17/#REF!)-1) -> N/A | AF17: =N17/Summary!$D$3 -> 0 | AG17: =(V17-N17)/Summary!$E$3 -> 0 | AH17: =AG17-AF17 -> 0 | AJ17: =CZ17-V17 -> 0 | AK17: =DA17-V17 -> 0 | AL17: =DB17-V17 -> 0 | AM17: =CT17-V17 -> 0 | AN17: =CF17-V17 -> 0 | AP17: =U17-L17 -> 0 | AQ17: =V17-N17 -> 0 | AS17: =SUMIFS('Sales Data'!$E:$E,'Sales Data'!$A:$A,$B17,'Sales Data'!$B:$B,AS$6,'Sales Data'!$C:$C,"Periodic")/Mapping!$C$2 -> 0 | AT17: =SUMIFS('Sales Data'!$E:$E,'Sales Data'!$A:$A,$B17,'Sales Data'!$B:$B,AT$6,'Sales Data'!$C:$C,"Periodic")/Mapping!$C$2 -> 0 | AU17: =SUMIFS('Sales Data'!$E:$E,'Sales Data'!$A:$A,$B17,'Sales Data'!$B:$B,AU$6,'Sales Data'!$C:$C,"Periodic")/Mapping!$C$2 -> 0 | AV17: =SUMIFS('Sales Data'!$E:$E,'Sales Data'!$A:$A,$B17,'Sales Data'!$B:$B,AV$6,'Sales Data'!$C:$C,"Periodic")/Mapping!$C$2 -> 0 | AW17: =SUMIFS('Sales Data'!$E:$E,'Sales Data'!$A:$A,$B17,'Sales Data'!$B:$B,AW$6,'Sales Data'!$C:$C,"Periodic")/Mapping!$C$2 -> 0 | AX17: =SUMIFS('Sales Data'!$E:$E,'Sales Data'!$A:$A,$B17,'Sales Data'!$B:$B,AX$6,'Sales Data'!$C:$C,"Periodic")/Mapping!$C$2 -> 0 | AY17: =SUMIFS('Sales Data'!$E:$E,'Sales Data'!$A:$A,$B17,'Sales Data'!$B:$B,AY$6,'Sales Data'!$C:$C,"Periodic")/Mapping!$C$2 -> 0 | AZ17: =SUMIFS('Sales Data'!$E:$E,'Sales Data'!$A:$A,$B17,'Sales Data'!$B:$B,AZ$6,'Sales Data'!$C:$C,"Periodic")/Mapping!$C$2 -> 0 | ... BD17: =SUMIFS('Sales Data'!$E:$E,'Sales Data'!$A:$A,$B17,'Sales Data'!$B:$B,BD$6,'Sales Data'!$C:$C,"Periodic")/Mapping!$C$2 -> 0 | BE17: =SUM(AS17:BD17) -> 0 | BG17: =SUMIFS('Sales Data'!$E:$E,'Sales Data'!$A:$A,$B17,'Sales Data'!$B:$B,BG$6,'Sales Data'!$C:$C,"Periodic")/Mapping!$C$2 -> 0 | BH17: =SUMIFS('Sales Data'!$E:$E,'Sales Data'!$A:$A,$B17,'Sales Data'!$B:$B,BH$6,'Sales Data'!$C:$C,"Periodic")/Mapping!$C$2 -> 0 | BI17: =SUMIFS('Sales Data'!$E:$E,'Sales Data'!$A:$A,$B17,'Sales Data'!$B:$B,BI$6,'Sales Data'!$C:$C,"Periodic")/Mapping!$C$2 -> 0 | BJ17: =SUMIFS('Sales Data'!$E:$E,'Sales Data'!$A:$A,$B17,'Sales Data'!$B:$B,BJ$6,'Sales Data'!$C:$C,"Periodic")/Mapping!$C$2 -> 0 | BK17: =SUMIFS('Sales Data'!$E:$E,'Sales Data'!$A:$A,$B17,'Sales Data'!$B:$B,BK$6,'Sales Data'!$C:$C,"Periodic")/Mapping!$C$2 -> 0 | BL17: =SUMIFS('Sales Data'!$E:$E,'Sales Data'!$A:$A,$B17,'Sales Data'!$B:$B,BL$6,'Sales Data'!$C:$C,"Periodic")/Mapping!$C$2 -> 0 | BM17: =SUMIFS('Sales Data'!$E:$E,'Sales Data'!$A:$A,$B17,'Sales Data'!$B:$B,BM$6,'Sales Data'!$C:$C,"Periodic")/Mapping!$C$2 -> 0 | BN17: =SUMIFS('Sales Data'!$E:$E,'Sales Data'!$A:$A,$B17,'Sales Data'!$B:$B,BN$6,'Sales Data'!$C:$C,"Periodic")/Mapping!$C$2 -> 0 | ... BR17: =SUMIFS('Sales Data'!$E:$E,'Sales Data'!$A:$A,$B17,'Sales Data'!$B:$B,BR$6,'Sales Data'!$C:$C,"Periodic")/Mapping!$C$2 -> 0 | BT17: =IFERROR(IF(AS17<>0,AS17,FORECAST(BT$1,$BG17:$BR17,$BG$1:$BR$1)),"") -> 0 | BU17: =IFERROR(IF(AT17<>0,AT17,FORECAST(BU$1,$BG17:$BR17,$BG$1:$BR$1)),"") -> 0 | BV17: =IFERROR(IF(AU17<>0,AU17,FORECAST(BV$1,$BG17:$BR17,$BG$1:$BR$1)),"") -> 0 | BW17: =IFERROR(IF(AV17<>0,AV17,FORECAST(BW$1,$BG17:$BR17,$BG$1:$BR$1)),"") -> 0 | BX17: =IFERROR(IF(AW17<>0,AW17,FORECAST(BX$1,$BG17:$BR17,$BG$1:$BR$1)),"") -> 0 | BY17: =IFERROR(IF(AX17<>0,AX17,FORECAST(BY$1,$BG17:$BR17,$BG$1:$BR$1)),"") -> 0 | BZ17: =IFERROR(IF(AY17<>0,AY17,FORECAST(BZ$1,$BG17:$BR17,$BG$1:$BR$1)),"") -> 0 | CA17: =IFERROR(IF(AZ17<>0,AZ17,FORECAST(CA$1,$BG17:$BR17,$BG$1:$BR$1)),"") -> 0 | ... CE17: =IFERROR(IF(BD17<>0,BD17,FORECAST(CE$1,$BG17:$BR17,$BG$1:$BR$1)),"") -> 0 | CF17: =SUM(BT17:CE17) -> 0 | CH17: =IFERROR(IF(AS17<>0,AS17,FORECAST(CH$1,$BM17:$BR17,$BM$1:$BR$1)),"") -> 0 | CI17: =IFERROR(IF(AT17<>0,AT17,FORECAST(CI$1,$BM17:$BR17,$BM$1:$BR$1)),"") -> 0 | CJ17: =IFERROR(IF(AU17<>0,AU17,FORECAST(CJ$1,$BM17:$BR17,$BM$1:$BR$1)),"") -> 0 | CK17: =IFERROR(IF(AV17<>0,AV17,FORECAST(CK$1,$BM17:$BR17,$BM$1:$BR$1)),"") -> 0 | CL17: =IFERROR(IF(AW17<>0,AW17,FORECAST(CL$1,$BM17:$BR17,$BM$1:$BR$1)),"") -> 0 | CM17: =IFERROR(IF(AX17<>0,AX17,FORECAST(CM$1,$BM17:$BR17,$BM$1:$BR$1)),"") -> 0 | CN17: =IFERROR(IF(AY17<>0,AY17,FORECAST(CN$1,$BM17:$BR17,$BM$1:$BR$1)),"") -> 0 | CO17: =IFERROR(IF(AZ17<>0,AZ17,FORECAST(CO$1,$BM17:$BR17,$BM$1:$BR$1)),"") -> 0 | ... CS17: =IFERROR(IF(BD17<>0,BD17,FORECAST(CS$1,$BM17:$BR17,$BM$1:$BR$1)),"") -> 0 | CT17: =SUM(CH17:CS17) -> 0 | CV17: =SUM(BP17:BR17)/3 -> 0 | CW17: =SUM(BM17:BR17)/6 -> 0 | CX17: =SUM(BG17:BR17)/12 -> 0 | CZ17: =N17+Summary!$E$3*CV17 -> 0 | DA17: =N17+CW17*Summary!$E$3 -> 0 | DB17: =N17+CX17*Summary!$E$3 -> 0
B18: =Mapping!A13 -> Placeholder 8 | C18: =SUMIFS('Sales Data'!$E:$E,'Sales Data'!$A:$A,$B18,'Sales Data'!$B:$B,Summary!$C$3&" "&Summary!$C$2-1,'Sales Data'!$C:$C,"Periodic")/Mapping!$C$2 -> 0 | D18: =SUMIFS('Sales Data'!$D:$D,'Sales Data'!$A:$A,$B18,'Sales Data'!$B:$B,Summary!$C$3&" "&Summary!$C$2,'Sales Data'!$C:$C,"Periodic")/Mapping!$C$2 -> 0 | E18: =SUMIFS('Sales Data'!$E:$E,'Sales Data'!$A:$A,$B18,'Sales Data'!$B:$B,Summary!$C$3&" "&Summary!$C$2,'Sales Data'!$C:$C,"Periodic")/Mapping!$C$2 -> 0 | G18: =E18-C18 -> 0 | H18: =IF(ISERROR((E18/C18)-1),"N/A",(E18/C18)-1) -> N/A | I18: =E18-D18 -> 0 | J18: =IF(ISERROR((E18/D18)-1),"N/A",(E18/D18)-1) -> N/A | L18: =SUMIFS('Sales Data'!$E:$E,'Sales Data'!$A:$A,$B18,'Sales Data'!$F:$F,$C$2-1,'Sales Data'!$G:$G,"<="&$D$3)/Mapping!$C$2 -> 0 | M18: =SUMIFS('Sales Data'!$D:$D,'Sales Data'!$A:$A,$B18,'Sales Data'!$F:$F,$C$2,'Sales Data'!$G:$G,"<="&$D$3)/Mapping!$C$2 -> 0 | N18: =SUMIFS('Sales Data'!$E:$E,'Sales Data'!$A:$A,$B18,'Sales Data'!$F:$F,$C$2,'Sales Data'!$G:$G,"<="&$D$3)/Mapping!$C$2 -> 0 | P18: =N18-L18 -> 0 | Q18: =IF(ISERROR((N18/L18)-1),"N/A",(N18/L18)-1) -> N/A | R18: =N18-M18 -> 0 | S18: =IF(ISERROR((N18/M18)-1),"N/A",(N18/M18)-1) -> N/A | U18: =SUMIFS('Sales Data'!$E:$E,'Sales Data'!$A:$A,$B18,'Sales Data'!$F:$F,$C$2-1,'Sales Data'!$G:$G,"<="&12)/Mapping!$C$2 -> 0 | V18: =SUMIFS('Sales Data'!$D:$D,'Sales Data'!$A:$A,$B18,'Sales Data'!$F:$F,$C$2,'Sales Data'!$G:$G,"<="&12)/Mapping!$C$2 -> 0 | W18: =SUMIFS('Sales Data'!$E:$E,'Sales Data'!$A:$A,$B18,'Sales Data'!$F:$F,$C$2,'Sales Data'!$G:$G,"<="&12)/Mapping!$C$2 -> 0 | Y18: =W18-U18 -> 0 | Z18: =IF(ISERROR((W18/U18)-1),"N/A",(W18/U18)-1) -> N/A | AA18: =W18-V18 -> 0 | AB18: =IF(ISERROR((W18/V18)-1),"N/A",(W18/V18)-1) -> N/A | AC18: =W18-#REF! -> #REF! | AD18: =IF(ISERROR((W18/#REF!)-1),"N/A",(W18/#REF!)-1) -> N/A | AF18: =N18/Summary!$D$3 -> 0 | AG18: =(V18-N18)/Summary!$E$3 -> 0 | AH18: =AG18-AF18 -> 0 | AJ18: =CZ18-V18 -> 0 | AK18: =DA18-V18 -> 0 | AL18: =DB18-V18 -> 0 | AM18: =CT18-V18 -> 0 | AN18: =CF18-V18 -> 0 | AP18: =U18-L18 -> 0 | AQ18: =V18-N18 -> 0 | AS18: =SUMIFS('Sales Data'!$E:$E,'Sales Data'!$A:$A,$B18,'Sales Data'!$B:$B,AS$6,'Sales Data'!$C:$C,"Periodic")/Mapping!$C$2 -> 0 | AT18: =SUMIFS('Sales Data'!$E:$E,'Sales Data'!$A:$A,$B18,'Sales Data'!$B:$B,AT$6,'Sales Data'!$C:$C,"Periodic")/Mapping!$C$2 -> 0 | AU18: =SUMIFS('Sales Data'!$E:$E,'Sales Data'!$A:$A,$B18,'Sales Data'!$B:$B,AU$6,'Sales Data'!$C:$C,"Periodic")/Mapping!$C$2 -> 0 | AV18: =SUMIFS('Sales Data'!$E:$E,'Sales Data'!$A:$A,$B18,'Sales Data'!$B:$B,AV$6,'Sales Data'!$C:$C,"Periodic")/Mapping!$C$2 -> 0 | AW18: =SUMIFS('Sales Data'!$E:$E,'Sales Data'!$A:$A,$B18,'Sales Data'!$B:$B,AW$6,'Sales Data'!$C:$C,"Periodic")/Mapping!$C$2 -> 0 | AX18: =SUMIFS('Sales Data'!$E:$E,'Sales Data'!$A:$A,$B18,'Sales Data'!$B:$B,AX$6,'Sales Data'!$C:$C,"Periodic")/Mapping!$C$2 -> 0 | AY18: =SUMIFS('Sales Data'!$E:$E,'Sales Data'!$A:$A,$B18,'Sales Data'!$B:$B,AY$6,'Sales Data'!$C:$C,"Periodic")/Mapping!$C$2 -> 0 | AZ18: =SUMIFS('Sales Data'!$E:$E,'Sales Data'!$A:$A,$B18,'Sales Data'!$B:$B,AZ$6,'Sales Data'!$C:$C,"Periodic")/Mapping!$C$2 -> 0 | ... BD18: =SUMIFS('Sales Data'!$E:$E,'Sales Data'!$A:$A,$B18,'Sales Data'!$B:$B,BD$6,'Sales Data'!$C:$C,"Periodic")/Mapping!$C$2 -> 0 | BE18: =SUM(AS18:BD18) -> 0 | BG18: =SUMIFS('Sales Data'!$E:$E,'Sales Data'!$A:$A,$B18,'Sales Data'!$B:$B,BG$6,'Sales Data'!$C:$C,"Periodic")/Mapping!$C$2 -> 0 | BH18: =SUMIFS('Sales Data'!$E:$E,'Sales Data'!$A:$A,$B18,'Sales Data'!$B:$B,BH$6,'Sales Data'!$C:$C,"Periodic")/Mapping!$C$2 -> 0 | BI18: =SUMIFS('Sales Data'!$E:$E,'Sales Data'!$A:$A,$B18,'Sales Data'!$B:$B,BI$6,'Sales Data'!$C:$C,"Periodic")/Mapping!$C$2 -> 0 | BJ18: =SUMIFS('Sales Data'!$E:$E,'Sales Data'!$A:$A,$B18,'Sales Data'!$B:$B,BJ$6,'Sales Data'!$C:$C,"Periodic")/Mapping!$C$2 -> 0 | BK18: =SUMIFS('Sales Data'!$E:$E,'Sales Data'!$A:$A,$B18,'Sales Data'!$B:$B,BK$6,'Sales Data'!$C:$C,"Periodic")/Mapping!$C$2 -> 0 | BL18: =SUMIFS('Sales Data'!$E:$E,'Sales Data'!$A:$A,$B18,'Sales Data'!$B:$B,BL$6,'Sales Data'!$C:$C,"Periodic")/Mapping!$C$2 -> 0 | BM18: =SUMIFS('Sales Data'!$E:$E,'Sales Data'!$A:$A,$B18,'Sales Data'!$B:$B,BM$6,'Sales Data'!$C:$C,"Periodic")/Mapping!$C$2 -> 0 | BN18: =SUMIFS('Sales Data'!$E:$E,'Sales Data'!$A:$A,$B18,'Sales Data'!$B:$B,BN$6,'Sales Data'!$C:$C,"Periodic")/Mapping!$C$2 -> 0 | ... BR18: =SUMIFS('Sales Data'!$E:$E,'Sales Data'!$A:$A,$B18,'Sales Data'!$B:$B,BR$6,'Sales Data'!$C:$C,"Periodic")/Mapping!$C$2 -> 0 | BT18: =IFERROR(IF(AS18<>0,AS18,FORECAST(BT$1,$BG18:$BR18,$BG$1:$BR$1)),"") -> 0 | BU18: =IFERROR(IF(AT18<>0,AT18,FORECAST(BU$1,$BG18:$BR18,$BG$1:$BR$1)),"") -> 0 | BV18: =IFERROR(IF(AU18<>0,AU18,FORECAST(BV$1,$BG18:$BR18,$BG$1:$BR$1)),"") -> 0 | BW18: =IFERROR(IF(AV18<>0,AV18,FORECAST(BW$1,$BG18:$BR18,$BG$1:$BR$1)),"") -> 0 | BX18: =IFERROR(IF(AW18<>0,AW18,FORECAST(BX$1,$BG18:$BR18,$BG$1:$BR$1)),"") -> 0 | BY18: =IFERROR(IF(AX18<>0,AX18,FORECAST(BY$1,$BG18:$BR18,$BG$1:$BR$1)),"") -> 0 | BZ18: =IFERROR(IF(AY18<>0,AY18,FORECAST(BZ$1,$BG18:$BR18,$BG$1:$BR$1)),"") -> 0 | CA18: =IFERROR(IF(AZ18<>0,AZ18,FORECAST(CA$1,$BG18:$BR18,$BG$1:$BR$1)),"") -> 0 | ... CE18: =IFERROR(IF(BD18<>0,BD18,FORECAST(CE$1,$BG18:$BR18,$BG$1:$BR$1)),"") -> 0 | CF18: =SUM(BT18:CE18) -> 0 | CH18: =IFERROR(IF(AS18<>0,AS18,FORECAST(CH$1,$BM18:$BR18,$BM$1:$BR$1)),"") -> 0 | CI18: =IFERROR(IF(AT18<>0,AT18,FORECAST(CI$1,$BM18:$BR18,$BM$1:$BR$1)),"") -> 0 | CJ18: =IFERROR(IF(AU18<>0,AU18,FORECAST(CJ$1,$BM18:$BR18,$BM$1:$BR$1)),"") -> 0 | CK18: =IFERROR(IF(AV18<>0,AV18,FORECAST(CK$1,$BM18:$BR18,$BM$1:$BR$1)),"") -> 0 | CL18: =IFERROR(IF(AW18<>0,AW18,FORECAST(CL$1,$BM18:$BR18,$BM$1:$BR$1)),"") -> 0 | CM18: =IFERROR(IF(AX18<>0,AX18,FORECAST(CM$1,$BM18:$BR18,$BM$1:$BR$1)),"") -> 0 | CN18: =IFERROR(IF(AY18<>0,AY18,FORECAST(CN$1,$BM18:$BR18,$BM$1:$BR$1)),"") -> 0 | CO18: =IFERROR(IF(AZ18<>0,AZ18,FORECAST(CO$1,$BM18:$BR18,$BM$1:$BR$1)),"") -> 0 | ... CS18: =IFERROR(IF(BD18<>0,BD18,FORECAST(CS$1,$BM18:$BR18,$BM$1:$BR$1)),"") -> 0 | CT18: =SUM(CH18:CS18) -> 0 | CV18: =SUM(BP18:BR18)/3 -> 0 | CW18: =SUM(BM18:BR18)/6 -> 0 | CX18: =SUM(BG18:BR18)/12 -> 0 | CZ18: =N18+Summary!$E$3*CV18 -> 0 | DA18: =N18+CW18*Summary!$E$3 -> 0 | DB18: =N18+CX18*Summary!$E$3 -> 0
B19: =Mapping!A14 -> Placeholder 9 | C19: =SUMIFS('Sales Data'!$E:$E,'Sales Data'!$A:$A,$B19,'Sales Data'!$B:$B,Summary!$C$3&" "&Summary!$C$2-1,'Sales Data'!$C:$C,"Periodic")/Mapping!$C$2 -> 0 | D19: =SUMIFS('Sales Data'!$D:$D,'Sales Data'!$A:$A,$B19,'Sales Data'!$B:$B,Summary!$C$3&" "&Summary!$C$2,'Sales Data'!$C:$C,"Periodic")/Mapping!$C$2 -> 0 | E19: =SUMIFS('Sales Data'!$E:$E,'Sales Data'!$A:$A,$B19,'Sales Data'!$B:$B,Summary!$C$3&" "&Summary!$C$2,'Sales Data'!$C:$C,"Periodic")/Mapping!$C$2 -> 0 | G19: =E19-C19 -> 0 | H19: =IF(ISERROR((E19/C19)-1),"N/A",(E19/C19)-1) -> N/A | I19: =E19-D19 -> 0 | J19: =IF(ISERROR((E19/D19)-1),"N/A",(E19/D19)-1) -> N/A | L19: =SUMIFS('Sales Data'!$E:$E,'Sales Data'!$A:$A,$B19,'Sales Data'!$F:$F,$C$2-1,'Sales Data'!$G:$G,"<="&$D$3)/Mapping!$C$2 -> 0 | M19: =SUMIFS('Sales Data'!$D:$D,'Sales Data'!$A:$A,$B19,'Sales Data'!$F:$F,$C$2,'Sales Data'!$G:$G,"<="&$D$3)/Mapping!$C$2 -> 0 | N19: =SUMIFS('Sales Data'!$E:$E,'Sales Data'!$A:$A,$B19,'Sales Data'!$F:$F,$C$2,'Sales Data'!$G:$G,"<="&$D$3)/Mapping!$C$2 -> 0 | P19: =N19-L19 -> 0 | Q19: =IF(ISERROR((N19/L19)-1),"N/A",(N19/L19)-1) -> N/A | R19: =N19-M19 -> 0 | S19: =IF(ISERROR((N19/M19)-1),"N/A",(N19/M19)-1) -> N/A | U19: =SUMIFS('Sales Data'!$E:$E,'Sales Data'!$A:$A,$B19,'Sales Data'!$F:$F,$C$2-1,'Sales Data'!$G:$G,"<="&12)/Mapping!$C$2 -> 0 | V19: =SUMIFS('Sales Data'!$D:$D,'Sales Data'!$A:$A,$B19,'Sales Data'!$F:$F,$C$2,'Sales Data'!$G:$G,"<="&12)/Mapping!$C$2 -> 0 | W19: =SUMIFS('Sales Data'!$E:$E,'Sales Data'!$A:$A,$B19,'Sales Data'!$F:$F,$C$2,'Sales Data'!$G:$G,"<="&12)/Mapping!$C$2 -> 0 | Y19: =W19-U19 -> 0 | Z19: =IF(ISERROR((W19/U19)-1),"N/A",(W19/U19)-1) -> N/A | AA19: =W19-V19 -> 0 | AB19: =IF(ISERROR((W19/V19)-1),"N/A",(W19/V19)-1) -> N/A | AC19: =W19-#REF! -> #REF! | AD19: =IF(ISERROR((W19/#REF!)-1),"N/A",(W19/#REF!)-1) -> N/A | AF19: =N19/Summary!$D$3 -> 0 | AG19: =(V19-N19)/Summary!$E$3 -> 0 | AH19: =AG19-AF19 -> 0 | AJ19: =CZ19-V19 -> 0 | AK19: =DA19-V19 -> 0 | AL19: =DB19-V19 -> 0 | AM19: =CT19-V19 -> 0 | AN19: =CF19-V19 -> 0 | AP19: =U19-L19 -> 0 | AQ19: =V19-N19 -> 0 | AS19: =SUMIFS('Sales Data'!$E:$E,'Sales Data'!$A:$A,$B19,'Sales Data'!$B:$B,AS$6,'Sales Data'!$C:$C,"Periodic")/Mapping!$C$2 -> 0 | AT19: =SUMIFS('Sales Data'!$E:$E,'Sales Data'!$A:$A,$B19,'Sales Data'!$B:$B,AT$6,'Sales Data'!$C:$C,"Periodic")/Mapping!$C$2 -> 0 | AU19: =SUMIFS('Sales Data'!$E:$E,'Sales Data'!$A:$A,$B19,'Sales Data'!$B:$B,AU$6,'Sales Data'!$C:$C,"Periodic")/Mapping!$C$2 -> 0 | AV19: =SUMIFS('Sales Data'!$E:$E,'Sales Data'!$A:$A,$B19,'Sales Data'!$B:$B,AV$6,'Sales Data'!$C:$C,"Periodic")/Mapping!$C$2 -> 0 | AW19: =SUMIFS('Sales Data'!$E:$E,'Sales Data'!$A:$A,$B19,'Sales Data'!$B:$B,AW$6,'Sales Data'!$C:$C,"Periodic")/Mapping!$C$2 -> 0 | AX19: =SUMIFS('Sales Data'!$E:$E,'Sales Data'!$A:$A,$B19,'Sales Data'!$B:$B,AX$6,'Sales Data'!$C:$C,"Periodic")/Mapping!$C$2 -> 0 | AY19: =SUMIFS('Sales Data'!$E:$E,'Sales Data'!$A:$A,$B19,'Sales Data'!$B:$B,AY$6,'Sales Data'!$C:$C,"Periodic")/Mapping!$C$2 -> 0 | AZ19: =SUMIFS('Sales Data'!$E:$E,'Sales Data'!$A:$A,$B19,'Sales Data'!$B:$B,AZ$6,'Sales Data'!$C:$C,"Periodic")/Mapping!$C$2 -> 0 | ... BD19: =SUMIFS('Sales Data'!$E:$E,'Sales Data'!$A:$A,$B19,'Sales Data'!$B:$B,BD$6,'Sales Data'!$C:$C,"Periodic")/Mapping!$C$2 -> 0 | BE19: =SUM(AS19:BD19) -> 0 | BG19: =SUMIFS('Sales Data'!$E:$E,'Sales Data'!$A:$A,$B19,'Sales Data'!$B:$B,BG$6,'Sales Data'!$C:$C,"Periodic")/Mapping!$C$2 -> 0 | BH19: =SUMIFS('Sales Data'!$E:$E,'Sales Data'!$A:$A,$B19,'Sales Data'!$B:$B,BH$6,'Sales Data'!$C:$C,"Periodic")/Mapping!$C$2 -> 0 | BI19: =SUMIFS('Sales Data'!$E:$E,'Sales Data'!$A:$A,$B19,'Sales Data'!$B:$B,BI$6,'Sales Data'!$C:$C,"Periodic")/Mapping!$C$2 -> 0 | BJ19: =SUMIFS('Sales Data'!$E:$E,'Sales Data'!$A:$A,$B19,'Sales Data'!$B:$B,BJ$6,'Sales Data'!$C:$C,"Periodic")/Mapping!$C$2 -> 0 | BK19: =SUMIFS('Sales Data'!$E:$E,'Sales Data'!$A:$A,$B19,'Sales Data'!$B:$B,BK$6,'Sales Data'!$C:$C,"Periodic")/Mapping!$C$2 -> 0 | BL19: =SUMIFS('Sales Data'!$E:$E,'Sales Data'!$A:$A,$B19,'Sales Data'!$B:$B,BL$6,'Sales Data'!$C:$C,"Periodic")/Mapping!$C$2 -> 0 | BM19: =SUMIFS('Sales Data'!$E:$E,'Sales Data'!$A:$A,$B19,'Sales Data'!$B:$B,BM$6,'Sales Data'!$C:$C,"Periodic")/Mapping!$C$2 -> 0 | BN19: =SUMIFS('Sales Data'!$E:$E,'Sales Data'!$A:$A,$B19,'Sales Data'!$B:$B,BN$6,'Sales Data'!$C:$C,"Periodic")/Mapping!$C$2 -> 0 | ... BR19: =SUMIFS('Sales Data'!$E:$E,'Sales Data'!$A:$A,$B19,'Sales Data'!$B:$B,BR$6,'Sales Data'!$C:$C,"Periodic")/Mapping!$C$2 -> 0 | BT19: =IFERROR(IF(AS19<>0,AS19,FORECAST(BT$1,$BG19:$BR19,$BG$1:$BR$1)),"") -> 0 | BU19: =IFERROR(IF(AT19<>0,AT19,FORECAST(BU$1,$BG19:$BR19,$BG$1:$BR$1)),"") -> 0 | BV19: =IFERROR(IF(AU19<>0,AU19,FORECAST(BV$1,$BG19:$BR19,$BG$1:$BR$1)),"") -> 0 | BW19: =IFERROR(IF(AV19<>0,AV19,FORECAST(BW$1,$BG19:$BR19,$BG$1:$BR$1)),"") -> 0 | BX19: =IFERROR(IF(AW19<>0,AW19,FORECAST(BX$1,$BG19:$BR19,$BG$1:$BR$1)),"") -> 0 | BY19: =IFERROR(IF(AX19<>0,AX19,FORECAST(BY$1,$BG19:$BR19,$BG$1:$BR$1)),"") -> 0 | BZ19: =IFERROR(IF(AY19<>0,AY19,FORECAST(BZ$1,$BG19:$BR19,$BG$1:$BR$1)),"") -> 0 | CA19: =IFERROR(IF(AZ19<>0,AZ19,FORECAST(CA$1,$BG19:$BR19,$BG$1:$BR$1)),"") -> 0 | ... CE19: =IFERROR(IF(BD19<>0,BD19,FORECAST(CE$1,$BG19:$BR19,$BG$1:$BR$1)),"") -> 0 | CF19: =SUM(BT19:CE19) -> 0 | CH19: =IFERROR(IF(AS19<>0,AS19,FORECAST(CH$1,$BM19:$BR19,$BM$1:$BR$1)),"") -> 0 | CI19: =IFERROR(IF(AT19<>0,AT19,FORECAST(CI$1,$BM19:$BR19,$BM$1:$BR$1)),"") -> 0 | CJ19: =IFERROR(IF(AU19<>0,AU19,FORECAST(CJ$1,$BM19:$BR19,$BM$1:$BR$1)),"") -> 0 | CK19: =IFERROR(IF(AV19<>0,AV19,FORECAST(CK$1,$BM19:$BR19,$BM$1:$BR$1)),"") -> 0 | CL19: =IFERROR(IF(AW19<>0,AW19,FORECAST(CL$1,$BM19:$BR19,$BM$1:$BR$1)),"") -> 0 | CM19: =IFERROR(IF(AX19<>0,AX19,FORECAST(CM$1,$BM19:$BR19,$BM$1:$BR$1)),"") -> 0 | CN19: =IFERROR(IF(AY19<>0,AY19,FORECAST(CN$1,$BM19:$BR19,$BM$1:$BR$1)),"") -> 0 | CO19: =IFERROR(IF(AZ19<>0,AZ19,FORECAST(CO$1,$BM19:$BR19,$BM$1:$BR$1)),"") -> 0 | ... CS19: =IFERROR(IF(BD19<>0,BD19,FORECAST(CS$1,$BM19:$BR19,$BM$1:$BR$1)),"") -> 0 | CT19: =SUM(CH19:CS19) -> 0 | CV19: =SUM(BP19:BR19)/3 -> 0 | CW19: =SUM(BM19:BR19)/6 -> 0 | CX19: =SUM(BG19:BR19)/12 -> 0 | CZ19: =N19+Summary!$E$3*CV19 -> 0 | DA19: =N19+CW19*Summary!$E$3 -> 0 | DB19: =N19+CX19*Summary!$E$3 -> 0
... B24: =Mapping!A19 -> Placeholder 14 | C24: =SUMIFS('Sales Data'!$E:$E,'Sales Data'!$A:$A,$B24,'Sales Data'!$B:$B,Summary!$C$3&" "&Summary!$C$2-1,'Sales Data'!$C:$C,"Periodic")/Mapping!$C$2 -> 0 | D24: =SUMIFS('Sales Data'!$D:$D,'Sales Data'!$A:$A,$B24,'Sales Data'!$B:$B,Summary!$C$3&" "&Summary!$C$2,'Sales Data'!$C:$C,"Periodic")/Mapping!$C$2 -> 0 | E24: =SUMIFS('Sales Data'!$E:$E,'Sales Data'!$A:$A,$B24,'Sales Data'!$B:$B,Summary!$C$3&" "&Summary!$C$2,'Sales Data'!$C:$C,"Periodic")/Mapping!$C$2 -> 0 | G24: =E24-C24 -> 0 | H24: =IF(ISERROR((E24/C24)-1),"N/A",(E24/C24)-1) -> N/A | I24: =E24-D24 -> 0 | J24: =IF(ISERROR((E24/D24)-1),"N/A",(E24/D24)-1) -> N/A | L24: =SUMIFS('Sales Data'!$E:$E,'Sales Data'!$A:$A,$B24,'Sales Data'!$F:$F,$C$2-1,'Sales Data'!$G:$G,"<="&$D$3)/Mapping!$C$2 -> 0 | M24: =SUMIFS('Sales Data'!$D:$D,'Sales Data'!$A:$A,$B24,'Sales Data'!$F:$F,$C$2,'Sales Data'!$G:$G,"<="&$D$3)/Mapping!$C$2 -> 0 | N24: =SUMIFS('Sales Data'!$E:$E,'Sales Data'!$A:$A,$B24,'Sales Data'!$F:$F,$C$2,'Sales Data'!$G:$G,"<="&$D$3)/Mapping!$C$2 -> 0 | P24: =N24-L24 -> 0 | Q24: =IF(ISERROR((N24/L24)-1),"N/A",(N24/L24)-1) -> N/A | R24: =N24-M24 -> 0 | S24: =IF(ISERROR((N24/M24)-1),"N/A",(N24/M24)-1) -> N/A | U24: =SUMIFS('Sales Data'!$E:$E,'Sales Data'!$A:$A,$B24,'Sales Data'!$F:$F,$C$2-1,'Sales Data'!$G:$G,"<="&12)/Mapping!$C$2 -> 0 | V24: =SUMIFS('Sales Data'!$D:$D,'Sales Data'!$A:$A,$B24,'Sales Data'!$F:$F,$C$2,'Sales Data'!$G:$G,"<="&12)/Mapping!$C$2 -> 0 | W24: =SUMIFS('Sales Data'!$E:$E,'Sales Data'!$A:$A,$B24,'Sales Data'!$F:$F,$C$2,'Sales Data'!$G:$G,"<="&12)/Mapping!$C$2 -> 0 | Y24: =W24-U24 -> 0 | Z24: =IF(ISERROR((W24/U24)-1),"N/A",(W24/U24)-1) -> N/A | AA24: =W24-V24 -> 0 | AB24: =IF(ISERROR((W24/V24)-1),"N/A",(W24/V24)-1) -> N/A | AC24: =W24-#REF! -> #REF! | AD24: =IF(ISERROR((W24/#REF!)-1),"N/A",(W24/#REF!)-1) -> N/A | AF24: =N24/Summary!$D$3 -> 0 | AG24: =(V24-N24)/Summary!$E$3 -> 0 | AH24: =AG24-AF24 -> 0 | AJ24: =CZ24-V24 -> 0 | AK24: =DA24-V24 -> 0 | AL24: =DB24-V24 -> 0 | AM24: =CT24-V24 -> 0 | AN24: =CF24-V24 -> 0 | AP24: =U24-L24 -> 0 | AQ24: =V24-N24 -> 0 | AS24: =SUMIFS('Sales Data'!$E:$E,'Sales Data'!$A:$A,$B24,'Sales Data'!$B:$B,AS$6,'Sales Data'!$C:$C,"Periodic")/Mapping!$C$2 -> 0 | AT24: =SUMIFS('Sales Data'!$E:$E,'Sales Data'!$A:$A,$B24,'Sales Data'!$B:$B,AT$6,'Sales Data'!$C:$C,"Periodic")/Mapping!$C$2 -> 0 | AU24: =SUMIFS('Sales Data'!$E:$E,'Sales Data'!$A:$A,$B24,'Sales Data'!$B:$B,AU$6,'Sales Data'!$C:$C,"Periodic")/Mapping!$C$2 -> 0 | AV24: =SUMIFS('Sales Data'!$E:$E,'Sales Data'!$A:$A,$B24,'Sales Data'!$B:$B,AV$6,'Sales Data'!$C:$C,"Periodic")/Mapping!$C$2 -> 0 | AW24: =SUMIFS('Sales Data'!$E:$E,'Sales Data'!$A:$A,$B24,'Sales Data'!$B:$B,AW$6,'Sales Data'!$C:$C,"Periodic")/Mapping!$C$2 -> 0 | AX24: =SUMIFS('Sales Data'!$E:$E,'Sales Data'!$A:$A,$B24,'Sales Data'!$B:$B,AX$6,'Sales Data'!$C:$C,"Periodic")/Mapping!$C$2 -> 0 | AY24: =SUMIFS('Sales Data'!$E:$E,'Sales Data'!$A:$A,$B24,'Sales Data'!$B:$B,AY$6,'Sales Data'!$C:$C,"Periodic")/Mapping!$C$2 -> 0 | AZ24: =SUMIFS('Sales Data'!$E:$E,'Sales Data'!$A:$A,$B24,'Sales Data'!$B:$B,AZ$6,'Sales Data'!$C:$C,"Periodic")/Mapping!$C$2 -> 0 | ... BD24: =SUMIFS('Sales Data'!$E:$E,'Sales Data'!$A:$A,$B24,'Sales Data'!$B:$B,BD$6,'Sales Data'!$C:$C,"Periodic")/Mapping!$C$2 -> 0 | BE24: =SUM(AS24:BD24) -> 0 | BG24: =SUMIFS('Sales Data'!$E:$E,'Sales Data'!$A:$A,$B24,'Sales Data'!$B:$B,BG$6,'Sales Data'!$C:$C,"Periodic")/Mapping!$C$2 -> 0 | BH24: =SUMIFS('Sales Data'!$E:$E,'Sales Data'!$A:$A,$B24,'Sales Data'!$B:$B,BH$6,'Sales Data'!$C:$C,"Periodic")/Mapping!$C$2 -> 0 | BI24: =SUMIFS('Sales Data'!$E:$E,'Sales Data'!$A:$A,$B24,'Sales Data'!$B:$B,BI$6,'Sales Data'!$C:$C,"Periodic")/Mapping!$C$2 -> 0 | BJ24: =SUMIFS('Sales Data'!$E:$E,'Sales Data'!$A:$A,$B24,'Sales Data'!$B:$B,BJ$6,'Sales Data'!$C:$C,"Periodic")/Mapping!$C$2 -> 0 | BK24: =SUMIFS('Sales Data'!$E:$E,'Sales Data'!$A:$A,$B24,'Sales Data'!$B:$B,BK$6,'Sales Data'!$C:$C,"Periodic")/Mapping!$C$2 -> 0 | BL24: =SUMIFS('Sales Data'!$E:$E,'Sales Data'!$A:$A,$B24,'Sales Data'!$B:$B,BL$6,'Sales Data'!$C:$C,"Periodic")/Mapping!$C$2 -> 0 | BM24: =SUMIFS('Sales Data'!$E:$E,'Sales Data'!$A:$A,$B24,'Sales Data'!$B:$B,BM$6,'Sales Data'!$C:$C,"Periodic")/Mapping!$C$2 -> 0 | BN24: =SUMIFS('Sales Data'!$E:$E,'Sales Data'!$A:$A,$B24,'Sales Data'!$B:$B,BN$6,'Sales Data'!$C:$C,"Periodic")/Mapping!$C$2 -> 0 | ... BR24: =SUMIFS('Sales Data'!$E:$E,'Sales Data'!$A:$A,$B24,'Sales Data'!$B:$B,BR$6,'Sales Data'!$C:$C,"Periodic")/Mapping!$C$2 -> 0 | BT24: =IFERROR(IF(AS24<>0,AS24,FORECAST(BT$1,$BG24:$BR24,$BG$1:$BR$1)),"") -> 0 | BU24: =IFERROR(IF(AT24<>0,AT24,FORECAST(BU$1,$BG24:$BR24,$BG$1:$BR$1)),"") -> 0 | BV24: =IFERROR(IF(AU24<>0,AU24,FORECAST(BV$1,$BG24:$BR24,$BG$1:$BR$1)),"") -> 0 | BW24: =IFERROR(IF(AV24<>0,AV24,FORECAST(BW$1,$BG24:$BR24,$BG$1:$BR$1)),"") -> 0 | BX24: =IFERROR(IF(AW24<>0,AW24,FORECAST(BX$1,$BG24:$BR24,$BG$1:$BR$1)),"") -> 0 | BY24: =IFERROR(IF(AX24<>0,AX24,FORECAST(BY$1,$BG24:$BR24,$BG$1:$BR$1)),"") -> 0 | BZ24: =IFERROR(IF(AY24<>0,AY24,FORECAST(BZ$1,$BG24:$BR24,$BG$1:$BR$1)),"") -> 0 | CA24: =IFERROR(IF(AZ24<>0,AZ24,FORECAST(CA$1,$BG24:$BR24,$BG$1:$BR$1)),"") -> 0 | ... CE24: =IFERROR(IF(BD24<>0,BD24,FORECAST(CE$1,$BG24:$BR24,$BG$1:$BR$1)),"") -> 0 | CF24: =SUM(BT24:CE24) -> 0 | CH24: =IFERROR(IF(AS24<>0,AS24,FORECAST(CH$1,$BM24:$BR24,$BM$1:$BR$1)),"") -> 0 | CI24: =IFERROR(IF(AT24<>0,AT24,FORECAST(CI$1,$BM24:$BR24,$BM$1:$BR$1)),"") -> 0 | CJ24: =IFERROR(IF(AU24<>0,AU24,FORECAST(CJ$1,$BM24:$BR24,$BM$1:$BR$1)),"") -> 0 | CK24: =IFERROR(IF(AV24<>0,AV24,FORECAST(CK$1,$BM24:$BR24,$BM$1:$BR$1)),"") -> 0 | CL24: =IFERROR(IF(AW24<>0,AW24,FORECAST(CL$1,$BM24:$BR24,$BM$1:$BR$1)),"") -> 0 | CM24: =IFERROR(IF(AX24<>0,AX24,FORECAST(CM$1,$BM24:$BR24,$BM$1:$BR$1)),"") -> 0 | CN24: =IFERROR(IF(AY24<>0,AY24,FORECAST(CN$1,$BM24:$BR24,$BM$1:$BR$1)),"") -> 0 | CO24: =IFERROR(IF(AZ24<>0,AZ24,FORECAST(CO$1,$BM24:$BR24,$BM$1:$BR$1)),"") -> 0 | ... CS24: =IFERROR(IF(BD24<>0,BD24,FORECAST(CS$1,$BM24:$BR24,$BM$1:$BR$1)),"") -> 0 | CT24: =SUM(CH24:CS24) -> 0 | CV24: =SUM(BP24:BR24)/3 -> 0 | CW24: =SUM(BM24:BR24)/6 -> 0 | CX24: =SUM(BG24:BR24)/12 -> 0 | CZ24: =N24+Summary!$E$3*CV24 -> 0 | DA24: =N24+CW24*Summary!$E$3 -> 0 | DB24: =N24+CX24*Summary!$E$3 -> 0
B25: Total | C25: =SUM(C7:C24) -> 3365.5092 | D25: =SUM(D7:D24) -> 3493.5557 | E25: =SUM(E7:E24) -> 3196.1381 | G25: =E25-C25 -> -169.37108 | H25: =IF(ISERROR((E25/C25)-1),"N/A",(E25/C25)-1) -> -0.050325543 | I25: =E25-D25 -> -297.41761 | J25: =IF(ISERROR((E25/D25)-1),"N/A",(E25/D25)-1) -> -0.08513321 | L25: =SUM(L7:L24) -> 19752.418 | M25: =SUM(M7:M24) -> 22596.702 | N25: =SUM(N7:N24) -> 22473.944 | P25: =N25-L25 -> 2721.5264 | Q25: =IF(ISERROR((N25/L25)-1),"N/A",(N25/L25)-1) -> 0.13778194 | R25: =N25-M25 -> -122.7582 | S25: =IF(ISERROR((N25/M25)-1),"N/A",(N25/M25)-1) -> -0.0054325717 | U25: =SUM(U7:U24) -> 34649.197 | V25: =SUM(V7:V24) -> 39600.102 | W25: =SUM(W7:W24) -> 22473.944 | Y25: =W25-U25 -> -12175.253 | Z25: =IF(ISERROR((W25/U25)-1),"N/A",(W25/U25)-1) -> -0.35138629 | AA25: =W25-V25 -> -17126.158 | AB25: =IF(ISERROR((W25/V25)-1),"N/A",(W25/V25)-1) -> -0.43247762 | AC25: =W25-#REF! -> #REF! | AD25: =IF(ISERROR((W25/#REF!)-1),"N/A",(W25/#REF!)-1) -> N/A | AF25: =N25/Summary!$D$3 -> 3210.5634 | AG25: =(V25-N25)/Summary!$E$3 -> 3425.2315 | AH25: =AG25-AF25 -> 214.66811 | AJ25: =SUM(AJ7:AJ24) -> 2223.4313 | AK25: =SUM(AK7:AK24) -> 1924.3818 | AL25: =SUM(AL7:AL24) -> 1588.6731 | AM25: =SUM(AM7:AM24) -> 5606.0483 | AN25: =SUM(AN7:AN24) -> -35.698959 | AP25: =U25-L25 -> 14896.779 | AQ25: =V25-N25 -> 17126.158 | AS25: =SUM(AS7:AS24) -> 3385.732 | AT25: =SUM(AT7:AT24) -> 2756.9595 | AU25: =SUM(AU7:AU24) -> 3895.9234 | AV25: =SUM(AV7:AV24) -> 2711.7934 | AW25: =SUM(AW7:AW24) -> 2952.9276 | AX25: =SUM(AX7:AX24) -> 3574.4699 | AY25: =SUM(AY7:AY24) -> 3196.1381 | AZ25: =SUM(AZ7:AZ24) -> 0 | ... BE25: =SUM(BE7:BE24) -> 22473.944 | BG25: =SUM(BG7:BG24) -> 2686.8064 | BH25: =SUM(BH7:BH24) -> 2877.2226 | BI25: =SUM(BI7:BI24) -> 3134.8696 | BJ25: =SUM(BJ7:BJ24) -> 3219.2641 | BK25: =SUM(BK7:BK24) -> 2978.6164 | BL25: =SUM(BL7:BL24) -> 3385.732 | BM25: =SUM(BM7:BM24) -> 2756.9595 | BN25: =SUM(BN7:BN24) -> 3895.9234 | ... BR25: =SUM(BR7:BR24) -> 3196.1381 | BT25: =SUM(BT7:BT24) -> 3385.732 | BU25: =SUM(BU7:BU24) -> 2756.9595 | BV25: =SUM(BV7:BV24) -> 3895.9234 | BW25: =SUM(BW7:BW24) -> 2711.7934 | BX25: =SUM(BX7:BX24) -> 2952.9276 | BY25: =SUM(BY7:BY24) -> 3574.4699 | BZ25: =SUM(BZ7:BZ24) -> 3196.1381 | CA25: =SUM(CA7:CA24) -> 2831.2718 | ... CF25: =SUM(CF7:CF24) -> 36420.706 | CH25: =SUM(CH7:CH24) -> 3385.732 | CI25: =SUM(CI7:CI24) -> 2756.9595 | CJ25: =SUM(CJ7:CJ24) -> 3895.9234 | CK25: =SUM(CK7:CK24) -> 2711.7934 | CL25: =SUM(CL7:CL24) -> 2952.9276 | CM25: =SUM(CM7:CM24) -> 3574.4699 | CN25: =SUM(CN7:CN24) -> 3196.1381 | CO25: =SUM(CO7:CO24) -> 3833.5496 | ... CT25: =SUM(CT7:CT24) -> 42062.454 | CV25: =SUM(BP25:BR25)/3 -> 3241.1785 | CW25: =SUM(BM25:BR25)/6 -> 3181.3687 | CX25: =SUM(BG25:BR25)/12 -> 3114.2269 | CZ25: =N25+Summary!$E$3*CV25 -> 38679.837 | DA25: =N25+CW25*Summary!$E$3 -> 38380.787 | DB25: =N25+CX25*Summary!$E$3 -> 38045.079

Sheet Chairs
E2: Chairs
T4: Units | Z4: Sales in kUSD | BF4: Current month | BG4: Prior month
E5: Units | F5: =Mapping!$D$2 -> Jan | G5: =Mapping!$D$3 -> Feb | H5: =Mapping!$D$4 -> Mar | I5: =Mapping!$D$5 -> Apr | J5: =Mapping!$D$6 -> May | K5: =Mapping!$D$7 -> Jun | L5: =Mapping!$D$8 -> Jul | M5: =Mapping!$D$9 -> Aug | N5: =Mapping!$D$10 -> Sep | O5: =Mapping!$D$11 -> Oct | P5: =Mapping!$D$12 -> Nov | Q5: =Mapping!$D$13 -> Dec | R5: FY | T5: =Z5 -> Forecast based on: | W5: =AC5 -> FY | X5: =AD5 -> vs. LO | Z5: Forecast based on: | AC5: FY | AD5: vs. LO | BF5: =Summary!$D$3 -> 7 | BG5: =BF5-1 -> 6
A6: =Summary!$C$2-2 -> 2018 | B6: =Mapping!$B$2 -> Actual | E6: =A6&" "&B6 -> 2018 Actual | F6: =SUMIFS('Units sold'!$E:$E,'Units sold'!$A:$A,$E$2,'Units sold'!$B:$B,F$5&" "&$A6,'Units sold'!$C:$C,"Periodic") -> 44 | G6: =SUMIFS('Units sold'!$E:$E,'Units sold'!$A:$A,$E$2,'Units sold'!$B:$B,G$5&" "&$A6,'Units sold'!$C:$C,"Periodic") -> 52 | H6: =SUMIFS('Units sold'!$E:$E,'Units sold'!$A:$A,$E$2,'Units sold'!$B:$B,H$5&" "&$A6,'Units sold'!$C:$C,"Periodic") -> 82 | I6: =SUMIFS('Units sold'!$E:$E,'Units sold'!$A:$A,$E$2,'Units sold'!$B:$B,I$5&" "&$A6,'Units sold'!$C:$C,"Periodic") -> 58 | J6: =SUMIFS('Units sold'!$E:$E,'Units sold'!$A:$A,$E$2,'Units sold'!$B:$B,J$5&" "&$A6,'Units sold'!$C:$C,"Periodic") -> 62 | K6: =SUMIFS('Units sold'!$E:$E,'Units sold'!$A:$A,$E$2,'Units sold'!$B:$B,K$5&" "&$A6,'Units sold'!$C:$C,"Periodic") -> 86 | L6: =SUMIFS('Units sold'!$E:$E,'Units sold'!$A:$A,$E$2,'Units sold'!$B:$B,L$5&" "&$A6,'Units sold'!$C:$C,"Periodic") -> 104 | M6: =SUMIFS('Units sold'!$E:$E,'Units sold'!$A:$A,$E$2,'Units sold'!$B:$B,M$5&" "&$A6,'Units sold'!$C:$C,"Periodic") -> 72 | ... Q6: =SUMIFS('Units sold'!$E:$E,'Units sold'!$A:$A,$E$2,'Units sold'!$B:$B,Q$5&" "&$A6,'Units sold'!$C:$C,"Periodic") -> 88 | R6: =SUM(F6:Q6) -> 874 | T6: =Z6 -> 3-month Rolling Rate | W6: =(SUM(AR8:AT8)/3*Summary!$E$3)+R9 -> 662 | X6: =$W$6-$R$8 -> -433.93029 | Z6: 3-month Rolling Rate | AC6: =(SUM(AR9:AT9)/3*Summary!$E$3)+R16 -> 2203.3072 | AD6: =$AC$6-$R$15 -> -1477.9885 | BF6: Month | BG6: 1 | BH6: 2 | BI6: 3 | BJ6: 4 | BK6: 5 | BL6: 6 | BM6: 7 | BN6: 8 | BO6: 9 | BP6: 10 | BQ6: 11 | BR6: 12
A7: =Summary!$C$2-1 -> 2019 | B7: =Mapping!$B$2 -> Actual | E7: =A7&" "&B7 -> 2019 Actual | F7: =SUMIFS('Units sold'!$E:$E,'Units sold'!$A:$A,$E$2,'Units sold'!$B:$B,F$5&" "&$A7,'Units sold'!$C:$C,"Periodic") -> 110 | G7: =SUMIFS('Units sold'!$E:$E,'Units sold'!$A:$A,$E$2,'Units sold'!$B:$B,G$5&" "&$A7,'Units sold'!$C:$C,"Periodic") -> 78 | H7: =SUMIFS('Units sold'!$E:$E,'Units sold'!$A:$A,$E$2,'Units sold'!$B:$B,H$5&" "&$A7,'Units sold'!$C:$C,"Periodic") -> 68 | I7: =SUMIFS('Units sold'!$E:$E,'Units sold'!$A:$A,$E$2,'Units sold'!$B:$B,I$5&" "&$A7,'Units sold'!$C:$C,"Periodic") -> 76 | J7: =SUMIFS('Units sold'!$E:$E,'Units sold'!$A:$A,$E$2,'Units sold'!$B:$B,J$5&" "&$A7,'Units sold'!$C:$C,"Periodic") -> 118 | K7: =SUMIFS('Units sold'!$E:$E,'Units sold'!$A:$A,$E$2,'Units sold'!$B:$B,K$5&" "&$A7,'Units sold'!$C:$C,"Periodic") -> 66 | L7: =SUMIFS('Units sold'!$E:$E,'Units sold'!$A:$A,$E$2,'Units sold'!$B:$B,L$5&" "&$A7,'Units sold'!$C:$C,"Periodic") -> 92 | M7: =SUMIFS('Units sold'!$E:$E,'Units sold'!$A:$A,$E$2,'Units sold'!$B:$B,M$5&" "&$A7,'Units sold'!$C:$C,"Periodic") -> 72 | ... Q7: =SUMIFS('Units sold'!$E:$E,'Units sold'!$A:$A,$E$2,'Units sold'!$B:$B,Q$5&" "&$A7,'Units sold'!$C:$C,"Periodic") -> 64 | R7: =SUM(F7:Q7) -> 980 | T7: =Z7 -> 2020 Trend 6 months | W7: =BS22 -> 1197.7623 | X7: =$W$7-$R$8 -> 101.83201 | Z7: =A9&" Trend 6 months" -> 2020 Trend 6 months | AC7: =BS40 -> 3934.6883 | AD7: =$AC$7-$R$15 -> 253.39257
A8: =Summary!$C$2 -> 2020 | B8: =Mapping!$B$3 -> Budget | E8: =A8&" "&B8 -> 2020 Budget | F8: =SUMIFS('Units sold'!$D:$D,'Units sold'!$A:$A,$E$2,'Units sold'!$B:$B,F$5&" "&$A8,'Units sold'!$C:$C,"Periodic") -> 93.437432 | G8: =SUMIFS('Units sold'!$D:$D,'Units sold'!$A:$A,$E$2,'Units sold'!$B:$B,G$5&" "&$A8,'Units sold'!$C:$C,"Periodic") -> 86.479723 | H8: =SUMIFS('Units sold'!$D:$D,'Units sold'!$A:$A,$E$2,'Units sold'!$B:$B,H$5&" "&$A8,'Units sold'!$C:$C,"Periodic") -> 91.714819 | I8: =SUMIFS('Units sold'!$D:$D,'Units sold'!$A:$A,$E$2,'Units sold'!$B:$B,I$5&" "&$A8,'Units sold'!$C:$C,"Periodic") -> 98.000651 | J8: =SUMIFS('Units sold'!$D:$D,'Units sold'!$A:$A,$E$2,'Units sold'!$B:$B,J$5&" "&$A8,'Units sold'!$C:$C,"Periodic") -> 94.174024 | K8: =SUMIFS('Units sold'!$D:$D,'Units sold'!$A:$A,$E$2,'Units sold'!$B:$B,K$5&" "&$A8,'Units sold'!$C:$C,"Periodic") -> 79.21937 | L8: =SUMIFS('Units sold'!$D:$D,'Units sold'!$A:$A,$E$2,'Units sold'!$B:$B,L$5&" "&$A8,'Units sold'!$C:$C,"Periodic") -> 98.9181 | M8: =SUMIFS('Units sold'!$D:$D,'Units sold'!$A:$A,$E$2,'Units sold'!$B:$B,M$5&" "&$A8,'Units sold'!$C:$C,"Periodic") -> 93.588293 | ... Q8: =SUMIFS('Units sold'!$D:$D,'Units sold'!$A:$A,$E$2,'Units sold'!$B:$B,Q$5&" "&$A8,'Units sold'!$C:$C,"Periodic") -> 90.401772 | R8: =SUM(F8:Q8) -> 1095.9303 | T8: =Z8 -> 2020 Trend 12 months | W8: =BS23 -> 1138.8804 | X8: =$W$8-$R$8 -> 42.950105 | Z8: =A9&" Trend 12 months" -> 2020 Trend 12 months | AC8: =BS41 -> 3717.7988 | AD8: =$AC$8-$R$15 -> 36.503066 | BF8: trend key | BG8: =IF($BF$5=BG6,1,0) -> 0 | BH8: =IF($BF$5=BH6,1,0) -> 0 | BI8: =IF($BF$5=BI6,1,0) -> 0 | BJ8: =IF($BF$5=BJ6,1,0) -> 0 | BK8: =IF($BF$5=BK6,1,0) -> 0 | BL8: =IF($BF$5=BL6,1,0) -> 0 | BM8: =IF($BF$5=BM6,1,0) -> 1 | BN8: =IF($BF$5=BN6,1,0) -> 0 | ... BR8: =IF($BF$5=BR6,1,0) -> 0
A9: =Summary!$C$2 -> 2020 | B9: =Mapping!$B$2 -> Actual | E9: =A9&" "&B9 -> 2020 Actual | F9: =SUMIFS('Units sold'!$E:$E,'Units sold'!$A:$A,$E$2,'Units sold'!$B:$B,F$5&" "&$A9,'Units sold'!$C:$C,"Periodic") -> 110 | G9: =SUMIFS('Units sold'!$E:$E,'Units sold'!$A:$A,$E$2,'Units sold'!$B:$B,G$5&" "&$A9,'Units sold'!$C:$C,"Periodic") -> 76 | H9: =SUMIFS('Units sold'!$E:$E,'Units sold'!$A:$A,$E$2,'Units sold'!$B:$B,H$5&" "&$A9,'Units sold'!$C:$C,"Periodic") -> 104 | I9: =SUMIFS('Units sold'!$E:$E,'Units sold'!$A:$A,$E$2,'Units sold'!$B:$B,I$5&" "&$A9,'Units sold'!$C:$C,"Periodic") -> 74 | J9: =SUMIFS('Units sold'!$E:$E,'Units sold'!$A:$A,$E$2,'Units sold'!$B:$B,J$5&" "&$A9,'Units sold'!$C:$C,"Periodic") -> 52 | K9: =SUMIFS('Units sold'!$E:$E,'Units sold'!$A:$A,$E$2,'Units sold'!$B:$B,K$5&" "&$A9,'Units sold'!$C:$C,"Periodic") -> 124 | L9: =SUMIFS('Units sold'!$E:$E,'Units sold'!$A:$A,$E$2,'Units sold'!$B:$B,L$5&" "&$A9,'Units sold'!$C:$C,"Periodic") -> 122 | M9: =SUMIFS('Units sold'!$E:$E,'Units sold'!$A:$A,$E$2,'Units sold'!$B:$B,M$5&" "&$A9,'Units sold'!$C:$C,"Periodic") -> 0 | ... Q9: =SUMIFS('Units sold'!$E:$E,'Units sold'!$A:$A,$E$2,'Units sold'!$B:$B,Q$5&" "&$A9,'Units sold'!$C:$C,"Periodic") -> 0 | R9: =SUM(F9:Q9) -> 662 | T9: =Z9 -> Prior Year exit rate (Q4 x 4) | W9: =SUM($O$7:$Q$7)*4 -> 832 | X9: =$W$9-$R$8 -> -263.93029 | Z9: Prior Year exit rate (Q4 x 4) | AC9: =SUM($O$14:$Q$14)*4 -> 2831.0565 | AD9: =$AC$9-$R$15 -> -850.2393 | BF9: trend key | BG9: =SUM($BG8:BG8) -> 0 | BH9: =SUM($BG8:BG8) -> 0 | BI9: =SUM($BG8:BH8) -> 0 | BJ9: =SUM($BG8:BI8) -> 0 | BK9: =SUM($BG8:BJ8) -> 0 | BL9: =SUM($BG8:BK8) -> 0 | BM9: =SUM($BG8:BL8) -> 0 | BN9: =SUM($BG8:BM8) -> 1 | BO9: =SUM($BG8:BN8) -> 1 | ... BR9: =SUM($BG8:BQ8) -> 1
E10: Forecast | F10: =IF(F9=0,F17/F24,F9) -> 110 | G10: =IF(G9=0,G17/G24,G9) -> 76 | H10: =IF(H9=0,H17/H24,H9) -> 104 | I10: =IF(I9=0,I17/I24,I9) -> 74 | J10: =IF(J9=0,J17/J24,J9) -> 52 | K10: =IF(K9=0,K17/K24,K9) -> 124 | L10: =IF(L9=0,L17/L24,L9) -> 122 | M10: =IF(M9=0,M17/M24,M9) -> 87.182787 | ... Q10: =IF(Q9=0,Q17/Q24,Q9) -> 90.607036 | R10: =SUM(F10:Q10) -> 1128.239 | BG10: 1 | BH10: 2 | BI10: 3 | BJ10: 4 | BK10: 5 | BL10: 6 | BM10: 7 | BN10: 8 | BO10: 9 | BP10: 10 | BQ10: 11 | BR10: 12
E12: Sales in kUSD | F12: =F$5 -> Jan | G12: =G$5 -> Feb | H12: =H$5 -> Mar | I12: =I$5 -> Apr | J12: =J$5 -> May | K12: =K$5 -> Jun | L12: =L$5 -> Jul | M12: =M$5 -> Aug | ... Q12: =Q$5 -> Dec | R12: FY | T12: Growth vs PY | V12: =AB12 -> YTD | W12: =AC12 -> YTG | X12: =AD12 -> Delta | Z12: Growth vs PY | AB12: YTD | AC12: YTG | AD12: Delta | AH12: 6m trend key | BC12: =BB12+1 -> 1 | BD12: =BC12+1 -> 2 | BE12: =BD12+1 -> 3 | BF12: =BE12+1 -> 4 | BG12: =BF12+1 -> 5 | BH12: =BG12+1 -> 6 | BI12: =BH12+1 -> 7 | BJ12: =BI12+1 -> 8 | ... BR12: =BQ12+1 -> 16
A13: =Summary!$C$2-2 -> 2018 | B13: =Mapping!$B$2 -> Actual | E13: =A13&" "&B13 -> 2018 Actual | F13: =SUMIFS('Sales Data'!$E:$E,'Sales Data'!$A:$A,$E$2,'Sales Data'!$B:$B,F$12&" "&$A13,'Sales Data'!$C:$C,"Periodic")/1000 -> 150.41512 | G13: =SUMIFS('Sales Data'!$E:$E,'Sales Data'!$A:$A,$E$2,'Sales Data'!$B:$B,G$12&" "&$A13,'Sales Data'!$C:$C,"Periodic")/1000 -> 201.71354 | H13: =SUMIFS('Sales Data'!$E:$E,'Sales Data'!$A:$A,$E$2,'Sales Data'!$B:$B,H$12&" "&$A13,'Sales Data'!$C:$C,"Periodic")/1000 -> 287.47803 | I13: =SUMIFS('Sales Data'!$E:$E,'Sales Data'!$A:$A,$E$2,'Sales Data'!$B:$B,I$12&" "&$A13,'Sales Data'!$C:$C,"Periodic")/1000 -> 207.07993 | J13: =SUMIFS('Sales Data'!$E:$E,'Sales Data'!$A:$A,$E$2,'Sales Data'!$B:$B,J$12&" "&$A13,'Sales Data'!$C:$C,"Periodic")/1000 -> 204.97804 | K13: =SUMIFS('Sales Data'!$E:$E,'Sales Data'!$A:$A,$E$2,'Sales Data'!$B:$B,K$12&" "&$A13,'Sales Data'!$C:$C,"Periodic")/1000 -> 262.353 | L13: =SUMIFS('Sales Data'!$E:$E,'Sales Data'!$A:$A,$E$2,'Sales Data'!$B:$B,L$12&" "&$A13,'Sales Data'!$C:$C,"Periodic")/1000 -> 361.30796 | M13: =SUMIFS('Sales Data'!$E:$E,'Sales Data'!$A:$A,$E$2,'Sales Data'!$B:$B,M$12&" "&$A13,'Sales Data'!$C:$C,"Periodic")/1000 -> 243.981 | ... Q13: =SUMIFS('Sales Data'!$E:$E,'Sales Data'!$A:$A,$E$2,'Sales Data'!$B:$B,Q$12&" "&$A13,'Sales Data'!$C:$C,"Periodic")/1000 -> 284.45186 | R13: =SUM(F13:Q13) -> 3004.1753 | T13: =Z13 -> GR% | V13: =IFERROR(($R$9/SUM(OFFSET(E7,,1,1,Summary!$D$3))-1),"") -> 0.088815789 | W13: =((R8-R9)/(R7-SUM(OFFSET(E7,0,1,1,Summary!$D$3))))-1 -> 0.16647927 | X13: =IFERROR(W13-V13,"") -> 0.077663483 | Z13: GR% | AB13: =IFERROR(R16/SUM(OFFSET(E14,0,1,1,Summary!$D$3))-1,"") -> 0.086066578 | AC13: =IFERROR((R15-R16)/(R14-SUM(OFFSET(E14,0,1,1,Summary!$D$3)))-1,"") -> 0.18602635 | AD13: =IFERROR(AC13-AB13,"") -> 0.099959771 | AH13: 12m trend key | AW13: =AV13+1 -> 1 | AX13: =AW13+1 -> 2 | AY13: =AX13+1 -> 3 | AZ13: =AY13+1 -> 4 | BA13: =AZ13+1 -> 5 | BB13: =BA13+1 -> 6 | BC13: =BB13+1 -> 7 | BD13: =BC13+1 -> 8 | ... BR13: =BQ13+1 -> 22
A14: =Summary!$C$2-1 -> 2019 | B14: =Mapping!$B$2 -> Actual | E14: =A14&" "&B14 -> 2019 Actual | F14: =SUMIFS('Sales Data'!$E:$E,'Sales Data'!$A:$A,$E$2,'Sales Data'!$B:$B,F$12&" "&$A14,'Sales Data'!$C:$C,"Periodic")/1000 -> 331.44905 | G14: =SUMIFS('Sales Data'!$E:$E,'Sales Data'!$A:$A,$E$2,'Sales Data'!$B:$B,G$12&" "&$A14,'Sales Data'!$C:$C,"Periodic")/1000 -> 192.22995 | H14: =SUMIFS('Sales Data'!$E:$E,'Sales Data'!$A:$A,$E$2,'Sales Data'!$B:$B,H$12&" "&$A14,'Sales Data'!$C:$C,"Periodic")/1000 -> 293.89065 | I14: =SUMIFS('Sales Data'!$E:$E,'Sales Data'!$A:$A,$E$2,'Sales Data'!$B:$B,I$12&" "&$A14,'Sales Data'!$C:$C,"Periodic")/1000 -> 298.2346 | J14: =SUMIFS('Sales Data'!$E:$E,'Sales Data'!$A:$A,$E$2,'Sales Data'!$B:$B,J$12&" "&$A14,'Sales Data'!$C:$C,"Periodic")/1000 -> 370.87774 | K14: =SUMIFS('Sales Data'!$E:$E,'Sales Data'!$A:$A,$E$2,'Sales Data'!$B:$B,K$12&" "&$A14,'Sales Data'!$C:$C,"Periodic")/1000 -> 211.52387 | L14: =SUMIFS('Sales Data'!$E:$E,'Sales Data'!$A:$A,$E$2,'Sales Data'!$B:$B,L$12&" "&$A14,'Sales Data'!$C:$C,"Periodic")/1000 -> 330.49778 | M14: =SUMIFS('Sales Data'!$E:$E,'Sales Data'!$A:$A,$E$2,'Sales Data'!$B:$B,M$12&" "&$A14,'Sales Data'!$C:$C,"Periodic")/1000 -> 207.34384 | ... Q14: =SUMIFS('Sales Data'!$E:$E,'Sales Data'!$A:$A,$E$2,'Sales Data'!$B:$B,Q$12&" "&$A14,'Sales Data'!$C:$C,"Periodic")/1000 -> 196.25758 | R14: =SUM(F14:Q14) -> 3274.872 | T14: Avg. packs per month | V14: =IFERROR(R9/Summary!$D$3,"") -> 94.571429 | W14: =IFERROR((R8-R9)/Summary!$E$3,"") -> 86.786058 | X14: =IFERROR(W14-V14,"") -> -7.7853707 | Z14: Avg. sales | AB14: =R16/Summary!$D$3 -> 314.75817 | AC14: =IFERROR((R15-R16)/Summary!$E$3,"") -> 295.59771 | AD14: =IFERROR(AC14-AB14,"") -> -19.160468 | AG14: Units
A15: =Summary!$C$2 -> 2020 | B15: =Mapping!$B$3 -> Budget | E15: =A15&" "&B15 -> 2020 Budget | F15: =SUMIFS('Sales Data'!$D:$D,'Sales Data'!$A:$A,$E$2,'Sales Data'!$B:$B,F$12&" "&$A15,'Sales Data'!$C:$C,"Periodic")/1000 -> 293.65757 | G15: =SUMIFS('Sales Data'!$D:$D,'Sales Data'!$A:$A,$E$2,'Sales Data'!$B:$B,G$12&" "&$A15,'Sales Data'!$C:$C,"Periodic")/1000 -> 265.52396 | H15: =SUMIFS('Sales Data'!$D:$D,'Sales Data'!$A:$A,$E$2,'Sales Data'!$B:$B,H$12&" "&$A15,'Sales Data'!$C:$C,"Periodic")/1000 -> 301.56365 | I15: =SUMIFS('Sales Data'!$D:$D,'Sales Data'!$A:$A,$E$2,'Sales Data'!$B:$B,I$12&" "&$A15,'Sales Data'!$C:$C,"Periodic")/1000 -> 314.80977 | J15: =SUMIFS('Sales Data'!$D:$D,'Sales Data'!$A:$A,$E$2,'Sales Data'!$B:$B,J$12&" "&$A15,'Sales Data'!$C:$C,"Periodic")/1000 -> 313.88511 | K15: =SUMIFS('Sales Data'!$D:$D,'Sales Data'!$A:$A,$E$2,'Sales Data'!$B:$B,K$12&" "&$A15,'Sales Data'!$C:$C,"Periodic")/1000 -> 310.3944 | L15: =SUMIFS('Sales Data'!$D:$D,'Sales Data'!$A:$A,$E$2,'Sales Data'!$B:$B,L$12&" "&$A15,'Sales Data'!$C:$C,"Periodic")/1000 -> 329.69726 | M15: =SUMIFS('Sales Data'!$D:$D,'Sales Data'!$A:$A,$E$2,'Sales Data'!$B:$B,M$12&" "&$A15,'Sales Data'!$C:$C,"Periodic")/1000 -> 290.16687 | ... Q15: =SUMIFS('Sales Data'!$D:$D,'Sales Data'!$A:$A,$E$2,'Sales Data'!$B:$B,Q$12&" "&$A15,'Sales Data'!$C:$C,"Periodic")/1000 -> 301.56365 | R15: =SUM(F15:Q15) -> 3681.2958 | AG15: Trend Calculation | AI15: ='Bridges for Trends'!Y4 -> Jan 2018 | AJ15: ='Bridges for Trends'!X4 -> Feb 2018 | AK15: ='Bridges for Trends'!W4 -> Mar 2018 | AL15: ='Bridges for Trends'!V4 -> Apr 2018 | AM15: ='Bridges for Trends'!U4 -> May 2018 | AN15: ='Bridges for Trends'!T4 -> Jun 2018 | AO15: ='Bridges for Trends'!S4 -> Jul 2018 | AP15: ='Bridges for Trends'!R4 -> Aug 2018 | AQ15: ='Bridges for Trends'!Q4 -> Sep 2018 | AR15: ='Bridges for Trends'!P4 -> Oct 2018 | AS15: ='Bridges for Trends'!O4 -> Nov 2018 | AT15: ='Bridges for Trends'!N4 -> Dec 2018 | AU15: ='Bridges for Trends'!M4 -> Jan 2019 | AV15: ='Bridges for Trends'!L4 -> Feb 2019 | AW15: ='Bridges for Trends'!K4 -> Mar 2019 | AX15: ='Bridges for Trends'!J4 -> Apr 2019 | AY15: ='Bridges for Trends'!I4 -> May 2019 | AZ15: ='Bridges for Trends'!H4 -> Jun 2019 | BA15: ='Bridges for Trends'!G4 -> Jul 2019 | BB15: ='Bridges for Trends'!F4 -> Aug 2019 | BC15: ='Bridges for Trends'!E4 -> Sep 2019 | BD15: ='Bridges for Trends'!D4 -> Oct 2019 | BE15: ='Bridges for Trends'!C4 -> Nov 2019 | BF15: ='Bridges for Trends'!B4 -> Dec 2019 | BG15: ='Bridges for Trends'!A4 -> Jan 2020 | BH15: ='Bridges for Trends'!A5 -> Feb 2020 | BI15: ='Bridges for Trends'!A6 -> Mar 2020 | BJ15: ='Bridges for Trends'!A7 -> Apr 2020 | BK15: ='Bridges for Trends'!A8 -> May 2020 | BL15: ='Bridges for Trends'!A9 -> Jun 2020 | BM15: ='Bridges for Trends'!A10 -> Jul 2020 | BN15: ='Bridges for Trends'!A11 -> Aug 2020 | BO15: ='Bridges for Trends'!A12 -> Sep 2020 | BP15: ='Bridges for Trends'!A13 -> Oct 2020 | BQ15: ='Bridges for Trends'!A14 -> Nov 2020 | BR15: ='Bridges for Trends'!A15 -> Dec 2020
A16: =Summary!$C$2 -> 2020 | B16: =Mapping!$B$2 -> Actual | E16: =A16&" "&B16 -> 2020 Actual | F16: =SUMIFS('Sales Data'!$E:$E,'Sales Data'!$A:$A,$E$2,'Sales Data'!$B:$B,F$12&" "&$A16,'Sales Data'!$C:$C,"Periodic")/1000 -> 346.82725 | G16: =SUMIFS('Sales Data'!$E:$E,'Sales Data'!$A:$A,$E$2,'Sales Data'!$B:$B,G$12&" "&$A16,'Sales Data'!$C:$C,"Periodic")/1000 -> 238.7955 | H16: =SUMIFS('Sales Data'!$E:$E,'Sales Data'!$A:$A,$E$2,'Sales Data'!$B:$B,H$12&" "&$A16,'Sales Data'!$C:$C,"Periodic")/1000 -> 350.5117 | I16: =SUMIFS('Sales Data'!$E:$E,'Sales Data'!$A:$A,$E$2,'Sales Data'!$B:$B,I$12&" "&$A16,'Sales Data'!$C:$C,"Periodic")/1000 -> 268.3706 | J16: =SUMIFS('Sales Data'!$E:$E,'Sales Data'!$A:$A,$E$2,'Sales Data'!$B:$B,J$12&" "&$A16,'Sales Data'!$C:$C,"Periodic")/1000 -> 198.77341 | K16: =SUMIFS('Sales Data'!$E:$E,'Sales Data'!$A:$A,$E$2,'Sales Data'!$B:$B,K$12&" "&$A16,'Sales Data'!$C:$C,"Periodic")/1000 -> 451.48431 | L16: =SUMIFS('Sales Data'!$E:$E,'Sales Data'!$A:$A,$E$2,'Sales Data'!$B:$B,L$12&" "&$A16,'Sales Data'!$C:$C,"Periodic")/1000 -> 348.54445 | M16: =SUMIFS('Sales Data'!$E:$E,'Sales Data'!$A:$A,$E$2,'Sales Data'!$B:$B,M$12&" "&$A16,'Sales Data'!$C:$C,"Periodic")/1000 -> 0 | ... Q16: =SUMIFS('Sales Data'!$E:$E,'Sales Data'!$A:$A,$E$2,'Sales Data'!$B:$B,Q$12&" "&$A16,'Sales Data'!$C:$C,"Periodic")/1000 -> 0 | R16: =SUM(F16:Q16) -> 2203.3072 | AH16: Actual | AI16: =SUMIFS('Units sold'!$E:$E,'Units sold'!$A:$A,$E$2,'Units sold'!$B:$B,AI$15,'Units sold'!$C:$C,"Periodic") -> 44 | AJ16: =SUMIFS('Units sold'!$E:$E,'Units sold'!$A:$A,$E$2,'Units sold'!$B:$B,AJ$15,'Units sold'!$C:$C,"Periodic") -> 52 | AK16: =SUMIFS('Units sold'!$E:$E,'Units sold'!$A:$A,$E$2,'Units sold'!$B:$B,AK$15,'Units sold'!$C:$C,"Periodic") -> 82 | AL16: =SUMIFS('Units sold'!$E:$E,'Units sold'!$A:$A,$E$2,'Units sold'!$B:$B,AL$15,'Units sold'!$C:$C,"Periodic") -> 58 | AM16: =SUMIFS('Units sold'!$E:$E,'Units sold'!$A:$A,$E$2,'Units sold'!$B:$B,AM$15,'Units sold'!$C:$C,"Periodic") -> 62 | AN16: =SUMIFS('Units sold'!$E:$E,'Units sold'!$A:$A,$E$2,'Units sold'!$B:$B,AN$15,'Units sold'!$C:$C,"Periodic") -> 86 | AO16: =SUMIFS('Units sold'!$E:$E,'Units sold'!$A:$A,$E$2,'Units sold'!$B:$B,AO$15,'Units sold'!$C:$C,"Periodic") -> 104 | AP16: =SUMIFS('Units sold'!$E:$E,'Units sold'!$A:$A,$E$2,'Units sold'!$B:$B,AP$15,'Units sold'!$C:$C,"Periodic") -> 72 | ... BF16: =SUMIFS('Units sold'!$E:$E,'Units sold'!$A:$A,$E$2,'Units sold'!$B:$B,BF$15,'Units sold'!$C:$C,"Periodic") -> 64 | BG16: =IF(OR(BG$8=1,BG$9=0),SUMIFS('Units sold'!$E:$E,'Units sold'!$A:$A,$E$2,'Units sold'!$B:$B,BG$15,'Units sold'!$C:$C,"Periodic"),"") -> 110 | BH16: =IF(OR(BH$8=1,BH$9=0),SUMIFS('Units sold'!$E:$E,'Units sold'!$A:$A,$E$2,'Units sold'!$B:$B,BH$15,'Units sold'!$C:$C,"Periodic"),"") -> 76 | BI16: =IF(OR(BI$8=1,BI$9=0),SUMIFS('Units sold'!$E:$E,'Units sold'!$A:$A,$E$2,'Units sold'!$B:$B,BI$15,'Units sold'!$C:$C,"Periodic"),"") -> 104 | BJ16: =IF(OR(BJ$8=1,BJ$9=0),SUMIFS('Units sold'!$E:$E,'Units sold'!$A:$A,$E$2,'Units sold'!$B:$B,BJ$15,'Units sold'!$C:$C,"Periodic"),"") -> 74 | BK16: =IF(OR(BK$8=1,BK$9=0),SUMIFS('Units sold'!$E:$E,'Units sold'!$A:$A,$E$2,'Units sold'!$B:$B,BK$15,'Units sold'!$C:$C,"Periodic"),"") -> 52 | BL16: =IF(OR(BL$8=1,BL$9=0),SUMIFS('Units sold'!$E:$E,'Units sold'!$A:$A,$E$2,'Units sold'!$B:$B,BL$15,'Units sold'!$C:$C,"Periodic"),"") -> 124 | BM16: =IF(OR(BM$8=1,BM$9=0),SUMIFS('Units sold'!$E:$E,'Units sold'!$A:$A,$E$2,'Units sold'!$B:$B,BM$15,'Units sold'!$C:$C,"Periodic"),"") -> 122 | BN16: =IF(OR(BN$8=1,BN$9=0),SUMIFS('Units sold'!$E:$E,'Units sold'!$A:$A,$E$2,'Units sold'!$B:$B,BN$15,'Units sold'!$C:$C,"Periodic"),"") | ... BR16: =IF(OR(BR$8=1,BR$9=0),SUMIFS('Units sold'!$E:$E,'Units sold'!$A:$A,$E$2,'Units sold'!$B:$B,BR$15,'Units sold'!$C:$C,"Periodic"),"")
E17: Forecast | F17: =IF(F16<>0,F16,F15) -> 346.82725 | G17: =IF(G16<>0,G16,G15) -> 238.7955 | H17: =IF(H16<>0,H16,H15) -> 350.5117 | I17: =IF(I16<>0,I16,I15) -> 268.3706 | J17: =IF(J16<>0,J16,J15) -> 198.77341 | K17: =IF(K16<>0,K16,K15) -> 451.48431 | L17: =IF(L16<>0,L16,L15) -> 348.54445 | M17: =IF(M16<>0,M16,M15) -> 290.16687 | ... Q17: =IF(Q16<>0,Q16,Q15) -> 301.56365 | R17: =SUM(F17:Q17) -> 3755.0713 | T17: Units | U17: =AA17 -> Q1 | V17: =AB17 -> Q2 | W17: =AC17 -> Q3 | X17: =AD17 -> Q4 | Z17: Sales | AA17: Q1 | AB17: Q2 | AC17: Q3 | AD17: Q4 | AH17: Budget | BG17: =IF(OR(BG$8=1,BG$9=1),SUMIFS('Units sold'!$D:$D,'Units sold'!$A:$A,$E$2,'Units sold'!$B:$B,BG$15,'Units sold'!$C:$C,"Periodic"),"") | BH17: =IF(OR(BH$8=1,BH$9=1),SUMIFS('Units sold'!$D:$D,'Units sold'!$A:$A,$E$2,'Units sold'!$B:$B,BH$15,'Units sold'!$C:$C,"Periodic"),"") | BI17: =IF(OR(BI$8=1,BI$9=1),SUMIFS('Units sold'!$D:$D,'Units sold'!$A:$A,$E$2,'Units sold'!$B:$B,BI$15,'Units sold'!$C:$C,"Periodic"),"") | BJ17: =IF(OR(BJ$8=1,BJ$9=1),SUMIFS('Units sold'!$D:$D,'Units sold'!$A:$A,$E$2,'Units sold'!$B:$B,BJ$15,'Units sold'!$C:$C,"Periodic"),"") | BK17: =IF(OR(BK$8=1,BK$9=1),SUMIFS('Units sold'!$D:$D,'Units sold'!$A:$A,$E$2,'Units sold'!$B:$B,BK$15,'Units sold'!$C:$C,"Periodic"),"") | BL17: =IF(OR(BL$8=1,BL$9=1),SUMIFS('Units sold'!$D:$D,'Units sold'!$A:$A,$E$2,'Units sold'!$B:$B,BL$15,'Units sold'!$C:$C,"Periodic"),"") | BM17: =IF(OR(BM$8=1,BM$9=1),SUMIFS('Units sold'!$D:$D,'Units sold'!$A:$A,$E$2,'Units sold'!$B:$B,BM$15,'Units sold'!$C:$C,"Periodic"),"") -> 98.9181 | BN17: =IF(OR(BN$8=1,BN$9=1),SUMIFS('Units sold'!$D:$D,'Units sold'!$A:$A,$E$2,'Units sold'!$B:$B,BN$15,'Units sold'!$C:$C,"Periodic"),"") -> 93.588293 | ... BR17: =IF(OR(BR$8=1,BR$9=1),SUMIFS('Units sold'!$D:$D,'Units sold'!$A:$A,$E$2,'Units sold'!$B:$B,BR$15,'Units sold'!$C:$C,"Periodic"),"") -> 90.401772
T18: =E6 -> 2018 Actual | U18: =SUM(F6:H6) -> 178 | V18: =SUM(I6:K6) -> 206 | W18: =SUM(L6:N6) -> 244 | X18: =SUM(O6:Q6) -> 246 | Z18: =+E13 -> 2018 Actual | AA18: =SUM(F13:H13) -> 639.60669 | AB18: =SUM(I13:K13) -> 674.41097 | AC18: =SUM(L13:N13) -> 832.79168 | AD18: =SUM(O13:Q13) -> 857.366 | AH18: Trend 6m | BG18: =IF(BG$9,FORECAST(BG12,$AP16:BF16,$AP12:BF12), "") | BH18: =IF(BH$9,FORECAST(BH12,$AP16:BG16,$AP12:BG12), "") | BI18: =IF(BI$9,FORECAST(BI12,$AP16:BH16,$AP12:BH12), "") | BJ18: =IF(BJ$9,FORECAST(BJ12,$AP16:BI16,$AP12:BI12), "") | BK18: =IF(BK$9,FORECAST(BK12,$AP16:BJ16,$AP12:BJ12), "") | BL18: =IF(BL$9,FORECAST(BL12,$AP16:BK16,$AP12:BK12), "") | BM18: =IF(BM$9,FORECAST(BM12,$AP16:BL16,$AP12:BL12), "") | BN18: =IF(BN$9,FORECAST(BN12,$AP16:BM16,$AP12:BM12), "") -> 105.23636 | ... BR18: =IF(BR$9,FORECAST(BR12,$AP16:BQ16,$AP12:BQ12), "") -> 117.09091
E19: Average Price in kUSD | F19: =F$5 -> Jan | G19: =G$5 -> Feb | H19: =H$5 -> Mar | I19: =I$5 -> Apr | J19: =J$5 -> May | K19: =K$5 -> Jun | L19: =L$5 -> Jul | M19: =M$5 -> Aug | ... Q19: =Q$5 -> Dec | R19: FY | T19: =E7 -> 2019 Actual | U19: =SUM(F7:H7) -> 256 | V19: =SUM(I7:K7) -> 260 | W19: =SUM(L7:N7) -> 256 | X19: =SUM(O7:Q7) -> 208 | Z19: =+E14 -> 2019 Actual | AA19: =SUM(F14:H14) -> 817.56965 | AB19: =SUM(I14:K14) -> 880.63621 | AC19: =SUM(L14:N14) -> 868.90205 | AD19: =SUM(O14:Q14) -> 707.76411 | AH19: Trend 12m | BG19: =IF(BG$9,FORECAST(BG13,$AP16:BF16,$AP13:BF13), "") | BH19: =IF(BH$9,FORECAST(BH13,$AP16:BG16,$AP13:BG13), "") | BI19: =IF(BI$9,FORECAST(BI13,$AP16:BH16,$AP13:BH13), "") | BJ19: =IF(BJ$9,FORECAST(BJ13,$AP16:BI16,$AP13:BI13), "") | BK19: =IF(BK$9,FORECAST(BK13,$AP16:BJ16,$AP13:BJ13), "") | BL19: =IF(BL$9,FORECAST(BL13,$AP16:BK16,$AP13:BK13), "") | BM19: =IF(BM$9,FORECAST(BM13,$AP16:BL16,$AP13:BL13), "") | BN19: =IF(BN$9,FORECAST(BN13,$AP16:BM16,$AP13:BM13), "") -> 96.867647 | ... BR19: =IF(BR$9,FORECAST(BR13,$AP16:BQ16,$AP13:BQ13), "") -> 101.90686
E20: =+E13 -> 2018 Actual | F20: =IFERROR(F13/F6,"") -> 3.4185254 | G20: =IFERROR(G13/G6,"") -> 3.8791066 | H20: =IFERROR(H13/H6,"") -> 3.5058296 | I20: =IFERROR(I13/I6,"") -> 3.5703436 | J20: =IFERROR(J13/J6,"") -> 3.3060975 | K20: =IFERROR(K13/K6,"") -> 3.0506163 | L20: =IFERROR(L13/L6,"") -> 3.474115 | M20: =IFERROR(M13/M6,"") -> 3.388625 | ... R20: =IFERROR(R13/R6,"") -> 3.4372716 | T20: =E8 -> 2020 Budget | U20: =SUM(F8:H8) -> 271.63198 | V20: =SUM(I8:K8) -> 271.39405 | W20: =SUM(L8:N8) -> 283.5127 | X20: =SUM(O8:Q8) -> 269.39157 | Z20: =+E15 -> 2020 Budget | AA20: =SUM(F15:H15) -> 860.74519 | AB20: =SUM(I15:K15) -> 939.08927 | AC20: =SUM(L15:N15) -> 936.31528 | AD20: =SUM(O15:Q15) -> 945.14602 | AH20: Budget | BG20: =SUMIFS('Units sold'!$D:$D,'Units sold'!$A:$A,$E$2,'Units sold'!$B:$B,BG$15,'Units sold'!$C:$C,"Periodic") -> 93.437432 | BH20: =SUMIFS('Units sold'!$D:$D,'Units sold'!$A:$A,$E$2,'Units sold'!$B:$B,BH$15,'Units sold'!$C:$C,"Periodic") -> 86.479723 | BI20: =SUMIFS('Units sold'!$D:$D,'Units sold'!$A:$A,$E$2,'Units sold'!$B:$B,BI$15,'Units sold'!$C:$C,"Periodic") -> 91.714819 | BJ20: =SUMIFS('Units sold'!$D:$D,'Units sold'!$A:$A,$E$2,'Units sold'!$B:$B,BJ$15,'Units sold'!$C:$C,"Periodic") -> 98.000651 | BK20: =SUMIFS('Units sold'!$D:$D,'Units sold'!$A:$A,$E$2,'Units sold'!$B:$B,BK$15,'Units sold'!$C:$C,"Periodic") -> 94.174024 | BL20: =SUMIFS('Units sold'!$D:$D,'Units sold'!$A:$A,$E$2,'Units sold'!$B:$B,BL$15,'Units sold'!$C:$C,"Periodic") -> 79.21937 | BM20: =SUMIFS('Units sold'!$D:$D,'Units sold'!$A:$A,$E$2,'Units sold'!$B:$B,BM$15,'Units sold'!$C:$C,"Periodic") -> 98.9181 | BN20: =SUMIFS('Units sold'!$D:$D,'Units sold'!$A:$A,$E$2,'Units sold'!$B:$B,BN$15,'Units sold'!$C:$C,"Periodic") -> 93.588293 | ... BR20: =SUMIFS('Units sold'!$D:$D,'Units sold'!$A:$A,$E$2,'Units sold'!$B:$B,BR$15,'Units sold'!$C:$C,"Periodic") -> 90.401772
E21: =+E14 -> 2019 Actual | F21: =IFERROR(F14/F7,"") -> 3.0131732 | G21: =IFERROR(G14/G7,"") -> 2.4644866 | H21: =IFERROR(H14/H7,"") -> 4.3219214 | I21: =IFERROR(I14/I7,"") -> 3.9241395 | J21: =IFERROR(J14/J7,"") -> 3.1430317 | K21: =IFERROR(K14/K7,"") -> 3.2049071 | L21: =IFERROR(L14/L7,"") -> 3.5923672 | M21: =IFERROR(M14/M7,"") -> 2.8797755 | ... R21: =IFERROR(R14/R7,"") -> 3.3417061 | T21: =E9 -> 2020 Actual | U21: =SUM(F9:H9) -> 290 | V21: =SUM(I9:K9) -> 250 | W21: =SUM(L9:N9) -> 122 | X21: =SUM(O9:Q9) -> 0 | Z21: =+E16 -> 2020 Actual | AA21: =SUM(F16:H16) -> 936.13445 | AB21: =SUM(I16:K16) -> 918.62832 | AC21: =SUM(L16:N16) -> 348.54445 | AD21: =SUM(O16:Q16) -> 0 | AH21: Forecast | BG21: =IF(OR(BG$8=1,BG$9=1),F10,"") | BH21: =IF(OR(BH$8=1,BH$9=1),G10,"") | BI21: =IF(OR(BI$8=1,BI$9=1),H10,"") | BJ21: =IF(OR(BJ$8=1,BJ$9=1),I10,"") | BK21: =IF(OR(BK$8=1,BK$9=1),J10,"") | BL21: =IF(OR(BL$8=1,BL$9=1),K10,"") | BM21: =IF(OR(BM$8=1,BM$9=1),L10,"") -> 122 | BN21: =IF(OR(BN$8=1,BN$9=1),M10,"") -> 87.182787 | ... BR21: =IF(OR(BR$8=1,BR$9=1),Q10,"") -> 90.607036
E22: =+E15 -> 2020 Budget | F22: =IFERROR(F15/F8,"") -> 3.1428258 | G22: =IFERROR(G15/G8,"") -> 3.0703609 | H22: =IFERROR(H15/H8,"") -> 3.2880581 | I22: =IFERROR(I15/I8,"") -> 3.2123233 | J22: =IFERROR(J15/J8,"") -> 3.3330327 | K22: =IFERROR(K15/K8,"") -> 3.9181629 | L22: =IFERROR(L15/L8,"") -> 3.3330327 | M22: =IFERROR(M15/M8,"") -> 3.1004611 | ... R22: =IFERROR(R15/R8,"") -> 3.3590601 | T22: Forecast | U22: =SUM(F10:H10) -> 290 | V22: =SUM(I10:K10) -> 250 | W22: =SUM(L10:N10) -> 304.26288 | X22: =SUM(O10:Q10) -> 283.97613 | Z22: Forecast | AA22: =SUM(F17:H17) -> 936.13445 | AB22: =SUM(I17:K17) -> 918.62832 | AC22: =SUM(L17:N17) -> 955.16246 | AD22: =SUM(O17:Q17) -> 945.14602 | AG22: Run rates | AH22: Trend 6m | BG22: =IF(BG18="",BG20,BG18) -> 93.437432 | BH22: =IF(BH18="",BH20,BH18) -> 86.479723 | BI22: =IF(BI18="",BI20,BI18) -> 91.714819 | BJ22: =IF(BJ18="",BJ20,BJ18) -> 98.000651 | BK22: =IF(BK18="",BK20,BK18) -> 94.174024 | BL22: =IF(BL18="",BL20,BL18) -> 79.21937 | BM22: =IF(BM18="",BM20,BM18) -> 98.9181 | BN22: =IF(BN18="",BN20,BN18) -> 105.23636 | ... BR22: =IF(BR18="",BR20,BR18) -> 117.09091 | BS22: =SUM(BG22:BR22) -> 1197.7623
E23: =+E16 -> 2020 Actual | F23: =IFERROR(F16/F9,"") -> 3.152975 | G23: =IFERROR(G16/G9,"") -> 3.142046 | H23: =IFERROR(H16/H9,"") -> 3.3703048 | I23: =IFERROR(I16/I9,"") -> 3.6266297 | J23: =IFERROR(J16/J9,"") -> 3.8225656 | K23: =IFERROR(K16/K9,"") -> 3.6410025 | L23: =IFERROR(L16/L9,"") -> 2.8569217 | M23: =IFERROR(M16/M9,"") | ... R23: =IFERROR(R16/R9,"") -> 3.3282586 | AH23: Trend 12m | BG23: =IF(BG19="",BG20,BG19) -> 93.437432 | BH23: =IF(BH19="",BH20,BH19) -> 86.479723 | BI23: =IF(BI19="",BI20,BI19) -> 91.714819 | BJ23: =IF(BJ19="",BJ20,BJ19) -> 98.000651 | BK23: =IF(BK19="",BK20,BK19) -> 94.174024 | BL23: =IF(BL19="",BL20,BL19) -> 79.21937 | BM23: =IF(BM19="",BM20,BM19) -> 98.9181 | BN23: =IF(BN19="",BN20,BN19) -> 96.867647 | ... BR23: =IF(BR19="",BR20,BR19) -> 101.90686 | BS23: =SUM(BG23:BR23) -> 1138.8804
E24: =+E17 -> Forecast | F24: =IF(F23="",IFERROR(SUM(E17:$F17)/SUM(E10:$F10),""),F17/F10) -> 3.152975 | G24: =IF(G23="",IFERROR(SUM(F17:$F17)/SUM(F10:$F10),""),G17/G10) -> 3.142046 | H24: =IF(H23="",IFERROR(SUM($F17:G17)/SUM($F10:G10),""),H17/H10) -> 3.3703048 | I24: =IF(I23="",IFERROR(SUM($F17:H17)/SUM($F10:H10),""),I17/I10) -> 3.6266297 | J24: =IF(J23="",IFERROR(SUM($F17:I17)/SUM($F10:I10),""),J17/J10) -> 3.8225656 | K24: =IF(K23="",IFERROR(SUM($F17:J17)/SUM($F10:J10),""),K17/K10) -> 3.6410025 | L24: =IF(L23="",IFERROR(SUM($F17:K17)/SUM($F10:K10),""),L17/L10) -> 2.8569217 | M24: =IF(M23="",IFERROR(SUM($F17:L17)/SUM($F10:L10),""),M17/M10) -> 3.3282586 | N24: =IF(N23="",IFERROR(SUM($F17:M17)/SUM($F10:M10),""),N17/N10) -> 3.3282586 | O24: =IF(O23="",IFERROR(SUM($F17:N17)/SUM($F10:N10),""),O17/O10) -> 3.3282586 | ... Q24: =IF(Q23="",IFERROR(SUM($F17:P17)/SUM($F10:P10),""),Q17/Q10) -> 3.3282586 | R24: =IFERROR(R17/R10,"") -> 3.3282586 | T24: Quarter Actuals | U24: =AA24 -> Q1 | V24: =AB24 -> Q2 | W24: =AC24 -> Q3 | X24: =AD24 -> Q4 | Z24: Quarter Actuals | AA24: Q1 | AB24: Q2 | AC24: Q3 | AD24: Q4 | AG24: Trend Charts
T25: ="vs "&$A$6 -> vs 2018 | U25: =IFERROR(U$21/U18-1,"") -> 0.62921348 | V25: =IFERROR(V$21/V18-1,"") -> 0.21359223 | W25: =IFERROR(W$21/W18-1,"") -> -0.5 | X25: =IFERROR(X$21/X18-1,"") -> -1 | Z25: ="vs "&$A$6 -> vs 2018 | AA25: =IFERROR(AA$21/AA18-1,"") -> 0.46360954 | AB25: =IFERROR(AB$21/AB18-1,"") -> 0.36211948 | AC25: =IFERROR(AC$21/AC18-1,"") -> -0.58147463 | AD25: =IFERROR(AD$21/AD18-1,"") -> -1 | AH25: =AH16 -> Actual | AU25: =IF(AU16="",NA(),AU16) -> 110 | AV25: =IF(AV16="",NA(),AV16) -> 78 | AW25: =IF(AW16="",NA(),AW16) -> 68 | AX25: =IF(AX16="",NA(),AX16) -> 76 | AY25: =IF(AY16="",NA(),AY16) -> 118 | AZ25: =IF(AZ16="",NA(),AZ16) -> 66 | BA25: =IF(BA16="",NA(),BA16) -> 92 | BB25: =IF(BB16="",NA(),BB16) -> 72 | ... BR25: =IF(BR16="",NA(),BR16) -> #N/A
T26: ="vs "&$A$7 -> vs 2019 | U26: =IFERROR(U$21/U19-1,"") -> 0.1328125 | V26: =IFERROR(V$21/V19-1,"") -> -0.038461538 | W26: =IFERROR(W$21/W19-1,"") -> -0.5234375 | X26: =IFERROR(X$21/X19-1,"") -> -1 | Z26: ="vs "&$A$7 -> vs 2019 | AA26: =IFERROR(AA$21/AA19-1,"") -> 0.14502104 | AB26: =IFERROR(AB$21/AB19-1,"") -> 0.043141668 | AC26: =IFERROR(AC$21/AC19-1,"") -> -0.59886796 | AD26: =IFERROR(AD$21/AD19-1,"") -> -1 | AH26: =AH20 -> Budget | AU26: =IF(AU17="",NA(),AU17) -> #N/A | AV26: =IF(AV17="",NA(),AV17) -> #N/A | AW26: =IF(AW17="",NA(),AW17) -> #N/A | AX26: =IF(AX17="",NA(),AX17) -> #N/A | AY26: =IF(AY17="",NA(),AY17) -> #N/A | AZ26: =IF(AZ17="",NA(),AZ17) -> #N/A | BA26: =IF(BA17="",NA(),BA17) -> #N/A | BB26: =IF(BB17="",NA(),BB17) -> #N/A | ... BR26: =IF(BR17="",NA(),BR17) -> 90.401772
T27: ="Forecast "&"vs. "&$A$7 -> Forecast vs. 2019 | U27: =IFERROR(U22/U19-1,"") -> 0.1328125 | V27: =IFERROR(V22/V19-1,"") -> -0.038461538 | W27: =IFERROR(W22/W19-1,"") -> 0.18852688 | X27: =IFERROR(X22/X19-1,"") -> 0.36526987 | Z27: ="Forecast "&"vs. "&$A$7 -> Forecast vs. 2019 | AA27: =IFERROR(AA22/AA19-1,"") -> 0.14502104 | AB27: =IFERROR(AB22/AB19-1,"") -> 0.043141668 | AC27: =IFERROR(AC22/AC19-1,"") -> 0.099275189 | AD27: =IFERROR(AD22/AD19-1,"") -> 0.33539692 | AH27: =AH18 -> Trend 6m | AU27: =IF(AU18="",NA(),AU18) -> #N/A | AV27: =IF(AV18="",NA(),AV18) -> #N/A | AW27: =IF(AW18="",NA(),AW18) -> #N/A | AX27: =IF(AX18="",NA(),AX18) -> #N/A | AY27: =IF(AY18="",NA(),AY18) -> #N/A | AZ27: =IF(AZ18="",NA(),AZ18) -> #N/A | BA27: =IF(BA18="",NA(),BA18) -> #N/A | BB27: =IF(BB18="",NA(),BB18) -> #N/A | ... BR27: =IF(BR18="",NA(),BR18) -> 117.09091
AH28: =AH19 -> Trend 12m | AU28: =IF(AU19="",NA(),AU19) -> #N/A | AV28: =IF(AV19="",NA(),AV19) -> #N/A | AW28: =IF(AW19="",NA(),AW19) -> #N/A | AX28: =IF(AX19="",NA(),AX19) -> #N/A | AY28: =IF(AY19="",NA(),AY19) -> #N/A | AZ28: =IF(AZ19="",NA(),AZ19) -> #N/A | BA28: =IF(BA19="",NA(),BA19) -> #N/A | BB28: =IF(BB19="",NA(),BB19) -> #N/A | ... BR28: =IF(BR19="",NA(),BR19) -> 101.90686
T29: Quarter Actuals | U29: =AA29 -> Q1 | V29: =AB29 -> Q2 | W29: =AC29 -> Q3 | X29: =AD29 -> Q4 | Z29: Quarter Actuals | AA29: Q1 | AB29: Q2 | AC29: Q3 | AD29: Q4 | AH29: Forecast | AU29: =IF(AU21="",NA(),AU21) -> #N/A | AV29: =IF(AV21="",NA(),AV21) -> #N/A | AW29: =IF(AW21="",NA(),AW21) -> #N/A | AX29: =IF(AX21="",NA(),AX21) -> #N/A | AY29: =IF(AY21="",NA(),AY21) -> #N/A | AZ29: =IF(AZ21="",NA(),AZ21) -> #N/A | BA29: =IF(BA21="",NA(),BA21) -> #N/A | BB29: =IF(BB21="",NA(),BB21) -> #N/A | ... BR29: =IF(BR21="",NA(),BR21) -> 90.607036
T30: =T25 -> vs 2018 | U30: =U$21-U18 -> 112 | V30: =V$21-V18 -> 44 | W30: =W$21-W18 -> -122 | X30: =X$21-X18 -> -246 | Z30: =Z25 -> vs 2018 | AA30: =AA$21-AA18 -> 296.52776 | AB30: =AB$21-AB18 -> 244.21735 | AC30: =AC$21-AC18 -> -484.24723 | AD30: =AD$21-AD18 -> -857.366
T31: =T26 -> vs 2019 | U31: =U$21-U19 -> 34 | V31: =V$21-V19 -> -10 | W31: =W$21-W19 -> -134 | X31: =X$21-X19 -> -208 | Z31: =Z26 -> vs 2019 | AA31: =AA$21-AA19 -> 118.5648 | AB31: =AB$21-AB19 -> 37.992115 | AC31: =AC$21-AC19 -> -520.3576 | AD31: =AD$21-AD19 -> -707.76411
T32: ="Forecast "&"vs. "&$A$7 -> Forecast vs. 2019 | U32: =U22-U19 -> 34 | V32: =V22-V19 -> -10 | W32: =W22-W19 -> 48.262882 | X32: =X22-X19 -> 75.976134 | Z32: ="Forecast "&"vs. "&$A$7 -> Forecast vs. 2019 | AA32: =AA22-AA19 -> 118.5648 | AB32: =AB22-AB19 -> 37.992115 | AC32: =AC22-AC19 -> 86.260415 | AD32: =AD22-AD19 -> 237.38191
AG33: Sales
T34: QoQ GR% | U34: =AA34 -> Q1 | V34: =AB34 -> Q2 | W34: =AC34 -> Q3 | X34: =AD34 -> Q4 | Z34: QoQ GR% | AA34: Q1 | AB34: Q2 | AC34: Q3 | AD34: Q4 | AG34: Trend Calculation | AH34: Actual | AI34: =SUMIFS('Sales Data'!$E:$E,'Sales Data'!$A:$A,$E$2,'Sales Data'!$B:$B,AI$15,'Sales Data'!$C:$C,"Periodic")/1000 -> 150.41512 | AJ34: =SUMIFS('Sales Data'!$E:$E,'Sales Data'!$A:$A,$E$2,'Sales Data'!$B:$B,AJ$15,'Sales Data'!$C:$C,"Periodic")/1000 -> 201.71354 | AK34: =SUMIFS('Sales Data'!$E:$E,'Sales Data'!$A:$A,$E$2,'Sales Data'!$B:$B,AK$15,'Sales Data'!$C:$C,"Periodic")/1000 -> 287.47803 | AL34: =SUMIFS('Sales Data'!$E:$E,'Sales Data'!$A:$A,$E$2,'Sales Data'!$B:$B,AL$15,'Sales Data'!$C:$C,"Periodic")/1000 -> 207.07993 | AM34: =SUMIFS('Sales Data'!$E:$E,'Sales Data'!$A:$A,$E$2,'Sales Data'!$B:$B,AM$15,'Sales Data'!$C:$C,"Periodic")/1000 -> 204.97804 | AN34: =SUMIFS('Sales Data'!$E:$E,'Sales Data'!$A:$A,$E$2,'Sales Data'!$B:$B,AN$15,'Sales Data'!$C:$C,"Periodic")/1000 -> 262.353 | AO34: =SUMIFS('Sales Data'!$E:$E,'Sales Data'!$A:$A,$E$2,'Sales Data'!$B:$B,AO$15,'Sales Data'!$C:$C,"Periodic")/1000 -> 361.30796 | AP34: =SUMIFS('Sales Data'!$E:$E,'Sales Data'!$A:$A,$E$2,'Sales Data'!$B:$B,AP$15,'Sales Data'!$C:$C,"Periodic")/1000 -> 243.981 | ... BF34: =SUMIFS('Sales Data'!$E:$E,'Sales Data'!$A:$A,$E$2,'Sales Data'!$B:$B,BF$15,'Sales Data'!$C:$C,"Periodic")/1000 -> 196.25758 | BG34: =IF(OR(BG$8=1,BG$9=0),SUMIFS('Sales Data'!$E:$E,'Sales Data'!$A:$A,$E$2,'Sales Data'!$B:$B,BG$15,'Sales Data'!$C:$C,"Periodic")/1000,"") -> 346.82725 | BH34: =IF(OR(BH$8=1,BH$9=0),SUMIFS('Sales Data'!$E:$E,'Sales Data'!$A:$A,$E$2,'Sales Data'!$B:$B,BH$15,'Sales Data'!$C:$C,"Periodic")/1000,"") -> 238.7955 | BI34: =IF(OR(BI$8=1,BI$9=0),SUMIFS('Sales Data'!$E:$E,'Sales Data'!$A:$A,$E$2,'Sales Data'!$B:$B,BI$15,'Sales Data'!$C:$C,"Periodic")/1000,"") -> 350.5117 | BJ34: =IF(OR(BJ$8=1,BJ$9=0),SUMIFS('Sales Data'!$E:$E,'Sales Data'!$A:$A,$E$2,'Sales Data'!$B:$B,BJ$15,'Sales Data'!$C:$C,"Periodic")/1000,"") -> 268.3706 | BK34: =IF(OR(BK$8=1,BK$9=0),SUMIFS('Sales Data'!$E:$E,'Sales Data'!$A:$A,$E$2,'Sales Data'!$B:$B,BK$15,'Sales Data'!$C:$C,"Periodic")/1000,"") -> 198.77341 | BL34: =IF(OR(BL$8=1,BL$9=0),SUMIFS('Sales Data'!$E:$E,'Sales Data'!$A:$A,$E$2,'Sales Data'!$B:$B,BL$15,'Sales Data'!$C:$C,"Periodic")/1000,"") -> 451.48431 | BM34: =IF(OR(BM$8=1,BM$9=0),SUMIFS('Sales Data'!$E:$E,'Sales Data'!$A:$A,$E$2,'Sales Data'!$B:$B,BM$15,'Sales Data'!$C:$C,"Periodic")/1000,"") -> 348.54445 | BN34: =IF(OR(BN$8=1,BN$9=0),SUMIFS('Sales Data'!$E:$E,'Sales Data'!$A:$A,$E$2,'Sales Data'!$B:$B,BN$15,'Sales Data'!$C:$C,"Periodic")/1000,"") | ... BR34: =IF(OR(BR$8=1,BR$9=0),SUMIFS('Sales Data'!$E:$E,'Sales Data'!$A:$A,$E$2,'Sales Data'!$B:$B,BR$15,'Sales Data'!$C:$C,"Periodic")/1000,"")
T35: =+T19 -> 2019 Actual | U35: =IFERROR(U19/X18-1,"") -> 0.040650407 | V35: =IFERROR(V19/U19-1,"") -> 0.015625 | W35: =IFERROR(W19/V19-1,"") -> -0.015384615 | X35: =IFERROR(X19/W19-1,"") -> -0.1875 | Z35: =+Z19 -> 2019 Actual | AA35: =IFERROR(AA19/AD18-1,"") -> -0.046416992 | AB35: =IFERROR(AB19/AA19-1,"") -> 0.077139061 | AC35: =IFERROR(AC19/AB19-1,"") -> -0.013324639 | AD35: =IFERROR(AD19/AC19-1,"") -> -0.18545006 | AH35: Budget | BG35: =IF(OR(BG$8=1,BG$9=1),SUMIFS('Sales Data'!$D:$D,'Sales Data'!$A:$A,$E$2,'Sales Data'!$B:$B,BG$15,'Sales Data'!$C:$C,"Periodic")/1000,"") | BH35: =IF(OR(BH$8=1,BH$9=1),SUMIFS('Sales Data'!$D:$D,'Sales Data'!$A:$A,$E$2,'Sales Data'!$B:$B,BH$15,'Sales Data'!$C:$C,"Periodic")/1000,"") | BI35: =IF(OR(BI$8=1,BI$9=1),SUMIFS('Sales Data'!$D:$D,'Sales Data'!$A:$A,$E$2,'Sales Data'!$B:$B,BI$15,'Sales Data'!$C:$C,"Periodic")/1000,"") | BJ35: =IF(OR(BJ$8=1,BJ$9=1),SUMIFS('Sales Data'!$D:$D,'Sales Data'!$A:$A,$E$2,'Sales Data'!$B:$B,BJ$15,'Sales Data'!$C:$C,"Periodic")/1000,"") | BK35: =IF(OR(BK$8=1,BK$9=1),SUMIFS('Sales Data'!$D:$D,'Sales Data'!$A:$A,$E$2,'Sales Data'!$B:$B,BK$15,'Sales Data'!$C:$C,"Periodic")/1000,"") | BL35: =IF(OR(BL$8=1,BL$9=1),SUMIFS('Sales Data'!$D:$D,'Sales Data'!$A:$A,$E$2,'Sales Data'!$B:$B,BL$15,'Sales Data'!$C:$C,"Periodic")/1000,"") | BM35: =IF(OR(BM$8=1,BM$9=1),SUMIFS('Sales Data'!$D:$D,'Sales Data'!$A:$A,$E$2,'Sales Data'!$B:$B,BM$15,'Sales Data'!$C:$C,"Periodic")/1000,"") -> 329.69726 | BN35: =IF(OR(BN$8=1,BN$9=1),SUMIFS('Sales Data'!$D:$D,'Sales Data'!$A:$A,$E$2,'Sales Data'!$B:$B,BN$15,'Sales Data'!$C:$C,"Periodic")/1000,"") -> 290.16687 | ... BR35: =IF(OR(BR$8=1,BR$9=1),SUMIFS('Sales Data'!$D:$D,'Sales Data'!$A:$A,$E$2,'Sales Data'!$B:$B,BR$15,'Sales Data'!$C:$C,"Periodic")/1000,"") -> 301.56365
T36: =+T20 -> 2020 Budget | U36: =IFERROR(U20/X19-1,"") -> 0.30592296 | V36: =IFERROR(V20/U20-1,"") -> -0.00087592781 | W36: =IFERROR(W20/V20-1,"") -> 0.044653339 | X36: =IFERROR(X20/W20-1,"") -> -0.049807722 | Z36: =+Z20 -> 2020 Budget | AA36: =IFERROR(AA20/AD19-1,"") -> 0.21614697 | AB36: =IFERROR(AB20/AA20-1,"") -> 0.091018908 | AC36: =IFERROR(AC20/AB20-1,"") -> -0.0029539217 | AD36: =IFERROR(AD20/AC20-1,"") -> 0.00943138 | AH36: Trend 6m | BG36: =IF(BG$9,FORECAST(BG$12,$AP34:BF34,$AP12:BF12), "") | BH36: =IF(BH$9,FORECAST(BH$12,$AP34:BG34,$AP12:BG12), "") | BI36: =IF(BI$9,FORECAST(BI$12,$AP34:BH34,$AP12:BH12), "") | BJ36: =IF(BJ$9,FORECAST(BJ$12,$AP34:BI34,$AP12:BI12), "") | BK36: =IF(BK$9,FORECAST(BK$12,$AP34:BJ34,$AP12:BJ12), "") | BL36: =IF(BL$9,FORECAST(BL$12,$AP34:BK34,$AP12:BK12), "") | BM36: =IF(BM$9,FORECAST(BM$12,$AP34:BL34,$AP12:BL12), "") | BN36: =IF(BN$9,FORECAST(BN$12,$AP34:BM34,$AP12:BM12), "") -> 344.4583 | ... BR36: =IF(BR$9,FORECAST(BR$12,$AP34:BQ34,$AP12:BQ12), "") -> 377.60434
T37: =+T21 -> 2020 Actual | U37: =IF(U21<>0,IFERROR(U21/X19-1,""),"") -> 0.39423077 | V37: =IF(V21<>0,IFERROR(V21/U21-1,""),"") -> -0.13793103 | W37: =IF(W21<>0,IFERROR(W21/V21-1,""),"") -> -0.512 | X37: =IF(X21<>0,IFERROR(X21/W21-1,""),"") | Z37: =+Z21 -> 2020 Actual | AA37: =IF(AA21<>0,IFERROR(AA21/AD19-1,""),"") -> 0.32266447 | AB37: =IF(AB21<>0,IFERROR(AB21/AA21-1,""),"") -> -0.018700442 | AC37: =IF(AC21<>0,IFERROR(AC21/AB21-1,""),"") -> -0.62058164 | AD37: =IF(AD21<>0,IFERROR(AD21/AC21-1,""),"") | AH37: Trend 12m | BG37: =IF(BG$9,FORECAST(BG$13,$AP34:BF34,$AP13:BF13), "") | BH37: =IF(BH$9,FORECAST(BH$13,$AP34:BG34,$AP13:BG13), "") | BI37: =IF(BI$9,FORECAST(BI$13,$AP34:BH34,$AP13:BH13), "") | BJ37: =IF(BJ$9,FORECAST(BJ$13,$AP34:BI34,$AP13:BI13), "") | BK37: =IF(BK$9,FORECAST(BK$13,$AP34:BJ34,$AP13:BJ13), "") | BL37: =IF(BL$9,FORECAST(BL$13,$AP34:BK34,$AP13:BK13), "") | BM37: =IF(BM$9,FORECAST(BM$13,$AP34:BL34,$AP13:BL13), "") | BN37: =IF(BN$9,FORECAST(BN$13,$AP34:BM34,$AP13:BM13), "") -> 312.88756 | ... BR37: =IF(BR$9,FORECAST(BR$13,$AP34:BQ34,$AP13:BQ13), "") -> 322.41928
T38: Forecast | U38: =IFERROR(U22/X19-1,"") -> 0.39423077 | V38: =IFERROR(V22/U22-1,"") -> -0.13793103 | W38: =IFERROR(W22/V22-1,"") -> 0.21705153 | X38: =IFERROR(X22/W22-1,"") -> -0.066675068 | Z38: Forecast | AA38: =IFERROR(AA22/AD19-1,"") -> 0.32266447 | AB38: =IFERROR(AB22/AA22-1,"") -> -0.018700442 | AC38: =IFERROR(AC22/AB22-1,"") -> 0.039770318 | AD38: =IFERROR(AD22/AC22-1,"") -> -0.010486636 | AH38: Budget | BG38: =SUMIFS('Sales Data'!$D:$D,'Sales Data'!$A:$A,$E$2,'Sales Data'!$B:$B,BG$15,'Sales Data'!$C:$C,"Periodic")/1000 -> 293.65757 | BH38: =SUMIFS('Sales Data'!$D:$D,'Sales Data'!$A:$A,$E$2,'Sales Data'!$B:$B,BH$15,'Sales Data'!$C:$C,"Periodic")/1000 -> 265.52396 | BI38: =SUMIFS('Sales Data'!$D:$D,'Sales Data'!$A:$A,$E$2,'Sales Data'!$B:$B,BI$15,'Sales Data'!$C:$C,"Periodic")/1000 -> 301.56365 | BJ38: =SUMIFS('Sales Data'!$D:$D,'Sales Data'!$A:$A,$E$2,'Sales Data'!$B:$B,BJ$15,'Sales Data'!$C:$C,"Periodic")/1000 -> 314.80977 | BK38: =SUMIFS('Sales Data'!$D:$D,'Sales Data'!$A:$A,$E$2,'Sales Data'!$B:$B,BK$15,'Sales Data'!$C:$C,"Periodic")/1000 -> 313.88511 | BL38: =SUMIFS('Sales Data'!$D:$D,'Sales Data'!$A:$A,$E$2,'Sales Data'!$B:$B,BL$15,'Sales Data'!$C:$C,"Periodic")/1000 -> 310.3944 | BM38: =SUMIFS('Sales Data'!$D:$D,'Sales Data'!$A:$A,$E$2,'Sales Data'!$B:$B,BM$15,'Sales Data'!$C:$C,"Periodic")/1000 -> 329.69726 | BN38: =SUMIFS('Sales Data'!$D:$D,'Sales Data'!$A:$A,$E$2,'Sales Data'!$B:$B,BN$15,'Sales Data'!$C:$C,"Periodic")/1000 -> 290.16687 | ... BR38: =SUMIFS('Sales Data'!$D:$D,'Sales Data'!$A:$A,$E$2,'Sales Data'!$B:$B,BR$15,'Sales Data'!$C:$C,"Periodic")/1000 -> 301.56365
AH39: Forecast | BG39: =IF(OR(BG$8=1,BG$9=1),F17,"") | BH39: =IF(OR(BH$8=1,BH$9=1),G17,"") | BI39: =IF(OR(BI$8=1,BI$9=1),H17,"") | BJ39: =IF(OR(BJ$8=1,BJ$9=1),I17,"") | BK39: =IF(OR(BK$8=1,BK$9=1),J17,"") | BL39: =IF(OR(BL$8=1,BL$9=1),K17,"") | BM39: =IF(OR(BM$8=1,BM$9=1),L17,"") -> 348.54445 | BN39: =IF(OR(BN$8=1,BN$9=1),M17,"") -> 290.16687 | ... BR39: =IF(OR(BR$8=1,BR$9=1),Q17,"") -> 301.56365
AH40: Trend 6m | BG40: =IF(BG36="",BG38,BG36) -> 293.65757 | BH40: =IF(BH36="",BH38,BH36) -> 265.52396 | BI40: =IF(BI36="",BI38,BI36) -> 301.56365 | BJ40: =IF(BJ36="",BJ38,BJ36) -> 314.80977 | BK40: =IF(BK36="",BK38,BK36) -> 313.88511 | BL40: =IF(BL36="",BL38,BL36) -> 310.3944 | BM40: =IF(BM36="",BM38,BM36) -> 329.69726 | BN40: =IF(BN36="",BN38,BN36) -> 344.4583 | ... BR40: =IF(BR36="",BR38,BR36) -> 377.60434 | BS40: =SUM(BG40:BR40) -> 3934.6883
AG41: Run rates | AH41: Trend 12m | BG41: =IF(BG37="",BG38,BG37) -> 293.65757 | BH41: =IF(BH37="",BH38,BH37) -> 265.52396 | BI41: =IF(BI37="",BI38,BI37) -> 301.56365 | BJ41: =IF(BJ37="",BJ38,BJ37) -> 314.80977 | BK41: =IF(BK37="",BK38,BK37) -> 313.88511 | BL41: =IF(BL37="",BL38,BL37) -> 310.3944 | BM41: =IF(BM37="",BM38,BM37) -> 329.69726 | BN41: =IF(BN37="",BN38,BN37) -> 312.88756 | ... BR41: =IF(BR37="",BR38,BR37) -> 322.41928 | BS41: =SUM(BG41:BR41) -> 3717.7988
AG43: Trend Charts | AH43: =AH34 -> Actual | AU43: =IF(AU34="",NA(),AU34) -> 331.44905 | AV43: =IF(AV34="",NA(),AV34) -> 192.22995 | AW43: =IF(AW34="",NA(),AW34) -> 293.89065 | AX43: =IF(AX34="",NA(),AX34) -> 298.2346 | AY43: =IF(AY34="",NA(),AY34) -> 370.87774 | AZ43: =IF(AZ34="",NA(),AZ34) -> 211.52387 | BA43: =IF(BA34="",NA(),BA34) -> 330.49778 | BB43: =IF(BB34="",NA(),BB34) -> 207.34384 | ... BR43: =IF(BR34="",NA(),BR34) -> #N/A
AH44: =AH38 -> Budget | AU44: =IF(AU35="",NA(),AU35) -> #N/A | AV44: =IF(AV35="",NA(),AV35) -> #N/A | AW44: =IF(AW35="",NA(),AW35) -> #N/A | AX44: =IF(AX35="",NA(),AX35) -> #N/A | AY44: =IF(AY35="",NA(),AY35) -> #N/A | AZ44: =IF(AZ35="",NA(),AZ35) -> #N/A | BA44: =IF(BA35="",NA(),BA35) -> #N/A | BB44: =IF(BB35="",NA(),BB35) -> #N/A | ... BR44: =IF(BR35="",NA(),BR35) -> 301.56365
AH45: =AH36 -> Trend 6m | AU45: =IF(AU36="",NA(),AU36) -> #N/A | AV45: =IF(AV36="",NA(),AV36) -> #N/A | AW45: =IF(AW36="",NA(),AW36) -> #N/A | AX45: =IF(AX36="",NA(),AX36) -> #N/A | AY45: =IF(AY36="",NA(),AY36) -> #N/A | AZ45: =IF(AZ36="",NA(),AZ36) -> #N/A | BA45: =IF(BA36="",NA(),BA36) -> #N/A | BB45: =IF(BB36="",NA(),BB36) -> #N/A | ... BR45: =IF(BR36="",NA(),BR36) -> 377.60434
AH46: =AH37 -> Trend 12m | AU46: =IF(AU37="",NA(),AU37) -> #N/A | AV46: =IF(AV37="",NA(),AV37) -> #N/A | AW46: =IF(AW37="",NA(),AW37) -> #N/A | AX46: =IF(AX37="",NA(),AX37) -> #N/A | AY46: =IF(AY37="",NA(),AY37) -> #N/A | AZ46: =IF(AZ37="",NA(),AZ37) -> #N/A | BA46: =IF(BA37="",NA(),BA37) -> #N/A | BB46: =IF(BB37="",NA(),BB37) -> #N/A | ... BR46: =IF(BR37="",NA(),BR37) -> 322.41928
AH47: Forecast | AU47: =IF(AU39="",NA(),AU39) -> #N/A | AV47: =IF(AV39="",NA(),AV39) -> #N/A | AW47: =IF(AW39="",NA(),AW39) -> #N/A | AX47: =IF(AX39="",NA(),AX39) -> #N/A | AY47: =IF(AY39="",NA(),AY39) -> #N/A | AZ47: =IF(AZ39="",NA(),AZ39) -> #N/A | BA47: =IF(BA39="",NA(),BA39) -> #N/A | BB47: =IF(BB39="",NA(),BB39) -> #N/A | ... BR47: =IF(BR39="",NA(),BR39) -> 301.56365

Sheet Tables
E2: Tables
T4: Units | Z4: Sales in kUSD | BF4: Current month | BG4: Prior month
E5: Units | F5: =Mapping!$D$2 -> Jan | G5: =Mapping!$D$3 -> Feb | H5: =Mapping!$D$4 -> Mar | I5: =Mapping!$D$5 -> Apr | J5: =Mapping!$D$6 -> May | K5: =Mapping!$D$7 -> Jun | L5: =Mapping!$D$8 -> Jul | M5: =Mapping!$D$9 -> Aug | N5: =Mapping!$D$10 -> Sep | O5: =Mapping!$D$11 -> Oct | P5: =Mapping!$D$12 -> Nov | Q5: =Mapping!$D$13 -> Dec | R5: FY | T5: =Z5 -> Forecast based on: | W5: =AC5 -> FY | X5: =AD5 -> vs. LO | Z5: Forecast based on: | AC5: FY | AD5: vs. LO | BF5: =Summary!$D$3 -> 7 | BG5: =BF5-1 -> 6
A6: =Summary!$C$2-2 -> 2018 | B6: =Mapping!$B$2 -> Actual | E6: =A6&" "&B6 -> 2018 Actual | F6: =SUMIFS('Units sold'!$E:$E,'Units sold'!$A:$A,$E$2,'Units sold'!$B:$B,F$5&" "&$A6,'Units sold'!$C:$C,"Periodic") -> 188 | G6: =SUMIFS('Units sold'!$E:$E,'Units sold'!$A:$A,$E$2,'Units sold'!$B:$B,G$5&" "&$A6,'Units sold'!$C:$C,"Periodic") -> 224 | H6: =SUMIFS('Units sold'!$E:$E,'Units sold'!$A:$A,$E$2,'Units sold'!$B:$B,H$5&" "&$A6,'Units sold'!$C:$C,"Periodic") -> 328 | I6: =SUMIFS('Units sold'!$E:$E,'Units sold'!$A:$A,$E$2,'Units sold'!$B:$B,I$5&" "&$A6,'Units sold'!$C:$C,"Periodic") -> 268 | J6: =SUMIFS('Units sold'!$E:$E,'Units sold'!$A:$A,$E$2,'Units sold'!$B:$B,J$5&" "&$A6,'Units sold'!$C:$C,"Periodic") -> 340 | K6: =SUMIFS('Units sold'!$E:$E,'Units sold'!$A:$A,$E$2,'Units sold'!$B:$B,K$5&" "&$A6,'Units sold'!$C:$C,"Periodic") -> 256 | L6: =SUMIFS('Units sold'!$E:$E,'Units sold'!$A:$A,$E$2,'Units sold'!$B:$B,L$5&" "&$A6,'Units sold'!$C:$C,"Periodic") -> 256 | M6: =SUMIFS('Units sold'!$E:$E,'Units sold'!$A:$A,$E$2,'Units sold'!$B:$B,M$5&" "&$A6,'Units sold'!$C:$C,"Periodic") -> 274 | ... Q6: =SUMIFS('Units sold'!$E:$E,'Units sold'!$A:$A,$E$2,'Units sold'!$B:$B,Q$5&" "&$A6,'Units sold'!$C:$C,"Periodic") -> 410 | R6: =SUM(F6:Q6) -> 3620 | T6: =Z6 -> 3-month Rolling Rate | W6: =(SUM(AR8:AT8)/3*Summary!$E$3)+R9 -> 2696 | X6: =$W$6-$R$8 -> -4070.654 | Z6: 3-month Rolling Rate | AC6: =(SUM(AR9:AT9)/3*Summary!$E$3)+R16 -> 2793.6432 | AD6: =$AC$6-$R$15 -> -3143.6962 | BF6: Month | BG6: 1 | BH6: 2 | BI6: 3 | BJ6: 4 | BK6: 5 | BL6: 6 | BM6: 7 | BN6: 8 | BO6: 9 | BP6: 10 | BQ6: 11 | BR6: 12
A7: =Summary!$C$2-1 -> 2019 | B7: =Mapping!$B$2 -> Actual | E7: =A7&" "&B7 -> 2019 Actual | F7: =SUMIFS('Units sold'!$E:$E,'Units sold'!$A:$A,$E$2,'Units sold'!$B:$B,F$5&" "&$A7,'Units sold'!$C:$C,"Periodic") -> 376 | G7: =SUMIFS('Units sold'!$E:$E,'Units sold'!$A:$A,$E$2,'Units sold'!$B:$B,G$5&" "&$A7,'Units sold'!$C:$C,"Periodic") -> 324 | H7: =SUMIFS('Units sold'!$E:$E,'Units sold'!$A:$A,$E$2,'Units sold'!$B:$B,H$5&" "&$A7,'Units sold'!$C:$C,"Periodic") -> 312 | I7: =SUMIFS('Units sold'!$E:$E,'Units sold'!$A:$A,$E$2,'Units sold'!$B:$B,I$5&" "&$A7,'Units sold'!$C:$C,"Periodic") -> 406 | J7: =SUMIFS('Units sold'!$E:$E,'Units sold'!$A:$A,$E$2,'Units sold'!$B:$B,J$5&" "&$A7,'Units sold'!$C:$C,"Periodic") -> 358 | K7: =SUMIFS('Units sold'!$E:$E,'Units sold'!$A:$A,$E$2,'Units sold'!$B:$B,K$5&" "&$A7,'Units sold'!$C:$C,"Periodic") -> 456 | L7: =SUMIFS('Units sold'!$E:$E,'Units sold'!$A:$A,$E$2,'Units sold'!$B:$B,L$5&" "&$A7,'Units sold'!$C:$C,"Periodic") -> 392 | M7: =SUMIFS('Units sold'!$E:$E,'Units sold'!$A:$A,$E$2,'Units sold'!$B:$B,M$5&" "&$A7,'Units sold'!$C:$C,"Periodic") -> 412 | ... Q7: =SUMIFS('Units sold'!$E:$E,'Units sold'!$A:$A,$E$2,'Units sold'!$B:$B,Q$5&" "&$A7,'Units sold'!$C:$C,"Periodic") -> 366 | R7: =SUM(F7:Q7) -> 4878 | T7: =Z7 -> 2020 Trend 6 months | W7: =BS22 -> 5511.143 | X7: =$W$7-$R$8 -> -1255.5111 | Z7: =A9&" Trend 6 months" -> 2020 Trend 6 months | AC7: =BS40 -> 5012.0888 | AD7: =$AC$7-$R$15 -> -925.25055
A8: =Summary!$C$2 -> 2020 | B8: =Mapping!$B$3 -> Budget | E8: =A8&" "&B8 -> 2020 Budget | F8: =SUMIFS('Units sold'!$D:$D,'Units sold'!$A:$A,$E$2,'Units sold'!$B:$B,F$5&" "&$A8,'Units sold'!$C:$C,"Periodic") -> 520.49613 | G8: =SUMIFS('Units sold'!$D:$D,'Units sold'!$A:$A,$E$2,'Units sold'!$B:$B,G$5&" "&$A8,'Units sold'!$C:$C,"Periodic") -> 484.69531 | H8: =SUMIFS('Units sold'!$D:$D,'Units sold'!$A:$A,$E$2,'Units sold'!$B:$B,H$5&" "&$A8,'Units sold'!$C:$C,"Periodic") -> 461.69058 | I8: =SUMIFS('Units sold'!$D:$D,'Units sold'!$A:$A,$E$2,'Units sold'!$B:$B,I$5&" "&$A8,'Units sold'!$C:$C,"Periodic") -> 599.5068 | J8: =SUMIFS('Units sold'!$D:$D,'Units sold'!$A:$A,$E$2,'Units sold'!$B:$B,J$5&" "&$A8,'Units sold'!$C:$C,"Periodic") -> 534.14345 | K8: =SUMIFS('Units sold'!$D:$D,'Units sold'!$A:$A,$E$2,'Units sold'!$B:$B,K$5&" "&$A8,'Units sold'!$C:$C,"Periodic") -> 619.13611 | L8: =SUMIFS('Units sold'!$D:$D,'Units sold'!$A:$A,$E$2,'Units sold'!$B:$B,L$5&" "&$A8,'Units sold'!$C:$C,"Periodic") -> 586.56549 | M8: =SUMIFS('Units sold'!$D:$D,'Units sold'!$A:$A,$E$2,'Units sold'!$B:$B,M$5&" "&$A8,'Units sold'!$C:$C,"Periodic") -> 610.84171 | ... Q8: =SUMIFS('Units sold'!$D:$D,'Units sold'!$A:$A,$E$2,'Units sold'!$B:$B,Q$5&" "&$A8,'Units sold'!$C:$C,"Periodic") -> 575.03394 | R8: =SUM(F8:Q8) -> 6766.654 | T8: =Z8 -> 2020 Trend 12 months | W8: =BS23 -> 5836.0868 | X8: =$W$8-$R$8 -> -930.5672 | Z8: =A9&" Trend 12 months" -> 2020 Trend 12 months | AC8: =BS41 -> 5398.6511 | AD8: =$AC$8-$R$15 -> -538.68824 | BF8: trend key | BG8: =IF($BF$5=BG6,1,0) -> 0 | BH8: =IF($BF$5=BH6,1,0) -> 0 | BI8: =IF($BF$5=BI6,1,0) -> 0 | BJ8: =IF($BF$5=BJ6,1,0) -> 0 | BK8: =IF($BF$5=BK6,1,0) -> 0 | BL8: =IF($BF$5=BL6,1,0) -> 0 | BM8: =IF($BF$5=BM6,1,0) -> 1 | BN8: =IF($BF$5=BN6,1,0) -> 0 | ... BR8: =IF($BF$5=BR6,1,0) -> 0
A9: =Summary!$C$2 -> 2020 | B9: =Mapping!$B$2 -> Actual | E9: =A9&" "&B9 -> 2020 Actual | F9: =SUMIFS('Units sold'!$E:$E,'Units sold'!$A:$A,$E$2,'Units sold'!$B:$B,F$5&" "&$A9,'Units sold'!$C:$C,"Periodic") -> 396 | G9: =SUMIFS('Units sold'!$E:$E,'Units sold'!$A:$A,$E$2,'Units sold'!$B:$B,G$5&" "&$A9,'Units sold'!$C:$C,"Periodic") -> 356 | H9: =SUMIFS('Units sold'!$E:$E,'Units sold'!$A:$A,$E$2,'Units sold'!$B:$B,H$5&" "&$A9,'Units sold'!$C:$C,"Periodic") -> 414 | I9: =SUMIFS('Units sold'!$E:$E,'Units sold'!$A:$A,$E$2,'Units sold'!$B:$B,I$5&" "&$A9,'Units sold'!$C:$C,"Periodic") -> 326 | J9: =SUMIFS('Units sold'!$E:$E,'Units sold'!$A:$A,$E$2,'Units sold'!$B:$B,J$5&" "&$A9,'Units sold'!$C:$C,"Periodic") -> 366 | K9: =SUMIFS('Units sold'!$E:$E,'Units sold'!$A:$A,$E$2,'Units sold'!$B:$B,K$5&" "&$A9,'Units sold'!$C:$C,"Periodic") -> 442 | L9: =SUMIFS('Units sold'!$E:$E,'Units sold'!$A:$A,$E$2,'Units sold'!$B:$B,L$5&" "&$A9,'Units sold'!$C:$C,"Periodic") -> 396 | M9: =SUMIFS('Units sold'!$E:$E,'Units sold'!$A:$A,$E$2,'Units sold'!$B:$B,M$5&" "&$A9,'Units sold'!$C:$C,"Periodic") -> 0 | ... Q9: =SUMIFS('Units sold'!$E:$E,'Units sold'!$A:$A,$E$2,'Units sold'!$B:$B,Q$5&" "&$A9,'Units sold'!$C:$C,"Periodic") -> 0 | R9: =SUM(F9:Q9) -> 2696 | T9: =Z9 -> Prior Year exit rate (Q4 x 4) | W9: =SUM($O$7:$Q$7)*4 -> 5720 | X9: =$W$9-$R$8 -> -1046.654 | Z9: Prior Year exit rate (Q4 x 4) | AC9: =SUM($O$14:$Q$14)*4 -> 6865.5196 | AD9: =$AC$9-$R$15 -> 928.18024 | BF9: trend key | BG9: =SUM($BG8:BG8) -> 0 | BH9: =SUM($BG8:BG8) -> 0 | BI9: =SUM($BG8:BH8) -> 0 | BJ9: =SUM($BG8:BI8) -> 0 | BK9: =SUM($BG8:BJ8) -> 0 | BL9: =SUM($BG8:BK8) -> 0 | BM9: =SUM($BG8:BL8) -> 0 | BN9: =SUM($BG8:BM8) -> 1 | BO9: =SUM($BG8:BN8) -> 1 | ... BR9: =SUM($BG8:BQ8) -> 1
E10: Forecast | F10: =IF(F9=0,F17/F24,F9) -> 396 | G10: =IF(G9=0,G17/G24,G9) -> 356 | H10: =IF(H9=0,H17/H24,H9) -> 414 | I10: =IF(I9=0,I17/I24,I9) -> 326 | J10: =IF(J9=0,J17/J24,J9) -> 366 | K10: =IF(K9=0,K17/K24,K9) -> 442 | L10: =IF(L9=0,L17/L24,L9) -> 396 | M10: =IF(M9=0,M17/M24,M9) -> 474.78994 | ... Q10: =IF(Q9=0,Q17/Q24,Q9) -> 441.09293 | R10: =SUM(F10:Q10) -> 5033.6979 | BG10: 1 | BH10: 2 | BI10: 3 | BJ10: 4 | BK10: 5 | BL10: 6 | BM10: 7 | BN10: 8 | BO10: 9 | BP10: 10 | BQ10: 11 | BR10: 12
E12: Sales in kUSD | F12: =F$5 -> Jan | G12: =G$5 -> Feb | H12: =H$5 -> Mar | I12: =I$5 -> Apr | J12: =J$5 -> May | K12: =K$5 -> Jun | L12: =L$5 -> Jul | M12: =M$5 -> Aug | ... Q12: =Q$5 -> Dec | R12: FY | T12: Growth vs PY | V12: =AB12 -> YTD | W12: =AC12 -> YTG | X12: =AD12 -> Delta | Z12: Growth vs PY | AB12: YTD | AC12: YTG | AD12: Delta | AH12: 6m trend key | BC12: =BB12+1 -> 1 | BD12: =BC12+1 -> 2 | BE12: =BD12+1 -> 3 | BF12: =BE12+1 -> 4 | BG12: =BF12+1 -> 5 | BH12: =BG12+1 -> 6 | BI12: =BH12+1 -> 7 | BJ12: =BI12+1 -> 8 | ... BR12: =BQ12+1 -> 16
A13: =Summary!$C$2-2 -> 2018 | B13: =Mapping!$B$2 -> Actual | E13: =A13&" "&B13 -> 2018 Actual | F13: =SUMIFS('Sales Data'!$E:$E,'Sales Data'!$A:$A,$E$2,'Sales Data'!$B:$B,F$12&" "&$A13,'Sales Data'!$C:$C,"Periodic")/1000 -> 278.68442 | G13: =SUMIFS('Sales Data'!$E:$E,'Sales Data'!$A:$A,$E$2,'Sales Data'!$B:$B,G$12&" "&$A13,'Sales Data'!$C:$C,"Periodic")/1000 -> 312.65156 | H13: =SUMIFS('Sales Data'!$E:$E,'Sales Data'!$A:$A,$E$2,'Sales Data'!$B:$B,H$12&" "&$A13,'Sales Data'!$C:$C,"Periodic")/1000 -> 477.07185 | I13: =SUMIFS('Sales Data'!$E:$E,'Sales Data'!$A:$A,$E$2,'Sales Data'!$B:$B,I$12&" "&$A13,'Sales Data'!$C:$C,"Periodic")/1000 -> 334.04349 | J13: =SUMIFS('Sales Data'!$E:$E,'Sales Data'!$A:$A,$E$2,'Sales Data'!$B:$B,J$12&" "&$A13,'Sales Data'!$C:$C,"Periodic")/1000 -> 496.15918 | K13: =SUMIFS('Sales Data'!$E:$E,'Sales Data'!$A:$A,$E$2,'Sales Data'!$B:$B,K$12&" "&$A13,'Sales Data'!$C:$C,"Periodic")/1000 -> 351.99729 | L13: =SUMIFS('Sales Data'!$E:$E,'Sales Data'!$A:$A,$E$2,'Sales Data'!$B:$B,L$12&" "&$A13,'Sales Data'!$C:$C,"Periodic")/1000 -> 329.62864 | M13: =SUMIFS('Sales Data'!$E:$E,'Sales Data'!$A:$A,$E$2,'Sales Data'!$B:$B,M$12&" "&$A13,'Sales Data'!$C:$C,"Periodic")/1000 -> 346.77263 | ... Q13: =SUMIFS('Sales Data'!$E:$E,'Sales Data'!$A:$A,$E$2,'Sales Data'!$B:$B,Q$12&" "&$A13,'Sales Data'!$C:$C,"Periodic")/1000 -> 358.29916 | R13: =SUM(F13:Q13) -> 4745.4063 | T13: =Z13 -> GR% | V13: =IFERROR(($R$9/SUM(OFFSET(E7,,1,1,Summary!$D$3))-1),"") -> 0.027439024 | W13: =((R8-R9)/(R7-SUM(OFFSET(E7,0,1,1,Summary!$D$3))))-1 -> 0.80596896 | X13: =IFERROR(W13-V13,"") -> 0.77852993 | Z13: GR% | AB13: =IFERROR(R16/SUM(OFFSET(E14,0,1,1,Summary!$D$3))-1,"") -> -0.15146711 | AC13: =IFERROR((R15-R16)/(R14-SUM(OFFSET(E14,0,1,1,Summary!$D$3)))-1,"") -> 0.18677701 | AD13: =IFERROR(AC13-AB13,"") -> 0.33824411 | AH13: 12m trend key | AW13: =AV13+1 -> 1 | AX13: =AW13+1 -> 2 | AY13: =AX13+1 -> 3 | AZ13: =AY13+1 -> 4 | BA13: =AZ13+1 -> 5 | BB13: =BA13+1 -> 6 | BC13: =BB13+1 -> 7 | BD13: =BC13+1 -> 8 | ... BR13: =BQ13+1 -> 22
A14: =Summary!$C$2-1 -> 2019 | B14: =Mapping!$B$2 -> Actual | E14: =A14&" "&B14 -> 2019 Actual | F14: =SUMIFS('Sales Data'!$E:$E,'Sales Data'!$A:$A,$E$2,'Sales Data'!$B:$B,F$12&" "&$A14,'Sales Data'!$C:$C,"Periodic")/1000 -> 450.49035 | G14: =SUMIFS('Sales Data'!$E:$E,'Sales Data'!$A:$A,$E$2,'Sales Data'!$B:$B,G$12&" "&$A14,'Sales Data'!$C:$C,"Periodic")/1000 -> 418.08677 | H14: =SUMIFS('Sales Data'!$E:$E,'Sales Data'!$A:$A,$E$2,'Sales Data'!$B:$B,H$12&" "&$A14,'Sales Data'!$C:$C,"Periodic")/1000 -> 363.19783 | I14: =SUMIFS('Sales Data'!$E:$E,'Sales Data'!$A:$A,$E$2,'Sales Data'!$B:$B,I$12&" "&$A14,'Sales Data'!$C:$C,"Periodic")/1000 -> 589.79345 | J14: =SUMIFS('Sales Data'!$E:$E,'Sales Data'!$A:$A,$E$2,'Sales Data'!$B:$B,J$12&" "&$A14,'Sales Data'!$C:$C,"Periodic")/1000 -> 473.90504 | K14: =SUMIFS('Sales Data'!$E:$E,'Sales Data'!$A:$A,$E$2,'Sales Data'!$B:$B,K$12&" "&$A14,'Sales Data'!$C:$C,"Periodic")/1000 -> 550.8607 | L14: =SUMIFS('Sales Data'!$E:$E,'Sales Data'!$A:$A,$E$2,'Sales Data'!$B:$B,L$12&" "&$A14,'Sales Data'!$C:$C,"Periodic")/1000 -> 445.98746 | M14: =SUMIFS('Sales Data'!$E:$E,'Sales Data'!$A:$A,$E$2,'Sales Data'!$B:$B,M$12&" "&$A14,'Sales Data'!$C:$C,"Periodic")/1000 -> 508.46155 | ... Q14: =SUMIFS('Sales Data'!$E:$E,'Sales Data'!$A:$A,$E$2,'Sales Data'!$B:$B,Q$12&" "&$A14,'Sales Data'!$C:$C,"Periodic")/1000 -> 383.17004 | R14: =SUM(F14:Q14) -> 5941.2575 | T14: Avg. packs per month | V14: =IFERROR(R9/Summary!$D$3,"") -> 385.14286 | W14: =IFERROR((R8-R9)/Summary!$E$3,"") -> 814.13081 | X14: =IFERROR(W14-V14,"") -> 428.98795 | Z14: Avg. sales | AB14: =R16/Summary!$D$3 -> 399.09188 | AC14: =IFERROR((R15-R16)/Summary!$E$3,"") -> 628.73924 | AD14: =IFERROR(AC14-AB14,"") -> 229.64735 | AG14: Units
A15: =Summary!$C$2 -> 2020 | B15: =Mapping!$B$3 -> Budget | E15: =A15&" "&B15 -> 2020 Budget | F15: =SUMIFS('Sales Data'!$D:$D,'Sales Data'!$A:$A,$E$2,'Sales Data'!$B:$B,F$12&" "&$A15,'Sales Data'!$C:$C,"Periodic")/1000 -> 510.53316 | G15: =SUMIFS('Sales Data'!$D:$D,'Sales Data'!$A:$A,$E$2,'Sales Data'!$B:$B,G$12&" "&$A15,'Sales Data'!$C:$C,"Periodic")/1000 -> 512.81953 | H15: =SUMIFS('Sales Data'!$D:$D,'Sales Data'!$A:$A,$E$2,'Sales Data'!$B:$B,H$12&" "&$A15,'Sales Data'!$C:$C,"Periodic")/1000 -> 480.23917 | I15: =SUMIFS('Sales Data'!$D:$D,'Sales Data'!$A:$A,$E$2,'Sales Data'!$B:$B,I$12&" "&$A15,'Sales Data'!$C:$C,"Periodic")/1000 -> 523.32732 | J15: =SUMIFS('Sales Data'!$D:$D,'Sales Data'!$A:$A,$E$2,'Sales Data'!$B:$B,J$12&" "&$A15,'Sales Data'!$C:$C,"Periodic")/1000 -> 510.74624 | K15: =SUMIFS('Sales Data'!$D:$D,'Sales Data'!$A:$A,$E$2,'Sales Data'!$B:$B,K$12&" "&$A15,'Sales Data'!$C:$C,"Periodic")/1000 -> 526.3021 | L15: =SUMIFS('Sales Data'!$D:$D,'Sales Data'!$A:$A,$E$2,'Sales Data'!$B:$B,L$12&" "&$A15,'Sales Data'!$C:$C,"Periodic")/1000 -> 451.00764 | M15: =SUMIFS('Sales Data'!$D:$D,'Sales Data'!$A:$A,$E$2,'Sales Data'!$B:$B,M$12&" "&$A15,'Sales Data'!$C:$C,"Periodic")/1000 -> 491.98578 | ... Q15: =SUMIFS('Sales Data'!$D:$D,'Sales Data'!$A:$A,$E$2,'Sales Data'!$B:$B,Q$12&" "&$A15,'Sales Data'!$C:$C,"Periodic")/1000 -> 457.06834 | R15: =SUM(F15:Q15) -> 5937.3393 | AG15: Trend Calculation | AI15: ='Bridges for Trends'!Y4 -> Jan 2018 | AJ15: ='Bridges for Trends'!X4 -> Feb 2018 | AK15: ='Bridges for Trends'!W4 -> Mar 2018 | AL15: ='Bridges for Trends'!V4 -> Apr 2018 | AM15: ='Bridges for Trends'!U4 -> May 2018 | AN15: ='Bridges for Trends'!T4 -> Jun 2018 | AO15: ='Bridges for Trends'!S4 -> Jul 2018 | AP15: ='Bridges for Trends'!R4 -> Aug 2018 | AQ15: ='Bridges for Trends'!Q4 -> Sep 2018 | AR15: ='Bridges for Trends'!P4 -> Oct 2018 | AS15: ='Bridges for Trends'!O4 -> Nov 2018 | AT15: ='Bridges for Trends'!N4 -> Dec 2018 | AU15: ='Bridges for Trends'!M4 -> Jan 2019 | AV15: ='Bridges for Trends'!L4 -> Feb 2019 | AW15: ='Bridges for Trends'!K4 -> Mar 2019 | AX15: ='Bridges for Trends'!J4 -> Apr 2019 | AY15: ='Bridges for Trends'!I4 -> May 2019 | AZ15: ='Bridges for Trends'!H4 -> Jun 2019 | BA15: ='Bridges for Trends'!G4 -> Jul 2019 | BB15: ='Bridges for Trends'!F4 -> Aug 2019 | BC15: ='Bridges for Trends'!E4 -> Sep 2019 | BD15: ='Bridges for Trends'!D4 -> Oct 2019 | BE15: ='Bridges for Trends'!C4 -> Nov 2019 | BF15: ='Bridges for Trends'!B4 -> Dec 2019 | BG15: ='Bridges for Trends'!A4 -> Jan 2020 | BH15: ='Bridges for Trends'!A5 -> Feb 2020 | BI15: ='Bridges for Trends'!A6 -> Mar 2020 | BJ15: ='Bridges for Trends'!A7 -> Apr 2020 | BK15: ='Bridges for Trends'!A8 -> May 2020 | BL15: ='Bridges for Trends'!A9 -> Jun 2020 | BM15: ='Bridges for Trends'!A10 -> Jul 2020 | BN15: ='Bridges for Trends'!A11 -> Aug 2020 | BO15: ='Bridges for Trends'!A12 -> Sep 2020 | BP15: ='Bridges for Trends'!A13 -> Oct 2020 | BQ15: ='Bridges for Trends'!A14 -> Nov 2020 | BR15: ='Bridges for Trends'!A15 -> Dec 2020
A16: =Summary!$C$2 -> 2020 | B16: =Mapping!$B$2 -> Actual | E16: =A16&" "&B16 -> 2020 Actual | F16: =SUMIFS('Sales Data'!$E:$E,'Sales Data'!$A:$A,$E$2,'Sales Data'!$B:$B,F$12&" "&$A16,'Sales Data'!$C:$C,"Periodic")/1000 -> 448.48043 | G16: =SUMIFS('Sales Data'!$E:$E,'Sales Data'!$A:$A,$E$2,'Sales Data'!$B:$B,G$12&" "&$A16,'Sales Data'!$C:$C,"Periodic")/1000 -> 404.02749 | H16: =SUMIFS('Sales Data'!$E:$E,'Sales Data'!$A:$A,$E$2,'Sales Data'!$B:$B,H$12&" "&$A16,'Sales Data'!$C:$C,"Periodic")/1000 -> 362.43555 | I16: =SUMIFS('Sales Data'!$E:$E,'Sales Data'!$A:$A,$E$2,'Sales Data'!$B:$B,I$12&" "&$A16,'Sales Data'!$C:$C,"Periodic")/1000 -> 309.66281 | J16: =SUMIFS('Sales Data'!$E:$E,'Sales Data'!$A:$A,$E$2,'Sales Data'!$B:$B,J$12&" "&$A16,'Sales Data'!$C:$C,"Periodic")/1000 -> 462.2603 | K16: =SUMIFS('Sales Data'!$E:$E,'Sales Data'!$A:$A,$E$2,'Sales Data'!$B:$B,K$12&" "&$A16,'Sales Data'!$C:$C,"Periodic")/1000 -> 484.91463 | L16: =SUMIFS('Sales Data'!$E:$E,'Sales Data'!$A:$A,$E$2,'Sales Data'!$B:$B,L$12&" "&$A16,'Sales Data'!$C:$C,"Periodic")/1000 -> 321.86195 | M16: =SUMIFS('Sales Data'!$E:$E,'Sales Data'!$A:$A,$E$2,'Sales Data'!$B:$B,M$12&" "&$A16,'Sales Data'!$C:$C,"Periodic")/1000 -> 0 | ... Q16: =SUMIFS('Sales Data'!$E:$E,'Sales Data'!$A:$A,$E$2,'Sales Data'!$B:$B,Q$12&" "&$A16,'Sales Data'!$C:$C,"Periodic")/1000 -> 0 | R16: =SUM(F16:Q16) -> 2793.6432 | AH16: Actual | AI16: =SUMIFS('Units sold'!$E:$E,'Units sold'!$A:$A,$E$2,'Units sold'!$B:$B,AI$15,'Units sold'!$C:$C,"Periodic") -> 188 | AJ16: =SUMIFS('Units sold'!$E:$E,'Units sold'!$A:$A,$E$2,'Units sold'!$B:$B,AJ$15,'Units sold'!$C:$C,"Periodic") -> 224 | AK16: =SUMIFS('Units sold'!$E:$E,'Units sold'!$A:$A,$E$2,'Units sold'!$B:$B,AK$15,'Units sold'!$C:$C,"Periodic") -> 328 | AL16: =SUMIFS('Units sold'!$E:$E,'Units sold'!$A:$A,$E$2,'Units sold'!$B:$B,AL$15,'Units sold'!$C:$C,"Periodic") -> 268 | AM16: =SUMIFS('Units sold'!$E:$E,'Units sold'!$A:$A,$E$2,'Units sold'!$B:$B,AM$15,'Units sold'!$C:$C,"Periodic") -> 340 | AN16: =SUMIFS('Units sold'!$E:$E,'Units sold'!$A:$A,$E$2,'Units sold'!$B:$B,AN$15,'Units sold'!$C:$C,"Periodic") -> 256 | AO16: =SUMIFS('Units sold'!$E:$E,'Units sold'!$A:$A,$E$2,'Units sold'!$B:$B,AO$15,'Units sold'!$C:$C,"Periodic") -> 256 | AP16: =SUMIFS('Units sold'!$E:$E,'Units sold'!$A:$A,$E$2,'Units sold'!$B:$B,AP$15,'Units sold'!$C:$C,"Periodic") -> 274 | ... BF16: =SUMIFS('Units sold'!$E:$E,'Units sold'!$A:$A,$E$2,'Units sold'!$B:$B,BF$15,'Units sold'!$C:$C,"Periodic") -> 366 | BG16: =IF(OR(BG$8=1,BG$9=0),SUMIFS('Units sold'!$E:$E,'Units sold'!$A:$A,$E$2,'Units sold'!$B:$B,BG$15,'Units sold'!$C:$C,"Periodic"),"") -> 396 | BH16: =IF(OR(BH$8=1,BH$9=0),SUMIFS('Units sold'!$E:$E,'Units sold'!$A:$A,$E$2,'Units sold'!$B:$B,BH$15,'Units sold'!$C:$C,"Periodic"),"") -> 356 | BI16: =IF(OR(BI$8=1,BI$9=0),SUMIFS('Units sold'!$E:$E,'Units sold'!$A:$A,$E$2,'Units sold'!$B:$B,BI$15,'Units sold'!$C:$C,"Periodic"),"") -> 414 | BJ16: =IF(OR(BJ$8=1,BJ$9=0),SUMIFS('Units sold'!$E:$E,'Units sold'!$A:$A,$E$2,'Units sold'!$B:$B,BJ$15,'Units sold'!$C:$C,"Periodic"),"") -> 326 | BK16: =IF(OR(BK$8=1,BK$9=0),SUMIFS('Units sold'!$E:$E,'Units sold'!$A:$A,$E$2,'Units sold'!$B:$B,BK$15,'Units sold'!$C:$C,"Periodic"),"") -> 366 | BL16: =IF(OR(BL$8=1,BL$9=0),SUMIFS('Units sold'!$E:$E,'Units sold'!$A:$A,$E$2,'Units sold'!$B:$B,BL$15,'Units sold'!$C:$C,"Periodic"),"") -> 442 | BM16: =IF(OR(BM$8=1,BM$9=0),SUMIFS('Units sold'!$E:$E,'Units sold'!$A:$A,$E$2,'Units sold'!$B:$B,BM$15,'Units sold'!$C:$C,"Periodic"),"") -> 396 | BN16: =IF(OR(BN$8=1,BN$9=0),SUMIFS('Units sold'!$E:$E,'Units sold'!$A:$A,$E$2,'Units sold'!$B:$B,BN$15,'Units sold'!$C:$C,"Periodic"),"") | ... BR16: =IF(OR(BR$8=1,BR$9=0),SUMIFS('Units sold'!$E:$E,'Units sold'!$A:$A,$E$2,'Units sold'!$B:$B,BR$15,'Units sold'!$C:$C,"Periodic"),"")
E17: Forecast | F17: =IF(F16<>0,F16,F15) -> 448.48043 | G17: =IF(G16<>0,G16,G15) -> 404.02749 | H17: =IF(H16<>0,H16,H15) -> 362.43555 | I17: =IF(I16<>0,I16,I15) -> 309.66281 | J17: =IF(J16<>0,J16,J15) -> 462.2603 | K17: =IF(K16<>0,K16,K15) -> 484.91463 | L17: =IF(L16<>0,L16,L15) -> 321.86195 | M17: =IF(M16<>0,M16,M15) -> 491.98578 | ... Q17: =IF(Q16<>0,Q16,Q15) -> 457.06834 | R17: =SUM(F17:Q17) -> 5216.0074 | T17: Units | U17: =AA17 -> Q1 | V17: =AB17 -> Q2 | W17: =AC17 -> Q3 | X17: =AD17 -> Q4 | Z17: Sales | AA17: Q1 | AB17: Q2 | AC17: Q3 | AD17: Q4 | AH17: Budget | BG17: =IF(OR(BG$8=1,BG$9=1),SUMIFS('Units sold'!$D:$D,'Units sold'!$A:$A,$E$2,'Units sold'!$B:$B,BG$15,'Units sold'!$C:$C,"Periodic"),"") | BH17: =IF(OR(BH$8=1,BH$9=1),SUMIFS('Units sold'!$D:$D,'Units sold'!$A:$A,$E$2,'Units sold'!$B:$B,BH$15,'Units sold'!$C:$C,"Periodic"),"") | BI17: =IF(OR(BI$8=1,BI$9=1),SUMIFS('Units sold'!$D:$D,'Units sold'!$A:$A,$E$2,'Units sold'!$B:$B,BI$15,'Units sold'!$C:$C,"Periodic"),"") | BJ17: =IF(OR(BJ$8=1,BJ$9=1),SUMIFS('Units sold'!$D:$D,'Units sold'!$A:$A,$E$2,'Units sold'!$B:$B,BJ$15,'Units sold'!$C:$C,"Periodic"),"") | BK17: =IF(OR(BK$8=1,BK$9=1),SUMIFS('Units sold'!$D:$D,'Units sold'!$A:$A,$E$2,'Units sold'!$B:$B,BK$15,'Units sold'!$C:$C,"Periodic"),"") | BL17: =IF(OR(BL$8=1,BL$9=1),SUMIFS('Units sold'!$D:$D,'Units sold'!$A:$A,$E$2,'Units sold'!$B:$B,BL$15,'Units sold'!$C:$C,"Periodic"),"") | BM17: =IF(OR(BM$8=1,BM$9=1),SUMIFS('Units sold'!$D:$D,'Units sold'!$A:$A,$E$2,'Units sold'!$B:$B,BM$15,'Units sold'!$C:$C,"Periodic"),"") -> 586.56549 | BN17: =IF(OR(BN$8=1,BN$9=1),SUMIFS('Units sold'!$D:$D,'Units sold'!$A:$A,$E$2,'Units sold'!$B:$B,BN$15,'Units sold'!$C:$C,"Periodic"),"") -> 610.84171 | ... BR17: =IF(OR(BR$8=1,BR$9=1),SUMIFS('Units sold'!$D:$D,'Units sold'!$A:$A,$E$2,'Units sold'!$B:$B,BR$15,'Units sold'!$C:$C,"Periodic"),"") -> 575.03394
T18: =E6 -> 2018 Actual | U18: =SUM(F6:H6) -> 740 | V18: =SUM(I6:K6) -> 864 | W18: =SUM(L6:N6) -> 870 | X18: =SUM(O6:Q6) -> 1146 | Z18: =+E13 -> 2018 Actual | AA18: =SUM(F13:H13) -> 1068.4078 | AB18: =SUM(I13:K13) -> 1182.2 | AC18: =SUM(L13:N13) -> 1217.746 | AD18: =SUM(O13:Q13) -> 1277.0525 | AH18: Trend 6m | BG18: =IF(BG$9,FORECAST(BG12,$AP16:BF16,$AP12:BF12), "") | BH18: =IF(BH$9,FORECAST(BH12,$AP16:BG16,$AP12:BG12), "") | BI18: =IF(BI$9,FORECAST(BI12,$AP16:BH16,$AP12:BH12), "") | BJ18: =IF(BJ$9,FORECAST(BJ12,$AP16:BI16,$AP12:BI12), "") | BK18: =IF(BK$9,FORECAST(BK12,$AP16:BJ16,$AP12:BJ12), "") | BL18: =IF(BL$9,FORECAST(BL12,$AP16:BK16,$AP12:BK12), "") | BM18: =IF(BM$9,FORECAST(BM12,$AP16:BL16,$AP12:BL12), "") | BN18: =IF(BN$9,FORECAST(BN12,$AP16:BM16,$AP12:BM12), "") -> 358.87273 | ... BR18: =IF(BR$9,FORECAST(BR12,$AP16:BQ16,$AP12:BQ12), "") -> 323.09091
E19: Average Price in kUSD | F19: =F$5 -> Jan | G19: =G$5 -> Feb | H19: =H$5 -> Mar | I19: =I$5 -> Apr | J19: =J$5 -> May | K19: =K$5 -> Jun | L19: =L$5 -> Jul | M19: =M$5 -> Aug | ... Q19: =Q$5 -> Dec | R19: FY | T19: =E7 -> 2019 Actual | U19: =SUM(F7:H7) -> 1012 | V19: =SUM(I7:K7) -> 1220 | W19: =SUM(L7:N7) -> 1216 | X19: =SUM(O7:Q7) -> 1430 | Z19: =+E14 -> 2019 Actual | AA19: =SUM(F14:H14) -> 1231.7749 | AB19: =SUM(I14:K14) -> 1614.5592 | AC19: =SUM(L14:N14) -> 1378.5434 | AD19: =SUM(O14:Q14) -> 1716.3799 | AH19: Trend 12m | BG19: =IF(BG$9,FORECAST(BG13,$AP16:BF16,$AP13:BF13), "") | BH19: =IF(BH$9,FORECAST(BH13,$AP16:BG16,$AP13:BG13), "") | BI19: =IF(BI$9,FORECAST(BI13,$AP16:BH16,$AP13:BH13), "") | BJ19: =IF(BJ$9,FORECAST(BJ13,$AP16:BI16,$AP13:BI13), "") | BK19: =IF(BK$9,FORECAST(BK13,$AP16:BJ16,$AP13:BJ13), "") | BL19: =IF(BL$9,FORECAST(BL13,$AP16:BK16,$AP13:BK13), "") | BM19: =IF(BM$9,FORECAST(BM13,$AP16:BL16,$AP13:BL13), "") | BN19: =IF(BN$9,FORECAST(BN13,$AP16:BM16,$AP13:BM13), "") -> 405.67647 | ... BR19: =IF(BR$9,FORECAST(BR13,$AP16:BQ16,$AP13:BQ13), "") -> 406.26471
E20: =+E13 -> 2018 Actual | F20: =IFERROR(F13/F6,"") -> 1.4823639 | G20: =IFERROR(G13/G6,"") -> 1.3957659 | H20: =IFERROR(H13/H6,"") -> 1.4544873 | I20: =IFERROR(I13/I6,"") -> 1.2464309 | J20: =IFERROR(J13/J6,"") -> 1.4592917 | K20: =IFERROR(K13/K6,"") -> 1.3749894 | L20: =IFERROR(L13/L6,"") -> 1.2876119 | M20: =IFERROR(M13/M6,"") -> 1.2655935 | ... R20: =IFERROR(R13/R6,"") -> 1.3108857 | T20: =E8 -> 2020 Budget | U20: =SUM(F8:H8) -> 1466.882 | V20: =SUM(I8:K8) -> 1752.7864 | W20: =SUM(L8:N8) -> 1746.6411 | X20: =SUM(O8:Q8) -> 1800.3445 | Z20: =+E15 -> 2020 Budget | AA20: =SUM(F15:H15) -> 1503.5918 | AB20: =SUM(I15:K15) -> 1560.3757 | AC20: =SUM(L15:N15) -> 1399.1934 | AD20: =SUM(O15:Q15) -> 1474.1785 | AH20: Budget | BG20: =SUMIFS('Units sold'!$D:$D,'Units sold'!$A:$A,$E$2,'Units sold'!$B:$B,BG$15,'Units sold'!$C:$C,"Periodic") -> 520.49613 | BH20: =SUMIFS('Units sold'!$D:$D,'Units sold'!$A:$A,$E$2,'Units sold'!$B:$B,BH$15,'Units sold'!$C:$C,"Periodic") -> 484.69531 | BI20: =SUMIFS('Units sold'!$D:$D,'Units sold'!$A:$A,$E$2,'Units sold'!$B:$B,BI$15,'Units sold'!$C:$C,"Periodic") -> 461.69058 | BJ20: =SUMIFS('Units sold'!$D:$D,'Units sold'!$A:$A,$E$2,'Units sold'!$B:$B,BJ$15,'Units sold'!$C:$C,"Periodic") -> 599.5068 | BK20: =SUMIFS('Units sold'!$D:$D,'Units sold'!$A:$A,$E$2,'Units sold'!$B:$B,BK$15,'Units sold'!$C:$C,"Periodic") -> 534.14345 | BL20: =SUMIFS('Units sold'!$D:$D,'Units sold'!$A:$A,$E$2,'Units sold'!$B:$B,BL$15,'Units sold'!$C:$C,"Periodic") -> 619.13611 | BM20: =SUMIFS('Units sold'!$D:$D,'Units sold'!$A:$A,$E$2,'Units sold'!$B:$B,BM$15,'Units sold'!$C:$C,"Periodic") -> 586.56549 | BN20: =SUMIFS('Units sold'!$D:$D,'Units sold'!$A:$A,$E$2,'Units sold'!$B:$B,BN$15,'Units sold'!$C:$C,"Periodic") -> 610.84171 | ... BR20: =SUMIFS('Units sold'!$D:$D,'Units sold'!$A:$A,$E$2,'Units sold'!$B:$B,BR$15,'Units sold'!$C:$C,"Periodic") -> 575.03394
E21: =+E14 -> 2019 Actual | F21: =IFERROR(F14/F7,"") -> 1.1981126 | G21: =IFERROR(G14/G7,"") -> 1.2903913 | H21: =IFERROR(H14/H7,"") -> 1.1640956 | I21: =IFERROR(I14/I7,"") -> 1.4526932 | J21: =IFERROR(J14/J7,"") -> 1.3237571 | K21: =IFERROR(K14/K7,"") -> 1.2080279 | L21: =IFERROR(L14/L7,"") -> 1.1377231 | M21: =IFERROR(M14/M7,"") -> 1.23413 | ... R21: =IFERROR(R14/R7,"") -> 1.21797 | T21: =E9 -> 2020 Actual | U21: =SUM(F9:H9) -> 1166 | V21: =SUM(I9:K9) -> 1134 | W21: =SUM(L9:N9) -> 396 | X21: =SUM(O9:Q9) -> 0 | Z21: =+E16 -> 2020 Actual | AA21: =SUM(F16:H16) -> 1214.9435 | AB21: =SUM(I16:K16) -> 1256.8377 | AC21: =SUM(L16:N16) -> 321.86195 | AD21: =SUM(O16:Q16) -> 0 | AH21: Forecast | BG21: =IF(OR(BG$8=1,BG$9=1),F10,"") | BH21: =IF(OR(BH$8=1,BH$9=1),G10,"") | BI21: =IF(OR(BI$8=1,BI$9=1),H10,"") | BJ21: =IF(OR(BJ$8=1,BJ$9=1),I10,"") | BK21: =IF(OR(BK$8=1,BK$9=1),J10,"") | BL21: =IF(OR(BL$8=1,BL$9=1),K10,"") | BM21: =IF(OR(BM$8=1,BM$9=1),L10,"") -> 396 | BN21: =IF(OR(BN$8=1,BN$9=1),M10,"") -> 474.78994 | ... BR21: =IF(OR(BR$8=1,BR$9=1),Q10,"") -> 441.09293
E22: =+E15 -> 2020 Budget | F22: =IFERROR(F15/F8,"") -> 0.98085869 | G22: =IFERROR(G15/G8,"") -> 1.0580245 | H22: =IFERROR(H15/H8,"") -> 1.0401754 | I22: =IFERROR(I15/I8,"") -> 0.87292973 | J22: =IFERROR(J15/J8,"") -> 0.95619676 | K22: =IFERROR(K15/K8,"") -> 0.8500588 | L22: =IFERROR(L15/L8,"") -> 0.76889562 | M22: =IFERROR(M15/M8,"") -> 0.8054227 | ... R22: =IFERROR(R15/R8,"") -> 0.87744095 | T22: Forecast | U22: =SUM(F10:H10) -> 1166 | V22: =SUM(I10:K10) -> 1134 | W22: =SUM(L10:N10) -> 1311.0448 | X22: =SUM(O10:Q10) -> 1422.6531 | Z22: Forecast | AA22: =SUM(F17:H17) -> 1214.9435 | AB22: =SUM(I17:K17) -> 1256.8377 | AC22: =SUM(L17:N17) -> 1270.0477 | AD22: =SUM(O17:Q17) -> 1474.1785 | AG22: Run rates | AH22: Trend 6m | BG22: =IF(BG18="",BG20,BG18) -> 520.49613 | BH22: =IF(BH18="",BH20,BH18) -> 484.69531 | BI22: =IF(BI18="",BI20,BI18) -> 461.69058 | BJ22: =IF(BJ18="",BJ20,BJ18) -> 599.5068 | BK22: =IF(BK18="",BK20,BK18) -> 534.14345 | BL22: =IF(BL18="",BL20,BL18) -> 619.13611 | BM22: =IF(BM18="",BM20,BM18) -> 586.56549 | BN22: =IF(BN18="",BN20,BN18) -> 358.87273 | ... BR22: =IF(BR18="",BR20,BR18) -> 323.09091 | BS22: =SUM(BG22:BR22) -> 5511.143
E23: =+E16 -> 2020 Actual | F23: =IFERROR(F16/F9,"") -> 1.1325263 | G23: =IFERROR(G16/G9,"") -> 1.1349087 | H23: =IFERROR(H16/H9,"") -> 0.8754482 | I23: =IFERROR(I16/I9,"") -> 0.94988592 | J23: =IFERROR(J16/J9,"") -> 1.2630063 | K23: =IFERROR(K16/K9,"") -> 1.0970919 | L23: =IFERROR(L16/L9,"") -> 0.8127827 | M23: =IFERROR(M16/M9,"") | ... R23: =IFERROR(R16/R9,"") -> 1.0362178 | AH23: Trend 12m | BG23: =IF(BG19="",BG20,BG19) -> 520.49613 | BH23: =IF(BH19="",BH20,BH19) -> 484.69531 | BI23: =IF(BI19="",BI20,BI19) -> 461.69058 | BJ23: =IF(BJ19="",BJ20,BJ19) -> 599.5068 | BK23: =IF(BK19="",BK20,BK19) -> 534.14345 | BL23: =IF(BL19="",BL20,BL19) -> 619.13611 | BM23: =IF(BM19="",BM20,BM19) -> 586.56549 | BN23: =IF(BN19="",BN20,BN19) -> 405.67647 | ... BR23: =IF(BR19="",BR20,BR19) -> 406.26471 | BS23: =SUM(BG23:BR23) -> 5836.0868
E24: =+E17 -> Forecast | F24: =IF(F23="",IFERROR(SUM(E17:$F17)/SUM(E10:$F10),""),F17/F10) -> 1.1325263 | G24: =IF(G23="",IFERROR(SUM(F17:$F17)/SUM(F10:$F10),""),G17/G10) -> 1.1349087 | H24: =IF(H23="",IFERROR(SUM($F17:G17)/SUM($F10:G10),""),H17/H10) -> 0.8754482 | I24: =IF(I23="",IFERROR(SUM($F17:H17)/SUM($F10:H10),""),I17/I10) -> 0.94988592 | J24: =IF(J23="",IFERROR(SUM($F17:I17)/SUM($F10:I10),""),J17/J10) -> 1.2630063 | K24: =IF(K23="",IFERROR(SUM($F17:J17)/SUM($F10:J10),""),K17/K10) -> 1.0970919 | L24: =IF(L23="",IFERROR(SUM($F17:K17)/SUM($F10:K10),""),L17/L10) -> 0.8127827 | M24: =IF(M23="",IFERROR(SUM($F17:L17)/SUM($F10:L10),""),M17/M10) -> 1.0362178 | N24: =IF(N23="",IFERROR(SUM($F17:M17)/SUM($F10:M10),""),N17/N10) -> 1.0362178 | O24: =IF(O23="",IFERROR(SUM($F17:N17)/SUM($F10:N10),""),O17/O10) -> 1.0362178 | ... Q24: =IF(Q23="",IFERROR(SUM($F17:P17)/SUM($F10:P10),""),Q17/Q10) -> 1.0362178 | R24: =IFERROR(R17/R10,"") -> 1.0362178 | T24: Quarter Actuals | U24: =AA24 -> Q1 | V24: =AB24 -> Q2 | W24: =AC24 -> Q3 | X24: =AD24 -> Q4 | Z24: Quarter Actuals | AA24: Q1 | AB24: Q2 | AC24: Q3 | AD24: Q4 | AG24: Trend Charts
T25: ="vs "&$A$6 -> vs 2018 | U25: =IFERROR(U$21/U18-1,"") -> 0.57567568 | V25: =IFERROR(V$21/V18-1,"") -> 0.3125 | W25: =IFERROR(W$21/W18-1,"") -> -0.54482759 | X25: =IFERROR(X$21/X18-1,"") -> -1 | Z25: ="vs "&$A$6 -> vs 2018 | AA25: =IFERROR(AA$21/AA18-1,"") -> 0.13715329 | AB25: =IFERROR(AB$21/AB18-1,"") -> 0.063134653 | AC25: =IFERROR(AC$21/AC18-1,"") -> -0.73569041 | AD25: =IFERROR(AD$21/AD18-1,"") -> -1 | AH25: =AH16 -> Actual | AU25: =IF(AU16="",NA(),AU16) -> 376 | AV25: =IF(AV16="",NA(),AV16) -> 324 | AW25: =IF(AW16="",NA(),AW16) -> 312 | AX25: =IF(AX16="",NA(),AX16) -> 406 | AY25: =IF(AY16="",NA(),AY16) -> 358 | AZ25: =IF(AZ16="",NA(),AZ16) -> 456 | BA25: =IF(BA16="",NA(),BA16) -> 392 | BB25: =IF(BB16="",NA(),BB16) -> 412 | ... BR25: =IF(BR16="",NA(),BR16) -> #N/A
T26: ="vs "&$A$7 -> vs 2019 | U26: =IFERROR(U$21/U19-1,"") -> 0.15217391 | V26: =IFERROR(V$21/V19-1,"") -> -0.070491803 | W26: =IFERROR(W$21/W19-1,"") -> -0.67434211 | X26: =IFERROR(X$21/X19-1,"") -> -1 | Z26: ="vs "&$A$7 -> vs 2019 | AA26: =IFERROR(AA$21/AA19-1,"") -> -0.0136644 | AB26: =IFERROR(AB$21/AB19-1,"") -> -0.22155983 | AC26: =IFERROR(AC$21/AC19-1,"") -> -0.76652027 | AD26: =IFERROR(AD$21/AD19-1,"") -> -1 | AH26: =AH20 -> Budget | AU26: =IF(AU17="",NA(),AU17) -> #N/A | AV26: =IF(AV17="",NA(),AV17) -> #N/A | AW26: =IF(AW17="",NA(),AW17) -> #N/A | AX26: =IF(AX17="",NA(),AX17) -> #N/A | AY26: =IF(AY17="",NA(),AY17) -> #N/A | AZ26: =IF(AZ17="",NA(),AZ17) -> #N/A | BA26: =IF(BA17="",NA(),BA17) -> #N/A | BB26: =IF(BB17="",NA(),BB17) -> #N/A | ... BR26: =IF(BR17="",NA(),BR17) -> 575.03394
T27: ="Forecast "&"vs. "&$A$7 -> Forecast vs. 2019 | U27: =IFERROR(U22/U19-1,"") -> 0.15217391 | V27: =IFERROR(V22/V19-1,"") -> -0.070491803 | W27: =IFERROR(W22/W19-1,"") -> 0.078161854 | X27: =IFERROR(X22/X19-1,"") -> -0.0051376704 | Z27: ="Forecast "&"vs. "&$A$7 -> Forecast vs. 2019 | AA27: =IFERROR(AA22/AA19-1,"") -> -0.0136644 | AB27: =IFERROR(AB22/AB19-1,"") -> -0.22155983 | AC27: =IFERROR(AC22/AC19-1,"") -> -0.078703183 | AD27: =IFERROR(AD22/AD19-1,"") -> -0.14111177 | AH27: =AH18 -> Trend 6m | AU27: =IF(AU18="",NA(),AU18) -> #N/A | AV27: =IF(AV18="",NA(),AV18) -> #N/A | AW27: =IF(AW18="",NA(),AW18) -> #N/A | AX27: =IF(AX18="",NA(),AX18) -> #N/A | AY27: =IF(AY18="",NA(),AY18) -> #N/A | AZ27: =IF(AZ18="",NA(),AZ18) -> #N/A | BA27: =IF(BA18="",NA(),BA18) -> #N/A | BB27: =IF(BB18="",NA(),BB18) -> #N/A | ... BR27: =IF(BR18="",NA(),BR18) -> 323.09091
AH28: =AH19 -> Trend 12m | AU28: =IF(AU19="",NA(),AU19) -> #N/A | AV28: =IF(AV19="",NA(),AV19) -> #N/A | AW28: =IF(AW19="",NA(),AW19) -> #N/A | AX28: =IF(AX19="",NA(),AX19) -> #N/A | AY28: =IF(AY19="",NA(),AY19) -> #N/A | AZ28: =IF(AZ19="",NA(),AZ19) -> #N/A | BA28: =IF(BA19="",NA(),BA19) -> #N/A | BB28: =IF(BB19="",NA(),BB19) -> #N/A | ... BR28: =IF(BR19="",NA(),BR19) -> 406.26471
T29: Quarter Actuals | U29: =AA29 -> Q1 | V29: =AB29 -> Q2 | W29: =AC29 -> Q3 | X29: =AD29 -> Q4 | Z29: Quarter Actuals | AA29: Q1 | AB29: Q2 | AC29: Q3 | AD29: Q4 | AH29: Forecast | AU29: =IF(AU21="",NA(),AU21) -> #N/A | AV29: =IF(AV21="",NA(),AV21) -> #N/A | AW29: =IF(AW21="",NA(),AW21) -> #N/A | AX29: =IF(AX21="",NA(),AX21) -> #N/A | AY29: =IF(AY21="",NA(),AY21) -> #N/A | AZ29: =IF(AZ21="",NA(),AZ21) -> #N/A | BA29: =IF(BA21="",NA(),BA21) -> #N/A | BB29: =IF(BB21="",NA(),BB21) -> #N/A | ... BR29: =IF(BR21="",NA(),BR21) -> 441.09293
T30: =T25 -> vs 2018 | U30: =U$21-U18 -> 426 | V30: =V$21-V18 -> 270 | W30: =W$21-W18 -> -474 | X30: =X$21-X18 -> -1146 | Z30: =Z25 -> vs 2018 | AA30: =AA$21-AA18 -> 146.53565 | AB30: =AB$21-AB18 -> 74.637784 | AC30: =AC$21-AC18 -> -895.88408 | AD30: =AD$21-AD18 -> -1277.0525
T31: =T26 -> vs 2019 | U31: =U$21-U19 -> 154 | V31: =V$21-V19 -> -86 | W31: =W$21-W19 -> -820 | X31: =X$21-X19 -> -1430 | Z31: =Z26 -> vs 2019 | AA31: =AA$21-AA19 -> -16.831466 | AB31: =AB$21-AB19 -> -357.72145 | AC31: =AC$21-AC19 -> -1056.6815 | AD31: =AD$21-AD19 -> -1716.3799
T32: ="Forecast "&"vs. "&$A$7 -> Forecast vs. 2019 | U32: =U22-U19 -> 154 | V32: =V22-V19 -> -86 | W32: =W22-W19 -> 95.044815 | X32: =X22-X19 -> -7.3468687 | Z32: ="Forecast "&"vs. "&$A$7 -> Forecast vs. 2019 | AA32: =AA22-AA19 -> -16.831466 | AB32: =AB22-AB19 -> -357.72145 | AC32: =AC22-AC19 -> -108.49576 | AD32: =AD22-AD19 -> -242.20141
AG33: Sales
T34: QoQ GR% | U34: =AA34 -> Q1 | V34: =AB34 -> Q2 | W34: =AC34 -> Q3 | X34: =AD34 -> Q4 | Z34: QoQ GR% | AA34: Q1 | AB34: Q2 | AC34: Q3 | AD34: Q4 | AG34: Trend Calculation | AH34: Actual | AI34: =SUMIFS('Sales Data'!$E:$E,'Sales Data'!$A:$A,$E$2,'Sales Data'!$B:$B,AI$15,'Sales Data'!$C:$C,"Periodic")/1000 -> 278.68442 | AJ34: =SUMIFS('Sales Data'!$E:$E,'Sales Data'!$A:$A,$E$2,'Sales Data'!$B:$B,AJ$15,'Sales Data'!$C:$C,"Periodic")/1000 -> 312.65156 | AK34: =SUMIFS('Sales Data'!$E:$E,'Sales Data'!$A:$A,$E$2,'Sales Data'!$B:$B,AK$15,'Sales Data'!$C:$C,"Periodic")/1000 -> 477.07185 | AL34: =SUMIFS('Sales Data'!$E:$E,'Sales Data'!$A:$A,$E$2,'Sales Data'!$B:$B,AL$15,'Sales Data'!$C:$C,"Periodic")/1000 -> 334.04349 | AM34: =SUMIFS('Sales Data'!$E:$E,'Sales Data'!$A:$A,$E$2,'Sales Data'!$B:$B,AM$15,'Sales Data'!$C:$C,"Periodic")/1000 -> 496.15918 | AN34: =SUMIFS('Sales Data'!$E:$E,'Sales Data'!$A:$A,$E$2,'Sales Data'!$B:$B,AN$15,'Sales Data'!$C:$C,"Periodic")/1000 -> 351.99729 | AO34: =SUMIFS('Sales Data'!$E:$E,'Sales Data'!$A:$A,$E$2,'Sales Data'!$B:$B,AO$15,'Sales Data'!$C:$C,"Periodic")/1000 -> 329.62864 | AP34: =SUMIFS('Sales Data'!$E:$E,'Sales Data'!$A:$A,$E$2,'Sales Data'!$B:$B,AP$15,'Sales Data'!$C:$C,"Periodic")/1000 -> 346.77263 | ... BF34: =SUMIFS('Sales Data'!$E:$E,'Sales Data'!$A:$A,$E$2,'Sales Data'!$B:$B,BF$15,'Sales Data'!$C:$C,"Periodic")/1000 -> 383.17004 | BG34: =IF(OR(BG$8=1,BG$9=0),SUMIFS('Sales Data'!$E:$E,'Sales Data'!$A:$A,$E$2,'Sales Data'!$B:$B,BG$15,'Sales Data'!$C:$C,"Periodic")/1000,"") -> 448.48043 | BH34: =IF(OR(BH$8=1,BH$9=0),SUMIFS('Sales Data'!$E:$E,'Sales Data'!$A:$A,$E$2,'Sales Data'!$B:$B,BH$15,'Sales Data'!$C:$C,"Periodic")/1000,"") -> 404.02749 | BI34: =IF(OR(BI$8=1,BI$9=0),SUMIFS('Sales Data'!$E:$E,'Sales Data'!$A:$A,$E$2,'Sales Data'!$B:$B,BI$15,'Sales Data'!$C:$C,"Periodic")/1000,"") -> 362.43555 | BJ34: =IF(OR(BJ$8=1,BJ$9=0),SUMIFS('Sales Data'!$E:$E,'Sales Data'!$A:$A,$E$2,'Sales Data'!$B:$B,BJ$15,'Sales Data'!$C:$C,"Periodic")/1000,"") -> 309.66281 | BK34: =IF(OR(BK$8=1,BK$9=0),SUMIFS('Sales Data'!$E:$E,'Sales Data'!$A:$A,$E$2,'Sales Data'!$B:$B,BK$15,'Sales Data'!$C:$C,"Periodic")/1000,"") -> 462.2603 | BL34: =IF(OR(BL$8=1,BL$9=0),SUMIFS('Sales Data'!$E:$E,'Sales Data'!$A:$A,$E$2,'Sales Data'!$B:$B,BL$15,'Sales Data'!$C:$C,"Periodic")/1000,"") -> 484.91463 | BM34: =IF(OR(BM$8=1,BM$9=0),SUMIFS('Sales Data'!$E:$E,'Sales Data'!$A:$A,$E$2,'Sales Data'!$B:$B,BM$15,'Sales Data'!$C:$C,"Periodic")/1000,"") -> 321.86195 | BN34: =IF(OR(BN$8=1,BN$9=0),SUMIFS('Sales Data'!$E:$E,'Sales Data'!$A:$A,$E$2,'Sales Data'!$B:$B,BN$15,'Sales Data'!$C:$C,"Periodic")/1000,"") | ... BR34: =IF(OR(BR$8=1,BR$9=0),SUMIFS('Sales Data'!$E:$E,'Sales Data'!$A:$A,$E$2,'Sales Data'!$B:$B,BR$15,'Sales Data'!$C:$C,"Periodic")/1000,"")
T35: =+T19 -> 2019 Actual | U35: =IFERROR(U19/X18-1,"") -> -0.11692845 | V35: =IFERROR(V19/U19-1,"") -> 0.2055336 | W35: =IFERROR(W19/V19-1,"") -> -0.0032786885 | X35: =IFERROR(X19/W19-1,"") -> 0.17598684 | Z35: =+Z19 -> 2019 Actual | AA35: =IFERROR(AA19/AD18-1,"") -> -0.035454733 | AB35: =IFERROR(AB19/AA19-1,"") -> 0.31075827 | AC35: =IFERROR(AC19/AB19-1,"") -> -0.14617969 | AD35: =IFERROR(AD19/AC19-1,"") -> 0.24506771 | AH35: Budget | BG35: =IF(OR(BG$8=1,BG$9=1),SUMIFS('Sales Data'!$D:$D,'Sales Data'!$A:$A,$E$2,'Sales Data'!$B:$B,BG$15,'Sales Data'!$C:$C,"Periodic")/1000,"") | BH35: =IF(OR(BH$8=1,BH$9=1),SUMIFS('Sales Data'!$D:$D,'Sales Data'!$A:$A,$E$2,'Sales Data'!$B:$B,BH$15,'Sales Data'!$C:$C,"Periodic")/1000,"") | BI35: =IF(OR(BI$8=1,BI$9=1),SUMIFS('Sales Data'!$D:$D,'Sales Data'!$A:$A,$E$2,'Sales Data'!$B:$B,BI$15,'Sales Data'!$C:$C,"Periodic")/1000,"") | BJ35: =IF(OR(BJ$8=1,BJ$9=1),SUMIFS('Sales Data'!$D:$D,'Sales Data'!$A:$A,$E$2,'Sales Data'!$B:$B,BJ$15,'Sales Data'!$C:$C,"Periodic")/1000,"") | BK35: =IF(OR(BK$8=1,BK$9=1),SUMIFS('Sales Data'!$D:$D,'Sales Data'!$A:$A,$E$2,'Sales Data'!$B:$B,BK$15,'Sales Data'!$C:$C,"Periodic")/1000,"") | BL35: =IF(OR(BL$8=1,BL$9=1),SUMIFS('Sales Data'!$D:$D,'Sales Data'!$A:$A,$E$2,'Sales Data'!$B:$B,BL$15,'Sales Data'!$C:$C,"Periodic")/1000,"") | BM35: =IF(OR(BM$8=1,BM$9=1),SUMIFS('Sales Data'!$D:$D,'Sales Data'!$A:$A,$E$2,'Sales Data'!$B:$B,BM$15,'Sales Data'!$C:$C,"Periodic")/1000,"") -> 451.00764 | BN35: =IF(OR(BN$8=1,BN$9=1),SUMIFS('Sales Data'!$D:$D,'Sales Data'!$A:$A,$E$2,'Sales Data'!$B:$B,BN$15,'Sales Data'!$C:$C,"Periodic")/1000,"") -> 491.98578 | ... BR35: =IF(OR(BR$8=1,BR$9=1),SUMIFS('Sales Data'!$D:$D,'Sales Data'!$A:$A,$E$2,'Sales Data'!$B:$B,BR$15,'Sales Data'!$C:$C,"Periodic")/1000,"") -> 457.06834
T36: =+T20 -> 2020 Budget | U36: =IFERROR(U20/X19-1,"") -> 0.025791626 | V36: =IFERROR(V20/U20-1,"") -> 0.19490616 | W36: =IFERROR(W20/V20-1,"") -> -0.0035059936 | X36: =IFERROR(X20/W20-1,"") -> 0.030746687 | Z36: =+Z20 -> 2020 Budget | AA36: =IFERROR(AA20/AD19-1,"") -> -0.12397491 | AB36: =IFERROR(AB20/AA20-1,"") -> 0.037765437 | AC36: =IFERROR(AC20/AB20-1,"") -> -0.10329711 | AD36: =IFERROR(AD20/AC20-1,"") -> 0.053591683 | AH36: Trend 6m | BG36: =IF(BG$9,FORECAST(BG$12,$AP34:BF34,$AP12:BF12), "") | BH36: =IF(BH$9,FORECAST(BH$12,$AP34:BG34,$AP12:BG12), "") | BI36: =IF(BI$9,FORECAST(BI$12,$AP34:BH34,$AP12:BH12), "") | BJ36: =IF(BJ$9,FORECAST(BJ$12,$AP34:BI34,$AP12:BI12), "") | BK36: =IF(BK$9,FORECAST(BK$12,$AP34:BJ34,$AP12:BJ12), "") | BL36: =IF(BL$9,FORECAST(BL$12,$AP34:BK34,$AP12:BK12), "") | BM36: =IF(BM$9,FORECAST(BM$12,$AP34:BL34,$AP12:BL12), "") | BN36: =IF(BN$9,FORECAST(BN$12,$AP34:BM34,$AP12:BM12), "") -> 336.70608 | ... BR36: =IF(BR$9,FORECAST(BR$12,$AP34:BQ34,$AP12:BQ12), "") -> 262.13938
T37: =+T21 -> 2020 Actual | U37: =IF(U21<>0,IFERROR(U21/X19-1,""),"") -> -0.18461538 | V37: =IF(V21<>0,IFERROR(V21/U21-1,""),"") -> -0.027444254 | W37: =IF(W21<>0,IFERROR(W21/V21-1,""),"") -> -0.65079365 | X37: =IF(X21<>0,IFERROR(X21/W21-1,""),"") | Z37: =+Z21 -> 2020 Actual | AA37: =IF(AA21<>0,IFERROR(AA21/AD19-1,""),"") -> -0.29214769 | AB37: =IF(AB21<>0,IFERROR(AB21/AA21-1,""),"") -> 0.034482477 | AC37: =IF(AC21<>0,IFERROR(AC21/AB21-1,""),"") -> -0.74391129 | AD37: =IF(AD21<>0,IFERROR(AD21/AC21-1,""),"") | AH37: Trend 12m | BG37: =IF(BG$9,FORECAST(BG$13,$AP34:BF34,$AP13:BF13), "") | BH37: =IF(BH$9,FORECAST(BH$13,$AP34:BG34,$AP13:BG13), "") | BI37: =IF(BI$9,FORECAST(BI$13,$AP34:BH34,$AP13:BH13), "") | BJ37: =IF(BJ$9,FORECAST(BJ$13,$AP34:BI34,$AP13:BI13), "") | BK37: =IF(BK$9,FORECAST(BK$13,$AP34:BJ34,$AP13:BJ13), "") | BL37: =IF(BL$9,FORECAST(BL$13,$AP34:BK34,$AP13:BK13), "") | BM37: =IF(BM$9,FORECAST(BM$13,$AP34:BL34,$AP13:BL13), "") | BN37: =IF(BN$9,FORECAST(BN$13,$AP34:BM34,$AP13:BM13), "") -> 392.36969 | ... BR37: =IF(BR$9,FORECAST(BR$13,$AP34:BQ34,$AP13:BQ13), "") -> 361.1007
T38: Forecast | U38: =IFERROR(U22/X19-1,"") -> -0.18461538 | V38: =IFERROR(V22/U22-1,"") -> -0.027444254 | W38: =IFERROR(W22/V22-1,"") -> 0.15612418 | X38: =IFERROR(X22/W22-1,"") -> 0.085129292 | Z38: Forecast | AA38: =IFERROR(AA22/AD19-1,"") -> -0.29214769 | AB38: =IFERROR(AB22/AA22-1,"") -> 0.034482477 | AC38: =IFERROR(AC22/AB22-1,"") -> 0.010510449 | AD38: =IFERROR(AD22/AC22-1,"") -> 0.1607269 | AH38: Budget | BG38: =SUMIFS('Sales Data'!$D:$D,'Sales Data'!$A:$A,$E$2,'Sales Data'!$B:$B,BG$15,'Sales Data'!$C:$C,"Periodic")/1000 -> 510.53316 | BH38: =SUMIFS('Sales Data'!$D:$D,'Sales Data'!$A:$A,$E$2,'Sales Data'!$B:$B,BH$15,'Sales Data'!$C:$C,"Periodic")/1000 -> 512.81953 | BI38: =SUMIFS('Sales Data'!$D:$D,'Sales Data'!$A:$A,$E$2,'Sales Data'!$B:$B,BI$15,'Sales Data'!$C:$C,"Periodic")/1000 -> 480.23917 | BJ38: =SUMIFS('Sales Data'!$D:$D,'Sales Data'!$A:$A,$E$2,'Sales Data'!$B:$B,BJ$15,'Sales Data'!$C:$C,"Periodic")/1000 -> 523.32732 | BK38: =SUMIFS('Sales Data'!$D:$D,'Sales Data'!$A:$A,$E$2,'Sales Data'!$B:$B,BK$15,'Sales Data'!$C:$C,"Periodic")/1000 -> 510.74624 | BL38: =SUMIFS('Sales Data'!$D:$D,'Sales Data'!$A:$A,$E$2,'Sales Data'!$B:$B,BL$15,'Sales Data'!$C:$C,"Periodic")/1000 -> 526.3021 | BM38: =SUMIFS('Sales Data'!$D:$D,'Sales Data'!$A:$A,$E$2,'Sales Data'!$B:$B,BM$15,'Sales Data'!$C:$C,"Periodic")/1000 -> 451.00764 | BN38: =SUMIFS('Sales Data'!$D:$D,'Sales Data'!$A:$A,$E$2,'Sales Data'!$B:$B,BN$15,'Sales Data'!$C:$C,"Periodic")/1000 -> 491.98578 | ... BR38: =SUMIFS('Sales Data'!$D:$D,'Sales Data'!$A:$A,$E$2,'Sales Data'!$B:$B,BR$15,'Sales Data'!$C:$C,"Periodic")/1000 -> 457.06834
AH39: Forecast | BG39: =IF(OR(BG$8=1,BG$9=1),F17,"") | BH39: =IF(OR(BH$8=1,BH$9=1),G17,"") | BI39: =IF(OR(BI$8=1,BI$9=1),H17,"") | BJ39: =IF(OR(BJ$8=1,BJ$9=1),I17,"") | BK39: =IF(OR(BK$8=1,BK$9=1),J17,"") | BL39: =IF(OR(BL$8=1,BL$9=1),K17,"") | BM39: =IF(OR(BM$8=1,BM$9=1),L17,"") -> 321.86195 | BN39: =IF(OR(BN$8=1,BN$9=1),M17,"") -> 491.98578 | ... BR39: =IF(OR(BR$8=1,BR$9=1),Q17,"") -> 457.06834
AH40: Trend 6m | BG40: =IF(BG36="",BG38,BG36) -> 510.53316 | BH40: =IF(BH36="",BH38,BH36) -> 512.81953 | BI40: =IF(BI36="",BI38,BI36) -> 480.23917 | BJ40: =IF(BJ36="",BJ38,BJ36) -> 523.32732 | BK40: =IF(BK36="",BK38,BK36) -> 510.74624 | BL40: =IF(BL36="",BL38,BL36) -> 526.3021 | BM40: =IF(BM36="",BM38,BM36) -> 451.00764 | BN40: =IF(BN36="",BN38,BN36) -> 336.70608 | ... BR40: =IF(BR36="",BR38,BR36) -> 262.13938 | BS40: =SUM(BG40:BR40) -> 5012.0888
AG41: Run rates | AH41: Trend 12m | BG41: =IF(BG37="",BG38,BG37) -> 510.53316 | BH41: =IF(BH37="",BH38,BH37) -> 512.81953 | BI41: =IF(BI37="",BI38,BI37) -> 480.23917 | BJ41: =IF(BJ37="",BJ38,BJ37) -> 523.32732 | BK41: =IF(BK37="",BK38,BK37) -> 510.74624 | BL41: =IF(BL37="",BL38,BL37) -> 526.3021 | BM41: =IF(BM37="",BM38,BM37) -> 451.00764 | BN41: =IF(BN37="",BN38,BN37) -> 392.36969 | ... BR41: =IF(BR37="",BR38,BR37) -> 361.1007 | BS41: =SUM(BG41:BR41) -> 5398.6511
AG43: Trend Charts | AH43: =AH34 -> Actual | AU43: =IF(AU34="",NA(),AU34) -> 450.49035 | AV43: =IF(AV34="",NA(),AV34) -> 418.08677 | AW43: =IF(AW34="",NA(),AW34) -> 363.19783 | AX43: =IF(AX34="",NA(),AX34) -> 589.79345 | AY43: =IF(AY34="",NA(),AY34) -> 473.90504 | AZ43: =IF(AZ34="",NA(),AZ34) -> 550.8607 | BA43: =IF(BA34="",NA(),BA34) -> 445.98746 | BB43: =IF(BB34="",NA(),BB34) -> 508.46155 | ... BR43: =IF(BR34="",NA(),BR34) -> #N/A
AH44: =AH38 -> Budget | AU44: =IF(AU35="",NA(),AU35) -> #N/A | AV44: =IF(AV35="",NA(),AV35) -> #N/A | AW44: =IF(AW35="",NA(),AW35) -> #N/A | AX44: =IF(AX35="",NA(),AX35) -> #N/A | AY44: =IF(AY35="",NA(),AY35) -> #N/A | AZ44: =IF(AZ35="",NA(),AZ35) -> #N/A | BA44: =IF(BA35="",NA(),BA35) -> #N/A | BB44: =IF(BB35="",NA(),BB35) -> #N/A | ... BR44: =IF(BR35="",NA(),BR35) -> 457.06834
AH45: =AH36 -> Trend 6m | AU45: =IF(AU36="",NA(),AU36) -> #N/A | AV45: =IF(AV36="",NA(),AV36) -> #N/A | AW45: =IF(AW36="",NA(),AW36) -> #N/A | AX45: =IF(AX36="",NA(),AX36) -> #N/A | AY45: =IF(AY36="",NA(),AY36) -> #N/A | AZ45: =IF(AZ36="",NA(),AZ36) -> #N/A | BA45: =IF(BA36="",NA(),BA36) -> #N/A | BB45: =IF(BB36="",NA(),BB36) -> #N/A | ... BR45: =IF(BR36="",NA(),BR36) -> 262.13938
AH46: =AH37 -> Trend 12m | AU46: =IF(AU37="",NA(),AU37) -> #N/A | AV46: =IF(AV37="",NA(),AV37) -> #N/A | AW46: =IF(AW37="",NA(),AW37) -> #N/A | AX46: =IF(AX37="",NA(),AX37) -> #N/A | AY46: =IF(AY37="",NA(),AY37) -> #N/A | AZ46: =IF(AZ37="",NA(),AZ37) -> #N/A | BA46: =IF(BA37="",NA(),BA37) -> #N/A | BB46: =IF(BB37="",NA(),BB37) -> #N/A | ... BR46: =IF(BR37="",NA(),BR37) -> 361.1007
AH47: Forecast | AU47: =IF(AU39="",NA(),AU39) -> #N/A | AV47: =IF(AV39="",NA(),AV39) -> #N/A | AW47: =IF(AW39="",NA(),AW39) -> #N/A | AX47: =IF(AX39="",NA(),AX39) -> #N/A | AY47: =IF(AY39="",NA(),AY39) -> #N/A | AZ47: =IF(AZ39="",NA(),AZ39) -> #N/A | BA47: =IF(BA39="",NA(),BA39) -> #N/A | BB47: =IF(BB39="",NA(),BB39) -> #N/A | ... BR47: =IF(BR39="",NA(),BR39) -> 457.06834

Sheet Kitchen
E2: Kitchen
T4: Units | Z4: Sales in kUSD | BF4: Current month | BG4: Prior month
E5: Units | F5: =Mapping!$D$2 -> Jan | G5: =Mapping!$D$3 -> Feb | H5: =Mapping!$D$4 -> Mar | I5: =Mapping!$D$5 -> Apr | J5: =Mapping!$D$6 -> May | K5: =Mapping!$D$7 -> Jun | L5: =Mapping!$D$8 -> Jul | M5: =Mapping!$D$9 -> Aug | N5: =Mapping!$D$10 -> Sep | O5: =Mapping!$D$11 -> Oct | P5: =Mapping!$D$12 -> Nov | Q5: =Mapping!$D$13 -> Dec | R5: FY | T5: =Z5 -> Forecast based on: | W5: =AC5 -> FY | X5: =AD5 -> vs. LO | Z5: Forecast based on: | AC5: FY | AD5: vs. LO | BF5: =Summary!$D$3 -> 7 | BG5: =BF5-1 -> 6
